Workbook

Sheet Gráfico1

Sheet CONTROL DE RENTAS
AP1: T.C. | AQ1: 19.7567
N3: MODIFICAR | O3: MODIFICAR | P3: MODIFICAR | Q3: MODIFICAR | R3: MODIFICAR | S3: MODIFICAR | T3: MODIFICAR | U3: MODIFICAR | W3: MODIFICAR | X3: MODIFICAR | Y3: NO MOVER | Z3: NO MOVER | AA3: NO MOVER | AB3: NO MOVER | AC3: NO MOVER | AE3: NO MOVER | AG3: =Y3 -> NO MOVER | AH3: NO MOVER | AI3: NO MOVER | AJ3: NO MOVER | AK3: NO MOVER | AN3: NO MOVER | AO3: NO MOVER | AP3: NO MOVER | AQ3: NO MOVER | AS3: NO MOVER | AT3: MODIFICAR | AU3: MODIFICAR | AW3: MODIFICAR | BC3: MODIFICAR | BM3: CONTROL DE SEGURO POR EQUIPO | BT3: CONTROL DE SUBRENTA
A4: N.E. | B4: ENERO | C4: FEBRERO | D4: MARZO | E4: ABRIL | F4: MAYO | G4: JUNIO | H4: JULIO | I4: AGOSTO | J4: SEPTIEMBRE | K4: OCTUBRE | L4: NOVIEMBRE | M4: DICIEMBRE | N4: COMENTARIOS | O4: DENTRO O FUERA | P4: CONTRATO | Q4: CLIENTE | R4: COMPRADOR | S4: OBRA | T4: HORAS | U4: VENDEDOR | V4: SUMA | W4: FECHA INICIO DE PERIODO | X4: DIAS CONTRATADO | Y4: NUMERO DE EQUIPO | Z4: FECHA DE VENCIMIENTO | AA4: BALANCE POR FECHA | AB4: DIAS TRANSCURRIDOS | AC4: TIPO DE NEGOCIO | AD4: ASEGURADO | AE4: PROVEEDOR | AF4: 0 | AG4: NUMERO DE EQUIPO 2 | AH4: DESCRIPCION DEL EQUIPO | AI4: MARCA | AJ4: MODELO | AK4: NUMERO DE SERIE | AL4: CATEGORIA | AM4: CLASE | AN4: AÑO | AO4: PRECIO DE LISTA | AP4: PRECIO REAL AL CLIENTE | AQ4: COSTO PROVEEDOR (USD) | AR4: COSTO PROVEEDOR (MXN) | AS4: Ganancia | AT4: TIPO RENTA | AU4: INICIO DE RENTA | AV4: REGRESO DE EQUIPO | AW4: COMENTARIOS | AX4: CIUDAD | AY4: UBICACIÓN | AZ4: CONTACTO | BA4: TELEFONO | BB4: Columna3 | BC4: Columna4 | BD4: Columna5 | BE4: Columna6 | BF4: Columna7 | BG4: Columna8 | BH4: Columna9 | BI4: Columna10 | BJ4: Columna11 | BK4: Columna12 | BL4: Columna13 | BM4: Columna14 | BN4: Columna15 | BO4: Columna16 | BP4: Columna17 | BQ4: Columna18 | BR4: Columna19 | BS4: Columna20 | BT4: Columna21 | BU4: Columna22 | BV4: Columna23 | BW4: Columna24 | BX4: Columna25 | BY4: Columna26 | BZ4: DIAS | CA4: ESTATUS DE VENCIMIENTO
A5: 1 | B5: 2022-2105-2178 | F5: 2730 | I5: 3141 | J5: 3429 | K5: 3498-3607 | O5: DENTRO | P5: 5855 | Q5: MTP MANTENIMIENTO | R5: MTP MANTENIMIENTO | S5: SAISA | T5: 1922 | U5: CARLOS | V5: 1 | W5: 45957 | X5: 6 | Y5: 1 | Z5: =W5+X5 -> 45963 | AA5: =TODAY() -> 45957 | AB5: =AA5-W5 -> 0 | AC5: COMYMAQ | AD5: COMYMAQ | AE5: SEGAMAC | AF5: ELECTRICA | AG5: 1 | AH5: PLATAFORMA ARTICULADA ELECTRICA | AI5: GENIE | AJ5: Z33/18 | AK5: Z331816M-918 | AL5: 10 | AM5: 03 | AN5: 2016 | AT5: DIRECTA | AU5: 45929
A6: 2 | B6: 2022-2105-2178 | I6: 3205-3265 | J6: 3265-3432 | O6: DENTRO | P6: 5780 | Q6: ALEJANDRO RUBIO FLORES | R6: ALEJANDRO RUBIO FLORES | S6: PARQUE INDUSTRIAL ORADEL | T6: 530 | U6: CARLOS | V6: 1 | W6: 45927 | X6: 27 | Y6: 2 | Z6: =W6+X6 -> 45954 | AA6: =TODAY() -> 45957 | AB6: =AA6-W6 -> 30 | AC6: COMYMAQ | AD6: COMYMAQ | AE6: SEGAMAC | AF6: ELECTRICA | AG6: 2 | AH6: PLATAFORMA TIPO TIJERA | AI6: GENIE | AJ6: GS3246 | AK6: GS4616C - 17123 | AT6: DIRECTA | AU6: 45899
A7: 3 | E7: 2607 | F7: 2642 | H7: 2970-3032 | I7: 3126-3215-3252 | J7: 3311-3386-3427 | O7: DISPONIBLE | V7: 1 | Y7: 3 | Z7: =W7+X7 -> 0 | AA7: =TODAY() -> 45957 | AB7: =AA7-W7 -> 45957 | AC7: COMYMAQ | AD7: COMYMAQ | AE7: SEGAMAC | AF7: ELECTRICA | AG7: 3 | AH7: PLATAFORMA ARTICULADA ELECTRICA | AI7: GENIE | AJ7: Z33/18 | AK7: Z331816M-724 | AL7: 10 | AM7: 03 | AN7: 2016
A8: 4 | F8: 2726 | G8: 2779-2809 | J8: 3347-3429 | K8: 3498-3607 | O8: DENTRO | P8: 5856 | Q8: MTP MANTENIMIENTO | R8: MTP MANTENIMIENTO | S8: SAISA | T8: 1740 | U8: CARLOS | V8: 1 | W8: 45957 | X8: 6 | Y8: 4 | Z8: =W8+X8 -> 45963 | AA8: =TODAY() -> 45957 | AB8: =AA8-W8 -> 0 | AC8: COMYMAQ | AD8: COMYMAQ | AE8: SEGAMAC | AF8: ELECTRICA | AG8: 4 | AH8: PLATAFORMA ARTICULADA ELECTRICA | AI8: GENIE | AJ8: Z33/18 | AK8: Z331816M-776 | AL8: 10 | AM8: 03 | AN8: 2016 | AT8: DIRECTA | AU8: 45929
A9: 5 | E9: S/FACTURA | F9: 2635 | O9: DISPONIBLE | V9: 1 | Y9: 5 | Z9: =W9+X9 -> 0 | AA9: =TODAY() -> 45957 | AB9: =AA9-W9 -> 45957 | AC9: COMYMAQ | AD9: COMYMAQ | AE9: SEGAMAC | AF9: ELECTRICA | AG9: 5 | AH9: PLATAFORMA ARTICULADA ELECTRICA | AI9: GENIE | AJ9: Z33/18 | AK9: Z331816M-732 | AL9: 10 | AM9: 03 | AN9: 2016
A10: 6 | J10: 3313-3389 | K10: 3603 | O10: DENTRO | P10: 5923 | Q10: TROYA INDUSTRIAL MONTERREY | R10: TROYA INDUSTRIAL MONTERREY | S10: SANTA ROSA | T10: 1701 | U10: CARLOS | V10: 1 | W10: 45955 | X10: 1 | Y10: 6 | Z10: =W10+X10 -> 45956 | AA10: =TODAY() -> 45957 | AB10: =AA10-W10 -> 2 | AC10: COMYMAQ | AD10: COMYMAQ | AE10: SEGAMAC | AF10: ELECTRICA | AG10: 6 | AH10: PLATAFORMA ARTICULADA ELECTRICA | AI10: GENIE | AJ10: Z33/18 | AK10: Z331816M-627 | AL10: 10 | AM10: 03 | AN10: 2016 | AT10: DIRECTA | AU10: 45955
A11: 7 | E11: 2475-2526-2510 | F11: 2645 | G11: 2812 | K11: 3507-3508-3809 | O11: DENTRO | P11: 5400 | Q11: CRISA LIBBEY MEXICO | R11: CRISA LIBBEY MEXICO | S11: CRISA | T11: 1466 | U11: JORGE | V11: 1 | W11: 45960 | X11: 13 | Y11: 7 | Z11: =W11+X11 -> 45973 | AA11: =TODAY() -> 45957 | AB11: =AA11-W11 -> -3 | AC11: COMYMAQ | AD11: COMYMAQ | AE11: SEGAMAC | AF11: ELECTRICA | AG11: 7 | AH11: PLATAFORMA ARTICULADA ELECTRICA | AI11: GENIE | AJ11: Z33/18 | AK11: Z331816M-717 | AL11: 10 | AM11: 03 | AN11: 2016
A12: 8 | I12: 3109-3113 | J12: 3313-3389 | O12: DISPONIBLE | V12: 1 | Y12: 8 | Z12: =W12+X12 -> 0 | AA12: =TODAY() -> 45957 | AB12: =AA12-W12 -> 45957 | AC12: COMYMAQ | AD12: COMYMAQ | AE12: SEGAMAC | AF12: ELECTRICA | AG12: 8 | AH12: PLATAFORMA ARTICULADA ELECTRICA | AI12: GENIE | AJ12: Z33/18 | AK12: Z331816M-614 | AL12: 10 | AM12: 03 | AN12: 2016
A13: 9 | K13: 3602 | O13: DENTRO | P13: 5919 | Q13: TROYA INDUSTRIAL MONTERREY | R13: TROYA INDUSTRIAL MONTERREY | S13: SANTA ROSA | T13: 1402 | U13: CARLOS | V13: 1 | W13: 45954 | X13: 6 | Y13: 9 | Z13: =W13+X13 -> 45960 | AA13: =TODAY() -> 45957 | AB13: =AA13-W13 -> 3 | AC13: COMYMAQ | AD13: COMYMAQ | AE13: SEGAMAC | AF13: ELECTRICA | AG13: 9 | AH13: PLATAFORMA ARTICULADA ELECTRICA | AI13: GENIE | AJ13: Z33/18 | AK13: Z331816M-647 | AL13: 10 | AM13: 03 | AN13: 2016 | AT13: DIRECTA | AU13: 45954
A14: 10 | E14: 2583 | G14: 2805 | O14: DISPONIBLE | V14: 1 | Y14: 10 | Z14: =W14+X14 -> 0 | AA14: =TODAY() -> 45957 | AB14: =AA14-W14 -> 45957 | AC14: COMYMAQ | AD14: COMYMAQ | AE14: SEGAMAC | AF14: ELECTRICA | AG14: 10 | AH14: PLATAFORMA ARTICULADA ELECTRICA | AI14: GENIE | AJ14: Z33/18 | AK14: Z331816M-735 | AL14: 10 | AM14: 03 | AN14: 2016
A15: 11 | O15: DISPONIBLE | V15: 1 | Y15: 11 | Z15: =W15+X15 -> 0 | AA15: =TODAY() -> 45957 | AB15: =AA15-W15 -> 45957 | AC15: COMYMAQ | AD15: COMYMAQ | AE15: SEGAMAC | AF15: ELECTRICA | AG15: 11 | AH15: PLATAFORMA ARTICULADA ELECTRICA | AI15: GENIE | AJ15: Z33/18 | AK15: Z331816M-803 | AL15: 10 | AM15: 03 | AN15: 2016
A16: 12 | H16: 2933 | O16: DISPONIBLE | V16: 1 | Y16: 12 | Z16: =W16+X16 -> 0 | AA16: =TODAY() -> 45957 | AB16: =AA16-W16 -> 45957 | AC16: COMYMAQ | AD16: COMYMAQ | AE16: SEGAMAC | AF16: ELECTRICA | AG16: 12 | AH16: PLATAFORMA ARTICULADA ELECTRICA | AI16: GENIE | AJ16: Z33/18 | AK16: Z331816M-606 | AL16: 10 | AM16: 03 | AN16: 2016
A17: 13 | F17: 2744 | G17: 2811 | I17: 3205 | O17: DENTRO | P17: 5929 | Q17: ALLIANCE SPECIALIZED SYSTEMS | R17: MAYELA ORNELAS LOPEZ | S17: TERNIUM PESQUERIA | T17: 403 | U17: JORGE | V17: 1 | W17: 45957 | X17: 27 | Y17: 13 | Z17: =W17+X17 -> 45984 | AA17: =TODAY() -> 45957 | AB17: =AA17-W17 -> 0 | AC17: COMYMAQ | AD17: COMYMAQ | AE17: SEGAMAC | AF17: ELECTRICA | AG17: 13 | AH17: PLATAFORMA TIPO TIJERA | AI17: GENIE | AJ17: GS2632 | AK17: GS3216C-15829 | AL17: 10 | AM17: 03 | AN17: 2016 | AT17: DIRECTA | AU17: 45957
A18: 14 | O18: TALLER | V18: 1 | Y18: 14 | Z18: =W18+X18 -> 0 | AA18: =TODAY() -> 45957 | AB18: =AA18-W18 -> 45957 | AC18: COMYMAQ | AD18: COMYMAQ | AE18: SEGAMAC | AF18: ELECTRICA | AG18: 14 | AH18: PLATAFORMA TIPO TIJERA | AI18: GENIE | AJ18: GS2632 | AK18: GS3216C-16255 | AL18: 10 | AM18: 03 | AN18: 2016
A19: 15 | H19: 3047 | I19: 3230 | J19: 3376 | K19: 3548 | O19: DENTRO | P19: 5674 | Q19: JOSE MARIO RODRIGUEZ GUERRERO | R19: JOSE MARIO RODRIGUEZ GUERRERO | S19: NUEVO LAREDO | T19: 428 | U19: CARLOS | V19: 1 | W19: 45946 | X19: 27 | Y19: 15 | Z19: =W19+X19 -> 45973 | AA19: =TODAY() -> 45957 | AB19: =AA19-W19 -> 11 | AC19: COMYMAQ | AD19: COMYMAQ | AE19: SEGAMAC | AF19: ELECTRICA | AG19: 15 | AH19: PLATAFORMA TIPO TIJERA | AI19: GENIE | AJ19: GS2632 | AK19: GS3216C-15778 | AL19: 10 | AM19: 03 | AN19: 2016 | AT19: DIRECTA | AU19: 45864 | AX19: NUEVO LAREDO | AY19: https://maps.app.goo.gl/BLjB842ei3UivWf56
A20: 16 | I20: 3205 | K20: 3511 | O20: DENTRO | P20: 5892 | Q20: GRUAS Y ELEVADORES DE MAZATLAN | R20: PEDRO TORRES PEREZ | S20: WALMART REFORMA NUEVO LAREDO | T20: 699 | U20: OSCAR | V20: 1 | W20: 45946 | X20: 27 | Y20: 16 | Z20: =W20+X20 -> 45973 | AA20: =TODAY() -> 45957 | AB20: =AA20-W20 -> 11 | AC20: COMYMAQ | AD20: COMYMAQ | AE20: SEGAMAC | AF20: ELECTRICA | AG20: 16 | AH20: PLATAFORMA TIPO TIJERA | AI20: GENIE | AJ20: GS2632 | AK20: GS3216C-15592 | AL20: 10 | AM20: 03 | AN20: 2016 | AT20: DIRECTA | AU20: 45946
A21: 17 | G21: 2831 | H21: 2996 | I21: 3121 | J21: 3284 | K21: 3468-3503 | O21: DENTRO | P21: 5924 | Q21: DETEC DISTRIBUIDORA | R21: ALEJANDRO MARTINEZ | S21: PARQUE INDUSTRIAL ORADEL | T21: 30 | U21: OSCAR | V21: 1 | W21: 45957 | X21: 27 | Y21: 17 | Z21: =W21+X21 -> 45984 | AA21: =TODAY() -> 45957 | AB21: =AA21-W21 -> 0 | AC21: COMYMAQ | AD21: DINGLI | AE21: COMYMAQ | AF21: ELECTRICA | AG21: 17 | AH21: PLATAFORMA TIPO TIJERA | AI21: DINGLI | AJ21: JCPT1412AC | AK21: JPC024E03100 | AL21: 30 | AM21: 05 | AN21: 2024 | AT21: DIRECTA | AU21: 45955
A22: 18 | F22: 2613 | G22: 2824 | H22: 2856 | I22: 3172 | K22: 3527 | O22: DENTRO | P22: 5877 | Q22: ALLIANCE SPECIALIZED SYSTEMS | R22: MAYELA ORNELAS LOPEZ | S22: YANG FENG RAMOS ARIZPE | T22: 63 | U22: JORGE | V22: 1 | W22: 45940 | X22: 29 | Y22: 18 | Z22: =W22+X22 -> 45969 | AA22: =TODAY() -> 45957 | AB22: =AA22-W22 -> 17 | AC22: COMYMAQ | AD22: DINGLI | AE22: COMYMAQ | AF22: ELECTRICA | AG22: 18 | AH22: PLATAFORMA TIPO TIJERA | AI22: DINGLI | AJ22: JCPT1412AC | AK22: JPC024E03104 | AL22: 30 | AM22: 05 | AN22: 2024 | AT22: DIRECTA | AU22: 45940 | AX22: RAMOS ARIZPE | AY22: https://maps.app.goo.gl/L8aWSyrBaMKx3bP67?g_st=aw | AZ22: EDUARDO SANCHEZ | BA22: 8993183255
A23: 19 | E23: 2593 | F23: 2703 | G23: 2880 | H23: 3030 | I23: 3180 | J23: 3381 | O23: DENTRO | P23: 5556 | Q23: TENCO INTEGRACION DE SISTEMAS | R23: TENCO INTEGRACION DE SISTEMAS | S23: AMAZON | T23: 6 | U23: JORGE | V23: 1 | W23: 45940 | X23: 27 | Y23: 19 | Z23: =W23+X23 -> 45967 | AA23: =TODAY() -> 45957 | AB23: =AA23-W23 -> 17 | AC23: COMYMAQ | AD23: DINGLI | AE23: COMYMAQ | AF23: ELECTRICA | AG23: 19 | AH23: PLATAFORMA TIPO TIJERA | AI23: DINGLI | AJ23: JCPT1412AC | AK23: JPC024F03478 | AL23: 30 | AM23: 05 | AN23: 2024 | AT23: DIRECTA | AU23: 45800 | AX23: ZUA ZUA | AY23: https://goo.gl/maps/vWx22rAxy8Habx7EA?g_st=aw | AZ23: BEATRIZ MENDOZA | BA23: 55 7929 3205
A24: 20 | I24: 3128-3237 | J24: 3338 | K24: 3456 | O24: DENTRO | P24: 5814 | Q24: DETEC DISTRIBUIDORA | R24: ALEJANDRO MARTINEZ | S24: PARQUE INDUSTRIAL ORADEL | T24: 11 | U24: OSCAR | V24: 1 | W24: 45941 | X24: 27 | Y24: 20 | Z24: =W24+X24 -> 45968 | AA24: =TODAY() -> 45957 | AB24: =AA24-W24 -> 16 | AC24: COMYMAQ | AD24: DINGLI | AE24: COMYMAQ | AF24: ELECTRICA | AG24: 20 | AH24: PLATAFORMA TIPO TIJERA | AI24: DINGLI | AJ24: JCPT1412AC | AK24: JPC024F03480 | AL24: 30 | AM24: 05 | AN24: 2024 | AT24: DIRECTA | AU24: 45913 | AX24: NUEVO LAREDO | AY24: https://goo.gl/maps/vWx22rAxy8Habx7EA?g_st=aw | AZ24: ALEJANDRO | BA24: 55 5043 5386
A25: 21 | H25: 2925-2947-2984 | J25: 3328 | O25: DISPONIBLE | V25: 1 | Y25: 21 | Z25: =W25+X25 -> 0 | AA25: =TODAY() -> 45957 | AB25: =AA25-W25 -> 45957 | AC25: COMYMAQ | AD25: DINGLI | AE25: COMYMAQ | AF25: ELECTRICA | AG25: 21 | AH25: PLATAFORMA TIPO TIJERA | AI25: DINGLI | AJ25: JCPT1412AC | AK25: JPC024F03485 | AL25: 30 | AM25: 05 | AN25: 2024
A26: 22 | H26: 2946 | I26: 3103 | J26: 3391-3447 | K26: 3549 | O26: TALLER | V26: 1 | Y26: 22 | Z26: =W26+X26 -> 0 | AA26: =TODAY() -> 45957 | AB26: =AA26-W26 -> 45957 | AC26: COMYMAQ | AD26: DINGLI | AE26: COMYMAQ | AF26: ELECTRICA | AG26: 22 | AH26: PLATAFORMA TIPO TIJERA | AI26: DINGLI | AJ26: JCPT1412AC | AK26: JPC024F03476 | AL26: 30 | AM26: 05 | AN26: 2024
A27: 23 | H27: 2946 | I27: 3103 | J27: 3391-3447 | O27: DISPONIBLE | V27: 1 | Y27: 23 | Z27: =W27+X27 -> 0 | AA27: =TODAY() -> 45957 | AB27: =AA27-W27 -> 45957 | AC27: COMYMAQ | AD27: DINGLI | AE27: COMYMAQ | AF27: ELECTRICA | AG27: 23 | AH27: PLATAFORMA TIPO TIJERA | AI27: DINGLI | AJ27: JCPT1412AC | AK27: JPC024F03482 | AL27: 30 | AM27: 05 | AN27: 2024
A28: 24 | H28: 3021 | I28: 3158 | J28: 3392 | O28: DISPONIBLE | V28: 1 | Y28: 24 | Z28: =W28+X28 -> 0 | AA28: =TODAY() -> 45957 | AB28: =AA28-W28 -> 45957 | AC28: COMYMAQ | AD28: DINGLI | AE28: COMYMAQ | AF28: ELECTRICA | AG28: 24 | AH28: PLATAFORMA TIPO TIJERA | AI28: DINGLI | AJ28: JCPT1412AC | AK28: JPC024F03483 | AL28: 30 | AM28: 05 | AN28: 2024
A29: 25 | F29: 2760 | G29: 2760 | H29: 2971-3065 | I29: 3219 | J29: 3388 | K29: 3568 | O29: DENTRO | P29: 5683 | Q29: SOLUCIONES Y DESARROLLOS MEP | R29: ALEJANDRA NUÑEZ | S29: PARQUE INDUSTRIAL ORADEL | T29: 18 | U29: OSCAR | V29: 1 | W29: 45948 | X29: 27 | Y29: 25 | Z29: =W29+X29 -> 45975 | AA29: =TODAY() -> 45957 | AB29: =AA29-W29 -> 9 | AC29: COMYMAQ | AD29: DINGLI | AE29: COMYMAQ | AF29: ELECTRICA | AG29: 25 | AH29: PLATAFORMA TIPO TIJERA | AI29: DINGLI | AJ29: JCPT1412AC | AK29: JPC024A01020 | AL29: 30 | AM29: 05 | AN29: 2024 | AT29: DIRECTA | AU29: 45864 | AX29: NUEVO LAREDO | AY29: https://goo.gl/maps/vWx22rAxy8Habx7EA?g_st=aw
A30: 26 | H30: 3060 | I30: 3085-3249 | J30: 3275-3338 | K30: 3456 | O30: DENTRO | P30: 5813 | Q30: DETEC DISTRIBUIDORA | R30: ALEJANDRO MARTINEZ | S30: PARQUE INDUSTRIAL ORADEL | T30: 19 | U30: OSCAR | V30: 1 | W30: 45941 | X30: 27 | Y30: 26 | Z30: =W30+X30 -> 45968 | AA30: =TODAY() -> 45957 | AB30: =AA30-W30 -> 16 | AC30: COMYMAQ | AD30: DINGLI | AE30: COMYMAQ | AF30: ELECTRICA | AG30: 26 | AH30: PLATAFORMA TIPO TIJERA | AI30: DINGLI | AJ30: S1412AC+ | AK30: JPC024E00047 | AL30: 30 | AM30: 05 | AN30: 2024 | AT30: DIRECTA | AU30: 45913 | AX30: NUEVO LAREDO | AY30: https://goo.gl/maps/vWx22rAxy8Habx7EA?g_st=aw | AZ30: ALEJANDRO | BA30: 55 5043 5386
A31: 27 | B31: 2147 | G31: 2823 | H31: 3029 | I31: 3241 | O31: TALLER | V31: 1 | Y31: 27 | Z31: =W31+X31 -> 0 | AA31: =TODAY() -> 45957 | AB31: =AA31-W31 -> 45957 | AC31: COMYMAQ | AD31: COMYMAQ | AE31: COMYMAQ | AF31: COMBUSTIÓN | AG31: 27 | AH31: COMPRESOR | AI31: ATLAS COPCO | AJ31: XATS375T3 | AK31: 4500B1310CR072827 | AL31: 40 | AM31: 02
A32: 28 | D32: 2340 | E32: S/FACTURA | F32: 2747 | J32: 3325 | K32: 3455 | O32: DENTRO | P32: 5809 | Q32: DETEC DISTRIBUIDORA | R32: ALEJANDRO MARTINEZ | S32: PARQUE INDUSTRIAL ORADEL | T32: 8323 | U32: OSCAR | V32: 1 | W32: 45939 | X32: 27 | Y32: 28 | Z32: =W32+X32 -> 45966 | AA32: =TODAY() -> 45957 | AB32: =AA32-W32 -> 18 | AC32: COMYMAQ | AD32: COMYMAQ | AE32: COMYMAQ | AF32: COMBUSTIÓN | AG32: 28 | AH32: GENERADOR DE 100KVA | AI32: HIMOINSA | AJ32: HFW-100 T6 CEM7 VTA | AK32: 171005365 | AL32: 60 | AM32: 3 | AN32: 2017 | AT32: DIRECTA | AU32: 45912 | AX32: NUEVO LAREDO | AY32: https://goo.gl/maps/vWx22rAxy8Habx7EA?g_st=aw | AZ32: ALEJANDRO | BA32: 55 5043 5386
A33: 29 | C33: 2333 | E33: 2479 | F33: 2669 | G33: 2844 | H33: 3000 | I33: 3155 | J33: 3307 | K33: 3481 | O33: DENTRO | P33: 5609 | Q33: ELECTROTEKNIA DE MEXICO | R33: LIZ MEDEL | S33: FRACCIONAMIENTO INDUSTRIAL INTERPUERTO MONTERREY | T33: 6258 | U33: JORGE | V33: 1 | W33: 45937 | X33: 27 | Y33: 29 | Z33: =W33+X33 -> 45964 | AA33: =TODAY() -> 45957 | AB33: =AA33-W33 -> 20 | AC33: COMYMAQ | AD33: COMYMAQ | AE33: COMYMAQ | AF33: COMBUSTIÓN | AG33: 29 | AH33: GENERADOR DE 45KVA | AI33: HIMOINSA | AJ33: HYW-45T T6 CEM7 VTA | AK33: 201004069 | AL33: 60 | AM33: 02 | AN33: 2020 | AT33: DIRECTA | AU33: 45825 | AX33: SALINAS VICTORIA
A34: 30 | O34: TALLER | V34: 1 | Y34: 30 | Z34: =W34+X34 -> 0 | AA34: =TODAY() -> 45957 | AB34: =AA34-W34 -> 45957 | AC34: LO | AD34: SEGAMAC | AE34: SEGAMAC | AF34: ELECTRICA | AG34: 30 | AH34: PLATAFORMA ELECTRICA ARTICULADA | AI34: GENIE | AJ34: Z33/18 | AK34: Z331816M-631 | AL34: 10 | AM34: 06
A35: 31 | B35: 2001-2080 | C35: 2262 | D35: 2390 | E35: 2571 | G35: 2850-2851 | H35: 2999 | I35: 3173 | J35: 3331 | K35: 3510 | O35: DENTRO | P35: 5193 | Q35: ALLIANCE SPECIALIZED SYSTEMS | R35: MAYELA ORNELAS LOPEZ | S35: SAN LUIS | T35: 1416 | U35: JORGE | V35: 1 | W35: 45942 | X35: 29 | Y35: 31 | Z35: =W35+X35 -> 45971 | AA35: =TODAY() -> 45957 | AB35: =AA35-W35 -> 15 | AC35: LO | AD35: SEGAMAC | AE35: SEGAMAC | AF35: ELECTRICA | AG35: 31 | AH35: PLATAFORMA ELECTRICA ARTICULADA | AI35: GENIE | AJ35: Z33/18 | AK35: Z331816M-697 | AL35: 10 | AM35: 06 | AT35: DIRECTA | AU35: 45642 | AX35: SAN LUIS
A36: 32 | C36: S/FACTURA | D36: S/FACTURA | G36: 2900 | I36: 3193 | J36: S/FACTURA | K36: 3458-3495 | O36: DISPONIBLE | V36: 1 | Y36: 32 | Z36: =W36+X36 -> 0 | AA36: =TODAY() -> 45957 | AB36: =AA36-W36 -> 45957 | AC36: LO | AD36: SEGAMAC | AE36: SEGAMAC | AF36: COMBUSTIÓN | AG36: 32 | AH36: PLATAFORMA TIPO TIJERA | AI36: GENIE | AJ36: GS-5390 RT | AK36: GS9016F-51069 | AL36: 30 | AM36: 05
A37: 33 | O37: DISPONIBLE | V37: 1 | Y37: 33 | Z37: =W37+X37 -> 0 | AA37: =TODAY() -> 45957 | AB37: =AA37-W37 -> 45957 | AC37: LO | AD37: SEGAMAC | AE37: SEGAMAC | AF37: COMBUSTIÓN | AG37: 33 | AH37: PLATAFORMA TIPO TIJERA | AI37: GENIE | AJ37: GS-5390 RT | AK37: GS9016F-51110 | AL37: 30 | AM37: 05 | AN37: 2015
A38: 34 | B38: 2041-2042-2181 | C38: 2311 | E38: 2494 | F38: 2715-2742 | G38: 2892 | H38: 2982 | K38: 3483 | O38: DENTRO | P38: 5880 | Q38: VAGO INSTALACIONES | R38: VAGO INSTALACIONES | S38: KHOLER | T38: 175 | U38: JORGE | V38: 1 | W38: 45943 | X38: 27 | Y38: 34 | Z38: =W38+X38 -> 45970 | AA38: =TODAY() -> 45957 | AB38: =AA38-W38 -> 14 | AC38: COMYMAQ | AD38: COMYMAQ | AE38: COMYMAQ | AF38: ELECTRICA | AG38: 34 | AH38: PLATAFORMA TELESCOPICA ELECTRICA | AI38: ZOOMLION | AJ38: ZT22JE | AK38: 07771200100P000052 | AL38: 10 | AM38: 09 | AN38: 2024 | AT38: DIRECTA | AU38: 45943
A39: 35 | H39: 2998 | K39: 3646 | O39: DENTRO | P39: 5865 | Q39: PROYECTOS Y CONSTRUCCIONES SIERRA MADRE | R39: ALFONSO SANCHEZ | S39: DHL | T39: 45 | U39: JORGE | V39: 1 | W39: 45945 | X39: 27 | Y39: 35 | Z39: =W39+X39 -> 45972 | AA39: =TODAY() -> 45957 | AB39: =AA39-W39 -> 12 | AC39: COMYMAQ | AD39: COMYMAQ | AE39: COMYMAQ | AF39: ELECTRICA | AG39: 35 | AH39: PLATAFORMA TELESCOPICA ELECTRICA | AI39: ZOOMLION | AJ39: ZT22JE | AK39: 07712000100P000053 | AL39: 10 | AM39: 09 | AN39: 2024 | AT39: DIRECTA | AU39: 45945
A40: 36 | B40: S/FACTURA | C40: S/FACTURA | D40: 2375-2413-2437-2463 | E40: S/FACTURA | G40: 2797 | H40: 2993 | I40: 3143 | J40: 3289 | K40: 3450 | O40: DENTRO | P40: 5305 | Q40: INTERNATIONAL METAL BUILDING | R40: GERARDO GOMEZ LUNA | S40: GK STAMPING FRONTERA | T40: 195 | U40: JORGE | V40: 1 | W40: 45934 | X40: 29 | Y40: 36 | Z40: =W40+X40 -> 45963 | AA40: =TODAY() -> 45957 | AB40: =AA40-W40 -> 23 | AC40: COMYMAQ | AD40: COMYMAQ | AE40: COMYMAQ | AF40: COMBUSTIÓN | AG40: 36 | AH40: PLATAFORMA TELESCOPICA DE COMBUSTION | AI40: ZOOMLION | AJ40: ZT20J | AK40: 0771100001P000073 | AL40: 10 | AM40: 08 | AN40: 2024 | AT40: DIRECTA | AU40: 45784
A41: 37 | B41: 2064 | C41: 2186 | D41: 2367 | E41: 2582 | F41: 2699-2737 | G41: 2788 | H41: 2959-2995 | I41: 3089 | J41: 3359 | K41: 3530 | O41: DENTRO | P41: 5864 | Q41: PROYECTOS Y CONSTRUCCIONES SIERRA MADRE | R41: ALFFONSO SANCHEZ | S41: DHL | T41: 544 | U41: JORGE | V41: 1 | W41: 45934 | X41: 27 | Y41: 37 | Z41: =W41+X41 -> 45961 | AA41: =TODAY() -> 45957 | AB41: =AA41-W41 -> 23 | AC41: COMYMAQ | AD41: COMYMAQ | AE41: COMYMAQ | AF41: COMBUSTIÓN | AG41: 37 | AH41: PLATAFORMA TELESCOPICA DE COMBUSTION | AI41: ZOOMLION | AJ41: ZT20J | AK41: 0771100001P000074 | AL41: 10 | AM41: 08 | AN41: 2024 | AT41: DIRECTA | AU41: 45934 | AX41: CIENEGA DE FLORES | AY41: https://maps.app.goo.gl/ccrcNXeBW4d8daiJA | AZ41: LUIS ALANIS | BA41: 8123199902
A42: 38 | B42: 2069 | C42: 2285 | D42: 2404 | E42: 2529 | F42: 2630 | G42: 2804 | H42: 2927 | I42: 3122-3242 | O42: DENTRO | P42: 5111 | Q42: SALTERRA | R42: YAZMIN VARGAS | S42: NEMAK, GARCIA | T42: 6606 | U42: CARLOS | V42: 1 | W42: 45895 | X42: 27 | Y42: 38 | Z42: =W42+X42 -> 45922 | AA42: =TODAY() -> 45957 | AB42: =AA42-W42 -> 62 | AC42: COMYMAQ | AD42: COMYMAQ | AE42: COMYMAQ | AF42: COMBUSTIÓN | AG42: 38 | AH42: MONTACARGAS | AI42: LIUGONG | AJ42: CLG2030G | AK42: CLG2000ZLKT044195 | AL42: 90 | AM42: 02 | AN42: 2019 | AP42: 0 | AT42: SUB RENTA | AU42: 45587 | AX42: GARCIA | AY42: https://maps.app.goo.gl/8e991B15tQHvxRT97?g_st=com.google.maps.preview.copy | AZ42: SALVADOR SALTERRA | BA42: 8125739289 | BB42: 03294T | BC42: RELLENAS | BD42: NO | BE42: N/A | BF42: GPS | BG42: 8117543562 | BH42: 49316.28 | BJ42: =IF(BK42="mxn",BH42/#REF!,BH42) -> 49316.28 | BK42: USD | BZ42: ='CONTROL DE RENTAS'!$Z42-'CONTROL DE RENTAS'!$AA42 -> -35 | CA42: =IF(BZ42>=7,"VIGENTE","POR VENCER") -> POR VENCER
A43: 39 | G43: 2834 | J43: 3299-3448 | K43: 3448 | O43: DENTRO | P43: 5790 | Q43: REDISA SOLUCIONES | R43: CRISTAL | S43: ESTADIO RAYADOS | T43: 8108 | U43: CARLOS | V43: 1 | W43: 45931 | X43: 27 | Y43: 39 | Z43: =W43+X43 -> 45958 | AA43: =TODAY() -> 45957 | AB43: =AA43-W43 -> 26 | AC43: COMYMAQ | AD43: COMYMAQ | AE43: COMYMAQ | AF43: COMBUSTIÓN | AG43: 39 | AH43: GENERADOR DE 45KVA | AI43: HIMOINSA | AJ43: HYW-45 T6 | AK43: 171005317 | AL43: 60 | AM43: 02 | AO43: 35000 | AP43: 0 | AT43: DIRECTA | AU43: 45903 | BZ43: ='CONTROL DE RENTAS'!$Z43-'CONTROL DE RENTAS'!$AA43 -> 1 | CA43: =IF(BZ43>=7,"VIGENTE","POR VENCER") -> POR VENCER
A44: 40 | I44: 3214 | O44: DISPONIBLE | V44: 1 | Y44: 40 | Z44: =W44+X44 -> 0 | AA44: =TODAY() -> 45957 | AB44: =AA44-W44 -> 45957 | AC44: COMYMAQ | AD44: COMYMAQ | AE44: COMYMAQ | AF44: COMBUSTIÓN | AG44: 40 | AH44: GENERADOR DE 45KVA | AI44: HIMOINSA | AJ44: HYW-45 T6 | AK44: 181002534 | AL44: 60 | AM44: 02 | AO44: 35000 | AP44: 0 | AT44: DIRECTA | AU44: 45888 | BZ44: ='CONTROL DE RENTAS'!$Z44-'CONTROL DE RENTAS'!$AA44 -> -45957 | CA44: =IF(BZ44>=7,"VIGENTE","POR VENCER") -> POR VENCER
A45: 41 | D45: 2398-2411-2448 | E45: 2587 | F45: 2702 | G45: 2852 | H45: 3042 | I45: 3203 | O45: DISPONIBLE | V45: 1 | Y45: 41 | Z45: =W45+X45 -> 0 | AA45: =TODAY() -> 45957 | AB45: =AA45-W45 -> 45957 | AC45: COMYMAQ | AD45: COMYMAQ | AE45: COMYMAQ | AF45: COMBUSTIÓN | AG45: 41 | AH45: GENERADOR DE 45KVA | AI45: HIMOINSA | AJ45: HYW-45 T6 | AK45: 181002535 | AL45: 60 | AM45: 02 | AO45: 35000 | AP45: 0 | BZ45: ='CONTROL DE RENTAS'!$Z45-'CONTROL DE RENTAS'!$AA45 -> -45957 | CA45: =IF(BZ45>=7,"VIGENTE","POR VENCER") -> POR VENCER
A46: 42 | B46: 2098 | C46: 2231 | E46: 2591 | H46: 3062 | I46: 3164-3264 | J46: 3314-3358 | K46: 3467 | O46: DISPONIBLE | V46: 1 | Y46: 42 | Z46: =W46+X46 -> 0 | AA46: =TODAY() -> 45957 | AB46: =AA46-W46 -> 45957 | AC46: COMYMAQ | AD46: COMYMAQ | AE46: COMYMAQ | AF46: COMBUSTIÓN | AG46: 42 | AH46: SOLDADORA | AI46: SHINDAIWA | AJ46: DGW400DMS | AK46: W00255006843 | AL46: 70 | AM46: 01 | AN46: 2018 | AO46: 24000 | AP46: 0 | BZ46: ='CONTROL DE RENTAS'!$Z46-'CONTROL DE RENTAS'!$AA46 -> -45957 | CA46: =IF(BZ46>=7,"VIGENTE","POR VENCER") -> POR VENCER
A47: 43 | B47: 2037 | E47: 251 | G47: 2875 | H47: 3031-3062 | I47: 3164-3264 | J47: 3314-3358 | K47: 3467 | O47: DISPONIBLE | V47: 1 | Y47: 43 | Z47: =W47+X47 -> 0 | AA47: =TODAY() -> 45957 | AB47: =AA47-W47 -> 45957 | AC47: COMYMAQ | AD47: COMYMAQ | AE47: COMYMAQ | AF47: COMBUSTIÓN | AG47: 43 | AH47: SOLDADORA | AI47: SHINDAIWA | AJ47: DGW400DMS | AK47: W00255006848 | AL47: 70 | AM47: 01 | AN47: 2018 | AO47: 24000 | AP47: 0 | BZ47: ='CONTROL DE RENTAS'!$Z47-'CONTROL DE RENTAS'!$AA47 -> -45957 | CA47: =IF(BZ47>=7,"VIGENTE","POR VENCER") -> POR VENCER
A48: 44 | B48: 2100 | C48: 2230 | E48: 2527 | F48: 2660 | G48: 2819 | H48: 2965 | I48: 3106 | J48: 3281-3433 | O48: DISPONIBLE | V48: 1 | Y48: 44 | Z48: =W48+X48 -> 0 | AA48: =TODAY() -> 45957 | AB48: =AA48-W48 -> 45957 | AC48: COMYMAQ | AD48: COMYMAQ | AE48: COMYMAQ | AF48: COMBUSTIÓN | AG48: 44 | AH48: SOLDADORA | AI48: SHINDAIWA | AJ48: DGW400DMS | AK48: W00255006861 | AL48: 70 | AM48: 01 | AO48: 24000 | AP48: 0 | BZ48: ='CONTROL DE RENTAS'!$Z48-'CONTROL DE RENTAS'!$AA48 -> -45957 | CA48: =IF(BZ48>=7,"VIGENTE","POR VENCER") -> POR VENCER
A49: 45 | B49: 2094-2159-2168 | C49: 2235 | I49: 3221 | J49: S/FACTURA | K49: S/FACTURA | O49: DENTRO | P49: 5853 | Q49: FRANCISCO JAVIER ROMERO CHAVEZ | R49: FRANCISCO JAVIER ROMERO CHAVEZ | S49: UNILEVER | T49: 5895 | U49: CARLOS | V49: 1 | W49: 45929 | X49: 27 | Y49: 45 | Z49: =W49+X49 -> 45956 | AA49: =TODAY() -> 45957 | AB49: =AA49-W49 -> 28 | AC49: COMYMAQ | AD49: COMYMAQ | AE49: COMYMAQ | AF49: COMBUSTIÓN | AG49: 45 | AH49: TORRE DE ILUMINACION | AI49: WAKER | AJ49: LTV-6L | AK49: WNCLTV01APUM02629 | AL49: 50 | AM49: 01 | AN49: 2012 | AP49: 0 | AT49: DIRECTA | AU49: 45929 | BZ49: ='CONTROL DE RENTAS'!$Z49-'CONTROL DE RENTAS'!$AA49 -> -1 | CA49: =IF(BZ49>=7,"VIGENTE","POR VENCER") -> POR VENCER
A50: 46 | B50: 2133 | D50: 2360 | G50: S/FACTURA | H50: S/FACTURA | I50: S/FACTURA | J50: S/FACTURA | K50: S/FACTURA | O50: DENTRO | P50: 5538 | Q50: BRANDO ZAPATA | R50: BRANDO ZAPATA | S50: ESCOBEDO | T50: 3519 | U50: CARLOS | V50: 1 | W50: 45930 | X50: 13 | Y50: 46 | Z50: =W50+X50 -> 45943 | AA50: =TODAY() -> 45957 | AB50: =AA50-W50 -> 27 | AC50: COMYMAQ | AD50: COMYMAQ | AE50: COMYMAQ | AF50: COMBUSTIÓN | AG50: 46 | AH50: TORRE DE ILUMINACION | AI50: WAKER | AJ50: LTV-6L | AK50: WNCLTV01EPUM02683 | AL50: 50 | AM50: 01 | AN50: 2012 | AO50: 12000 | AT50: DIRECTA | AU50: 45790 | AX50: ESCOBEDO | AY50: https://maps.app.goo.gl/usWrez1vJNbq5wnb8 | AZ50: ADALBERTO DE LA O | BA50: 81 3176 1064 | BZ50: ='CONTROL DE RENTAS'!$Z50-'CONTROL DE RENTAS'!$AA50 -> -14 | CA50: =IF(BZ50>=7,"VIGENTE","POR VENCER") -> POR VENCER
A51: 47 | F51: 2734 | I51: 3088 | K51: 3608 | O51: DENTRO | P51: 5918 | Q51: MARLEY INDUSTRIAL SUPPLY | R51: ELIZABETH ESTRADA | S51: PEDRERAS | T51: 2565 | U51: CARLOS | V51: 1 | W51: 45953 | X51: 13 | Y51: 47 | Z51: =W51+X51 -> 45966 | AA51: =TODAY() -> 45957 | AB51: =AA51-W51 -> 4 | AC51: COMYMAQ | AD51: COMYMAQ | AE51: COMYMAQ | AF51: COMBUSTIÓN | AG51: 47 | AH51: PLATAFORMA TIPO TIJERA | AI51: GENIE | AJ51: GS-5390 RT | AK51: GS9015-50990 | AL51: 30 | AM51: 05 | AO51: 50000 | AP51: 0 | AT51: DIRECTA | AU51: 45953 | BZ51: ='CONTROL DE RENTAS'!$Z51-'CONTROL DE RENTAS'!$AA51 -> 9 | CA51: =IF(BZ51>=7,"VIGENTE","POR VENCER") -> VIGENTE
A52: 48 | B52: 2167 | C52: 2304 | K52: 3533 | O52: DENTRO | P52: 5902 | Q52: INFRISA MEXICO | R52: INFRISA MEXICO | S52: CHURUBUSCO | T52: 1679 | U52: OSCAR | V52: 1 | W52: 45950 | X52: 27 | Y52: 48 | Z52: =W52+X52 -> 45977 | AA52: =TODAY() -> 45957 | AB52: =AA52-W52 -> 7 | AC52: COMYMAQ | AD52: COMYMAQ | AE52: COMYMAQ | AF52: COMBUSTIÓN | AG52: 48 | AH52: PLATAFORMA TIPO TIJERA | AI52: GENIE | AJ52: GS-4069 RT | AK52: GS6915-7668 | AL52: 30 | AM52: 04 | AN52: 2016 | AO52: 35000 | AP52: 0 | AT52: DIRECTA | BZ52: ='CONTROL DE RENTAS'!$Z52-'CONTROL DE RENTAS'!$AA52 -> 20 | CA52: =IF(BZ52>=7,"VIGENTE","POR VENCER") -> VIGENTE
A53: 49 | B53: 2143 | C53: 2304 | E53: S/FACTURA | F53: S/FACTURA | G53: S/FACTURA | H53: S/FACTURA | I53: S/FACTURA | K53: S/FACTURA | O53: DENTRO | P53: 5860 | Q53: JORGE ADALBERTO MORENO HERNANDEZ | R53: JORGE ADALBERTO MORENO HERNANDEZ | S53: MILENIUM CENTER APODACA | T53: 2902 | U53: OSCAR | V53: 1 | W53: 45931 | X53: 27 | Y53: 49 | Z53: =W53+X53 -> 45958 | AA53: =TODAY() -> 45957 | AB53: =AA53-W53 -> 26 | AC53: COMYMAQ | AD53: COMYMAQ | AE53: COMYMAQ | AF53: COMBUSTIÓN | AG53: 49 | AH53: PLATAFORMA TIPO TIJERA | AI53: GENIE | AJ53: GS-4069 RT | AK53: GS6916F-8982 | AL53: 30 | AM53: 04 | AN53: 2016 | AO53: 35000 | AP53: 0 | BZ53: ='CONTROL DE RENTAS'!$Z53-'CONTROL DE RENTAS'!$AA53 -> 1 | CA53: =IF(BZ53>=7,"VIGENTE","POR VENCER") -> POR VENCER
A54: 50 | B54: 2035-2167 | C54: 2299 | D54: S/FACTURA | E54: S/FACTURA | F54: 2646-2691-2720 | G54: 2763 | H54: 2949 | I54: 3108/SIN FACTURA | J54: 3370 | K54: 3567 | O54: DENTRO | P54: 5836 | Q54: INFRISA MEXICO | R54: INFRISA MEXICO | S54: SANTA ROSA | T54: 1555 | U54: OSCAR | V54: 1 | W54: 45951 | X54: 27 | Y54: 50 | Z54: =W54+X54 -> 45978 | AA54: =TODAY() -> 45957 | AB54: =AA54-W54 -> 6 | AC54: COMYMAQ | AD54: COMYMAQ | AE54: COMYMAQ | AF54: COMBUSTIÓN | AG54: 50 | AH54: PLATAFORMA TIPO TIJERA | AI54: GENIE | AJ54: GS-4390 RT | AK54: GS9016F-52358 | AL54: 30 | AM54: 04 | AN54: 2015 | AO54: 40000 | AP54: 0 | AT54: DIRECTA | AU54: 45926 | BZ54: ='CONTROL DE RENTAS'!$Z54-'CONTROL DE RENTAS'!$AA54 -> 21 | CA54: =IF(BZ54>=7,"VIGENTE","POR VENCER") -> VIGENTE
A55: 51 | B55: 2180 | C55: 2205-2309 | D55: 2470 | G55: 2825-2878-2913 | H55: 2944-2989-3022-3051 | I55: 3138-3178-3254 | O55: TALLER | V55: 1 | Y55: 51 | Z55: =W55+X55 -> 0 | AA55: =TODAY() -> 45957 | AB55: =AA55-W55 -> 45957 | AC55: COMYMAQ | AD55: COMYMAQ | AE55: COMYMAQ | AF55: COMBUSTIÓN | AG55: 51 | AH55: COMPRESOR | AI55: ATLAS COPCO | AJ55: XAS 375 | AK55: 8972 4224 87 | AL55: 40 | AM55: 02 | AO55: 51000 | AP55: 53040 | BZ55: ='CONTROL DE RENTAS'!$Z55-'CONTROL DE RENTAS'!$AA55 -> -45957 | CA55: =IF(BZ55>=7,"VIGENTE","POR VENCER") -> POR VENCER
A56: 52 | B56: 2129 | C56: 2300 | D56: 2238 | G56: 2783-2827-2874-2911 | H56: 2955-2997 | I56: 3138-3178 | O56: TALLER | V56: 1 | Y56: 52 | Z56: =W56+X56 -> 0 | AA56: =TODAY() -> 45957 | AB56: =AA56-W56 -> 45957 | AC56: COMYMAQ | AD56: COMYMAQ | AE56: COMYMAQ | AF56: COMBUSTIÓN | AG56: 52 | AH56: COMPRESOR | AI56: ATLAS COPCO | AJ56: XAS 375 | AK56: 8972422490 | AL56: 40 | AM56: 02 | AN56: 2012 | AO56: 51000 | AP56: 0 | BZ56: ='CONTROL DE RENTAS'!$Z56-'CONTROL DE RENTAS'!$AA56 -> -45957 | CA56: =IF(BZ56>=7,"VIGENTE","POR VENCER") -> POR VENCER
A57: 53 | B57: 2065 | C57: 2222 | D57: 2351 | E57: 2487 | F57: 2707-2749 | G57: 2829 | H57: 3006 | I57: 3157 | J57: 3344 | K57: 3489 | O57: DENTRO | P57: 5457 | Q57: GRUPO FERVI-GFC SA DE CV | R57: LUIS DANIEL RODRIGUEZ ESPINDOLA | S57: FORZA STEEL | T57: 5631 | U57: JORGE | V57: 1 | W57: 45940 | X57: 27 | Y57: 53 | Z57: =W57+X57 -> 45967 | AA57: =TODAY() -> 45957 | AB57: =AA57-W57 -> 17 | AC57: COMYMAQ | AD57: N/A | AE57: COMYMAQ | AF57: COMBUSTIÓN | AG57: 53 | AH57: PLATAFORMA TELESCOPICA DE COMBUSTION | AI57: GENIE | AJ57: S-60X | AK57: S60X14A-28910 | AL57: 20 | AM57: 01 | AN57: 2014 | AO57: 51000 | AP57: 53500 | AT57: SUB RENTA | AU57: 45744 | AX57: SALINAS VICTORIA | AY57: https://maps.app.goo.gl/zGR9XMib6YwfYcFE9 | AZ57: JORGE | BA57: 55 3816 3569 | BC57: N/A | BD57: NO | BE57: N/A | BF57: N/A | BG57: N/A | BI57: 125000 | BJ57: =IF(BK57="mxn",BI57/#REF!,BI57) -> #REF! | BK57: MXN | BZ57: ='CONTROL DE RENTAS'!$Z57-'CONTROL DE RENTAS'!$AA57 -> 10 | CA57: =IF(BZ57>=7,"VIGENTE","POR VENCER") -> VIGENTE
A58: 54 | B58: 2032 | C58: 2195 | D58: 2346 | E58: 2485 | F58: 2639 | G58: 2798 | H58: 2994 | I58: 3144 | J58: 3320 | K58: 3451 | O58: DENTRO | P58: 5306 | Q58: INTERNATIONAL METAL BUILDING | R58: GERARDO GOMEZ LUNA | S58: GK STAMPING FRONTERA | T58: 4608 | U58: JORGE | V58: 1 | W58: 45935 | X58: 29 | Y58: 54 | Z58: =W58+X58 -> 45964 | AA58: =TODAY() -> 45957 | AB58: =AA58-W58 -> 22 | AC58: COMYMAQ | AD58: N/A | AE58: COMYMAQ | AF58: COMBUSTIÓN | AG58: 54 | AH58: PLATAFORMA TELESCOPICA DE COMBUSTION | AI58: GENIE | AJ58: S-60X | AK58: S60X14A-28914 | AL58: 20 | AM58: 01 | AN58: 2014 | AO58: 51000 | AP58: 55620 | AT58: DIRECTA | AU58: 45665 | AX58: MONCLOVA | AY58: https://maps.app.goo.gl/pcVZ3EyxsEwPPGDW9 | BC58: N/A | BD58: NO | BE58: N/A | BF58: N/A | BG58: N/A | BI58: 125000 | BJ58: =IF(BK58="mxn",BI58/#REF!,BI58) -> #REF! | BK58: MXN | BZ58: ='CONTROL DE RENTAS'!$Z58-'CONTROL DE RENTAS'!$AA58 -> 7 | CA58: =IF(BZ58>=7,"VIGENTE","POR VENCER") -> VIGENTE
A59: 55 | B59: S/FACTURA | F59: 2705 | G59: 2830 | O59: TALLER | V59: 1 | Y59: 55 | Z59: =W59+X59 -> 0 | AA59: =TODAY() -> 45957 | AB59: =AA59-W59 -> 45957 | AC59: COMYMAQ | AD59: N/A | AE59: COMYMAQ | AF59: COMBUSTIÓN | AG59: 55 | AH59: PLATAFORMA TELESCOPICA DE COMBUSTION | AI59: GENIE | AJ59: S-85 | AK59: S8515-12224 | AL59: 20 | AM59: 02 | AN59: 2015 | AO59: 110000 | AP59: 0 | BP59: HDI | BZ59: ='CONTROL DE RENTAS'!$Z59-'CONTROL DE RENTAS'!$AA59 -> -45957 | CA59: =IF(BZ59>=7,"VIGENTE","POR VENCER") -> POR VENCER
A60: 56 | D60: 2434 | E60: 2570 | F60: 2675 | G60: 2828 | H60: 3005 | I60: 3156 | J60: 3343 | K60: 3490 | O60: DENTRO | P60: 5451 | Q60: GRUPO FERVI-GFC SA DE CV | R60: LUIS DANIEL RODRIGUEZ ESPINDOLA | S60: FORZA STEEL | T60: 4011 | U60: JORGE | V60: 1 | W60: 45946 | X60: 27 | Y60: 56 | Z60: =W60+X60 -> 45973 | AA60: =TODAY() -> 45957 | AB60: =AA60-W60 -> 11 | AC60: COMYMAQ | AD60: N/A | AE60: COMYMAQ | AF60: COMBUSTIÓN | AG60: 56 | AH60: PLATAFORMA TELESCOPICA DE COMBUSTION | AI60: GENIE | AJ60: S-80X | AK60: S80X15-13102 | AL60: 20 | AM60: 02 | AN60: 2015 | AO60: 100000 | AP60: 109000 | AT60: DIRECTA | AU60: 45741 | AX60: SALINAS VICTORIA | AY60: https://maps.app.goo.gl/LydcujXiR1ddduj29 | AZ60: JAGR | BA60: 55 3816 3569 | BP60: HDI | BZ60: ='CONTROL DE RENTAS'!$Z60-'CONTROL DE RENTAS'!$AA60 -> 16 | CA60: =IF(BZ60>=7,"VIGENTE","POR VENCER") -> VIGENTE
A61: 57 | O61: TALLER | V61: 1 | Y61: 57 | Z61: =W61+X61 -> 0 | AA61: =TODAY() -> 45957 | AB61: =AA61-W61 -> 45957 | AC61: COMYMAQ | AD61: N/A | AE61: COMYMAQ | AF61: COMBUSTIÓN | AG61: 57 | AH61: PLATAFORMA ARTICULADA DE COMBUSTION | AI61: GENIE | AJ61: ZX-135/70 | AK61: ZX13515-2730 | AL61: 10 | AM61: 10 | AN61: 2015 | AO61: 180000 | BP61: HDI | BZ61: ='CONTROL DE RENTAS'!$Z61-'CONTROL DE RENTAS'!$AA61 -> -45957 | CA61: =IF(BZ61>=7,"VIGENTE","POR VENCER") -> POR VENCER
A62: 58 | B62: 2103 | C62: 2253 | D62: 2401 | E62: 2532 | F62: 2659 | G62: 2858 | H62: 2972 | I62: S/FACTURA | J62: 3363 | K62: 3475 | O62: DISPONIBLE | V62: 1 | Y62: 58 | Z62: =W62+X62 -> 0 | AA62: =TODAY() -> 45957 | AB62: =AA62-W62 -> 45957 | AC62: LO | AD62: SEGAMAC | AE62: SEGAMAC | AF62: COMBUSTIÓN | AG62: 58 | AH62: PLATAFORMA ARTICULADA DE COMBUSTION | AI62: ZOOMLION | AJ62: ZA14J | AK62: 0773400000P000439 | AL62: 10 | AM62: 02 | AN62: 2024 | AO62: 33000 | AP62: 39200 | BP62: HDI | BZ62: ='CONTROL DE RENTAS'!$Z62-'CONTROL DE RENTAS'!$AA62 -> -45957 | CA62: =IF(BZ62>=7,"VIGENTE","POR VENCER") -> POR VENCER
A63: 59 | B63: 2018-2132 | C63: 2289 | D63: 2442 | E63: S/FACTURA | F63: S/FACTURA | J63: 3364 | K63: 3525 | O63: DENTRO | P63: 5869 | Q63: ALLIANCE SPECIALIZED SYSTEMS | R63: MAYELA ORNELAS LOPEZ | S63: YOKOHAMA | T63: 1078 | U63: JORGE | V63: 1 | W63: 45936 | X63: 29 | Y63: 59 | Z63: =W63+X63 -> 45965 | AA63: =TODAY() -> 45957 | AB63: =AA63-W63 -> 21 | AC63: LO | AD63: SEGAMAC | AE63: SEGAMAC | AF63: COMBUSTIÓN | AG63: 59 | AH63: PLATAFORMA ARTICULADA DE COMBUSTION | AI63: ZOOMLION | AJ63: ZA14J | AK63: 0773400000P000440 | AL63: 10 | AM63: 02 | AN63: 2024 | AO63: 33000 | AP63: 39020 | AT63: DIRECTA | AU63: 45936 | AX63: DERRAMADERO | AY63: https://maps.app.goo.gl/HBQV4ZTVdqQ29wFRA?g_st=aw | AZ63: GONZALO GALINDO | BA63: 8994603976 | BP63: HDI | BZ63: ='CONTROL DE RENTAS'!$Z63-'CONTROL DE RENTAS'!$AA63 -> 8 | CA63: =IF(BZ63>=7,"VIGENTE","POR VENCER") -> VIGENTE
A64: 60 | B64: 2053-2177 | D64: 2401 | E64: 2532 | F64: 2659 | G64: 2858 | H64: 2972-3004-3036 | I64: 3109-3113 | J64: 3365 | K64: 3478 | O64: TALLER | V64: 1 | Y64: 60 | Z64: =W64+X64 -> 0 | AA64: =TODAY() -> 45957 | AB64: =AA64-W64 -> 45957 | AC64: LO | AD64: SEGAMAC | AE64: SEGAMAC | AF64: COMBUSTIÓN | AG64: 60 | AH64: PLATAFORMA ARTICULADA DE COMBUSTION | AI64: ZOOMLION | AJ64: ZA14J | AK64: 0773400000P000437 | AL64: 10 | AM64: 02 | AN64: 2024 | AO64: 33000 | AP64: 33000 | BP64: HDI | BZ64: ='CONTROL DE RENTAS'!$Z64-'CONTROL DE RENTAS'!$AA64 -> -45957 | CA64: =IF(BZ64>=7,"VIGENTE","POR VENCER") -> POR VENCER
A65: 61 | B65: 2103 | C65: 2253 | D65: 2401 | E65: 2532 | F65: 2659 | G65: 2858 | H65: 2972-3004-3036 | I65: 3109-3113 | J65: 3366 | K65: 3477 | O65: DISPONIBLE | V65: 1 | Y65: 61 | Z65: =W65+X65 -> 0 | AA65: =TODAY() -> 45957 | AB65: =AA65-W65 -> 45957 | AC65: LO | AD65: SEGAMAC | AE65: SEGAMAC | AF65: COMBUSTIÓN | AG65: 61 | AH65: PLATAFORMA ARTICULADA DE COMBUSTION | AI65: ZOOMLION | AJ65: ZA14J | AK65: 0773400000P000438 | AL65: 10 | AM65: 02 | AN65: 2024 | AO65: 33000 | AP65: 33000 | BP65: HDI | BZ65: ='CONTROL DE RENTAS'!$Z65-'CONTROL DE RENTAS'!$AA65 -> -45957 | CA65: =IF(BZ65>=7,"VIGENTE","POR VENCER") -> POR VENCER
A66: 62 | B66: 2170 | C66: 2228-2234-2308 | D66: 2362 | J66: 3286-3371 | K66: 3543 | O66: DENTRO | P66: 5787 | Q66: FERROMINIO DISEÑO Y CONSTRUCCION | R66: ARIANA HERNANDEZ | S66: CIENEGA DE FLORES LITIO | T66: 6788 | U66: JORGE | V66: 1 | W66: 45946 | X66: 27 | Y66: 62 | Z66: =W66+X66 -> 45973 | AA66: =TODAY() -> 45957 | AB66: =AA66-W66 -> 11 | AC66: COMYMAQ | AD66: N/A | AE66: COMYMAQ | AF66: COMBUSTIÓN | AG66: 62 | AH66: TORRE DE ILUMINACION | AI66: TEREX | AJ66: AL4060 | AK66: GKF-22377 | AL66: 50 | AM66: 01 | AN66: 2022 | AP66: 0 | AT66: DIRECTA | AU66: 45902 | BP66: HDI | BZ66: ='CONTROL DE RENTAS'!$Z66-'CONTROL DE RENTAS'!$AA66 -> 16 | CA66: =IF(BZ66>=7,"VIGENTE","POR VENCER") -> VIGENTE
A67: 63 | J67: 3286-3371 | K67: 3543 | O67: DENTRO | P67: 5786 | Q67: FERROMINIO DISEÑO Y CONSTRUCCION | R67: ARIANA HERNANDEZ | S67: CIENEGA DE FLORES LITIO | T67: 7713 | U67: JORGE | V67: 1 | W67: 45946 | X67: 27 | Y67: 63 | Z67: =W67+X67 -> 45973 | AA67: =TODAY() -> 45957 | AB67: =AA67-W67 -> 11 | AC67: COMYMAQ | AD67: N/A | AE67: COMYMAQ | AF67: COMBUSTIÓN | AG67: 63 | AH67: TORRE DE ILUMINACION | AI67: TEREX | AJ67: AL4060 | AK67: GKF-22372 | AL67: 50 | AM67: 01 | AN67: 2022 | AP67: 0 | AT67: DIRECTA | AU67: 45902 | BZ67: ='CONTROL DE RENTAS'!$Z67-'CONTROL DE RENTAS'!$AA67 -> 16 | CA67: =IF(BZ67>=7,"VIGENTE","POR VENCER") -> VIGENTE
A68: 64 | O68: DISPONIBLE | V68: 1 | Y68: 64 | Z68: =W68+X68 -> 0 | AA68: =TODAY() -> 45957 | AB68: =AA68-W68 -> 45957 | AC68: COMYMAQ | AD68: N/A | AE68: COMYMAQ | AF68: COMBUSTIÓN | AG68: 64 | AH68: TORRE DE ILUMINACION | AI68: MAGNUM | AJ68: MLT3060M | AK68: 1001673 | AL68: 50 | AM68: 01 | AN68: 2010 | AP68: 0 | BZ68: ='CONTROL DE RENTAS'!$Z68-'CONTROL DE RENTAS'!$AA68 -> -45957 | CA68: =IF(BZ68>=7,"VIGENTE","POR VENCER") -> POR VENCER
A69: 65 | B69: 2029 | C69: 2244 | E69: 2477 | I69: 3244 | J69: 3414 | K69: 3578 | O69: DENTRO | P69: 5775 | Q69: FERROMINIO DISEÑO Y CONSTRUCCION | R69: ARIANA HERNANDEZ | S69: CIENEGA DE FLORES LITIO | T69: 1928 | U69: JORGE | V69: 1 | W69: 45952 | X69: 27 | Y69: 65 | Z69: =W69+X69 -> 45979 | AA69: =TODAY() -> 45957 | AB69: =AA69-W69 -> 5 | AC69: COMYMAQ | AD69: N/A | AE69: COMYMAQ | AF69: COMBUSTIÓN | AG69: 65 | AH69: TORRE DE ILUMINACION | AI69: MAGNUM | AJ69: MLT3060M | AK69: 0830125 | AL69: 50 | AM69: 01 | AN69: 2008 | AP69: 0 | AT69: DIRECTA | AU69: 45896 | BZ69: ='CONTROL DE RENTAS'!$Z69-'CONTROL DE RENTAS'!$AA69 -> 22 | CA69: =IF(BZ69>=7,"VIGENTE","POR VENCER") -> VIGENTE
A70: 66 | O70: DISPONIBLE | V70: 1 | Y70: 66 | Z70: =W70+X70 -> 0 | AA70: =TODAY() -> 45957 | AB70: =AA70-W70 -> 45957 | AC70: COMYMAQ | AD70: N/A | AE70: COMYMAQ | AF70: COMBUSTIÓN | AG70: 66 | AH70: TORRE DE ILUMINACION | AI70: WARREN POWER SYSTEMS | AJ70: WCW64MH | AK70: C06-12-02050 | AL70: 50 | AM70: 01 | AN70: 2006 | AP70: 0 | BZ70: ='CONTROL DE RENTAS'!$Z70-'CONTROL DE RENTAS'!$AA70 -> -45957 | CA70: =IF(BZ70>=7,"VIGENTE","POR VENCER") -> POR VENCER
A71: 67 | O71: TALLER | V71: 1 | Y71: 67 | Z71: =W71+X71 -> 0 | AA71: =TODAY() -> 45957 | AB71: =AA71-W71 -> 45957 | AC71: COMYMAQ | AD71: N/A | AE71: COMYMAQ | AF71: COMBUSTIÓN | AG71: 67 | AH71: TORRE DE ILUMINACION | AI71: WARREN POWER SYSTEMS | AJ71: WCW64MH | AK71: C07-01-02153 | AL71: 50 | AM71: 01 | AN71: 2006 | AP71: 0 | BZ71: ='CONTROL DE RENTAS'!$Z71-'CONTROL DE RENTAS'!$AA71 -> -45957 | CA71: =IF(BZ71>=7,"VIGENTE","POR VENCER") -> POR VENCER
A72: 68 | O72: DISPONIBLE | V72: 1 | Y72: 68 | Z72: =W72+X72 -> 0 | AA72: =TODAY() -> 45957 | AB72: =AA72-W72 -> 45957 | AC72: COMYMAQ | AD72: N/A | AE72: COMYMAQ | AF72: COMBUSTIÓN | AG72: 68 | AH72: TORRE DE ILUMINACION | AI72: WARREN POWER SYSTEMS | AJ72: WCW64MH | AK72: 2176 | AL72: 50 | AM72: 01 | AN72: 2006 | AO72: 15000 | AP72: 12480 | BZ72: ='CONTROL DE RENTAS'!$Z72-'CONTROL DE RENTAS'!$AA72 -> -45957 | CA72: =IF(BZ72>=7,"VIGENTE","POR VENCER") -> POR VENCER
A73: 69 | B73: 2130 | C73: 2278 | D73: S/FACTURA | F73: 2694 | G73: 2694-2862 | H73: 2958 | J73: 3419 | K73: 3604 | O73: DENTRO | P73: 5576 | Q73: JOSE MARIO RODRIGUEZ GUERRERO | R73: JOSE MARIO RODRIGUEZ GUERRERO | S73: NUEVO LAREDO | T73: 41017 | U73: CARLOS | V73: 1 | W73: 45950 | X73: 27 | Y73: 69 | Z73: =W73+X73 -> 45977 | AA73: =TODAY() -> 45957 | AB73: =AA73-W73 -> 7 | AC73: COMYMAQ | AD73: VIDAL | AE73: COMYMAQ | AF73: ELECTRICA | AG73: 69 | AH73: PLATAFORMA TIPO TIJERA | AI73: GENIE | AJ73: GS1930 | AK73: GS30P-179311 | AL73: 30 | AM73: 01 | AN73: 2018 | AO73: 18000 | AP73: 18000 | AQ73: =219.38 -> 219.38 | AR73: =AQ73*$AQ$1 -> 4334.2248 | AS73: =AP73-AR73 -> 13665.775 | BZ73: ='CONTROL DE RENTAS'!$Z73-'CONTROL DE RENTAS'!$AA73 -> 20 | CA73: =IF(BZ73>=7,"VIGENTE","POR VENCER") -> VIGENTE
A74: 70 | B74: S/FACTURA | C74: S/FACTURA | D74: S/FACTURA | I74: 3184 | J74: 3350 | K74: 3484 | O74: DENTRO | P74: 5745 | Q74: VAGO INSTALACIONES | R74: OLEGARIO RODRIGUEZ | S74: KOHLER SFO | T74: 347 | U74: JORGE | V74: 1 | W74: 45943 | X74: 27 | Y74: 70 | Z74: =W74+X74 -> 45970 | AA74: =TODAY() -> 45957 | AB74: =AA74-W74 -> 14 | AC74: COMYMAQ | AD74: VIDAL | AE74: COMYMAQ | AF74: ELECTRICA | AG74: 70 | AH74: PLATAFORMA TIPO TIJERA | AI74: GENIE | AJ74: GS1930 | AK74: GS30P-179312 | AL74: 30 | AM74: 01 | AN74: 2018 | AO74: 18000 | AP74: 35200 | AQ74: =219.38 -> 219.38 | AR74: =AQ74*$AQ$1 -> 4334.2248 | AS74: =AP74-AR74 -> 30865.775 | AT74: DIRECTA | AU74: 45887 | BC74: N/A | BD74: N/A | BE74: N/A | BL74: MOTOR | BZ74: ='CONTROL DE RENTAS'!$Z74-'CONTROL DE RENTAS'!$AA74 -> 13 | CA74: =IF(BZ74>=7,"VIGENTE","POR VENCER") -> VIGENTE
A75: 71 | B75: 2099 | E75: 2522 | I75: 3259 | J75: 3313-3389 | O75: DISPONIBLE | V75: 1 | Y75: 71 | Z75: =W75+X75 -> 0 | AA75: =TODAY() -> 45957 | AB75: =AA75-W75 -> 45957 | AC75: COMYMAQ | AD75: COMYMAQ | AE75: COMYMAQ | AF75: COMBUSTIÓN | AG75: 71 | AH75: SOLDADORA | AI75: SHINDAIWA | AJ75: DGW4000MC | AK75: W002555006846 | AL75: 70 | AM75: 01 | AN75: 2017 | BB75: 03118T | BC75: RELLENAS | BD75: NO | BE75: N/A | BF75: GPS | BG75: 8121785820 | BH75: 42525 | BJ75: =IF(BK75="mxn",BH75/#REF!,BH75) -> 42525 | BK75: USD | BZ75: ='CONTROL DE RENTAS'!$Z75-'CONTROL DE RENTAS'!$AA75 -> -45957 | CA75: =IF(BZ75>=7,"VIGENTE","POR VENCER") -> POR VENCER
A76: 72 | B76: S/FACTURA | C76: S/FACTURA | D76: 2460 | E76: 2581 | F76: 2697 | G76: 2883 | H76: 3013 | I76: 3159 | O76: DISPONIBLE | V76: 1 | Y76: 72 | Z76: =W76+X76 -> 0 | AA76: =TODAY() -> 45957 | AB76: =AA76-W76 -> 45957 | AC76: COMYMAQ | AD76: N/A | AE76: COMYMAQ | AF76: COMBUSTIÓN | AG76: 72 | AH76: COMPRESOR | AI76: AIRMAN | AJ76: PDS185S-6C2 | AK76: B4-6C2C884 | AL76: 40 | AM76: 01 | AN76: 2024 | AO76: 30000 | AP76: 33000 | BB76: 02152T | BD76: NO | BE76: N/A | BF76: SIN GPS | BG76: APLICA | BH76: 40766.92 | BJ76: =IF(BK76="mxn",BH76/#REF!,BH76) -> 40766.92 | BK76: USD | BZ76: ='CONTROL DE RENTAS'!$Z76-'CONTROL DE RENTAS'!$AA76 -> -45957 | CA76: =IF(BZ76>=7,"VIGENTE","POR VENCER") -> POR VENCER
A77: 73 | B77: 2104 | C77: 2255 | D77: 2384 | F77: S/FACTURA | H77: S/FACTURA | I77: S/FACTURA | J77: S/FACTURA | O77: DISPONIBLE | V77: 1 | Y77: 73 | Z77: =W77+X77 -> 0 | AA77: =TODAY() -> 45957 | AB77: =AA77-W77 -> 45957 | AC77: COMYMAQ | AD77: N/A | AE77: COMYMAQ | AF77: COMBUSTIÓN | AG77: 73 | AH77: COMPRESOR | AI77: AIRMAN | AJ77: PDS185S-6C2 | AK77: B4-6C2C944 | AL77: 40 | AM77: 01 | AN77: 2024 | AO77: 30000 | AP77: 26700 | BZ77: ='CONTROL DE RENTAS'!$Z77-'CONTROL DE RENTAS'!$AA77 -> -45957 | CA77: =IF(BZ77>=7,"VIGENTE","POR VENCER") -> POR VENCER
A78: 74 | C78: 2201-2288 | F78: 2695 | O78: DISPONIBLE | V78: 1 | Y78: 74 | Z78: =W78+X78 -> 0 | AA78: =TODAY() -> 45957 | AB78: =AA78-W78 -> 45957 | AC78: COMYMAQ | AD78: N/A | AE78: COMYMAQ | AF78: COMBUSTIÓN | AG78: 74 | AH78: COMPRESOR | AI78: AIRMAN | AJ78: PDS185S-6C2 | AK78: B4-6C2C945 | AL78: 40 | AM78: 01 | AN78: 2024 | AO78: 30000 | AP78: 26700 | BZ78: ='CONTROL DE RENTAS'!$Z78-'CONTROL DE RENTAS'!$AA78 -> -45957 | CA78: =IF(BZ78>=7,"VIGENTE","POR VENCER") -> POR VENCER
A79: 75 | B79: 2104 | C79: 2255 | D79: 2384 | E79: 2553 | F79: 2629-2657 | G79: 2800 | H79: 2957 | I79: 3101-3194 | J79: 3301 | O79: DISPONIBLE | V79: 1 | Y79: 75 | Z79: =W79+X79 -> 0 | AA79: =TODAY() -> 45957 | AB79: =AA79-W79 -> 45957 | AC79: COMYMAQ | AD79: N/A | AE79: COMYMAQ | AF79: COMBUSTIÓN | AG79: 75 | AH79: COMPRESOR | AI79: AIRMAN | AJ79: PDS185S-6C2 | AK79: B4-6C2C946 | AL79: 40 | AM79: 01 | AN79: 2024 | AO79: 30000 | AP79: 0 | BZ79: ='CONTROL DE RENTAS'!$Z79-'CONTROL DE RENTAS'!$AA79 -> -45957 | CA79: =IF(BZ79>=7,"VIGENTE","POR VENCER") -> POR VENCER
A80: 76 | B80: 2005-2175 | D80: 2365 | E80: 2500 | F80: 2653-2752 | H80: 2930-2967 | J80: S/FACTURA | K80: S/FACTURA | O80: DENTRO | P80: 5812 | Q80: DANIEL MARTINEZ ROBLES | R80: DANIEL MARTINEZ ROBLES | S80: MARIN | T80: 1144 | U80: OSCAR | V80: 1 | W80: 45912 | X80: 27 | Y80: 76 | Z80: =W80+X80 -> 45939 | AA80: =TODAY() -> 45957 | AB80: =AA80-W80 -> 45 | AC80: LO | AD80: N/A | AE80: DINGLI | AF80: COMBUSTIÓN | AG80: 76 | AH80: PLATAFORMA ARTICULADA DE COMBUSTION | AI80: DINGLI | AJ80: BA16CRT2 | AK80: BARC023J00304 | AL80: 10 | AM80: 02 | AN80: 2024 | AO80: 36000 | AP80: 33000 | AT80: DIRECTA | AU80: 45912 | AX80: MARIN | AY80: https://maps.app.goo.gl/v8CpF4GatET7JP5t5 | AZ80: ING. JULIO CESAR | BA80: 8124930939 | BZ80: ='CONTROL DE RENTAS'!$Z80-'CONTROL DE RENTAS'!$AA80 -> -18 | CA80: =IF(BZ80>=7,"VIGENTE","POR VENCER") -> POR VENCER
A81: 77 | B81: 2060 | C81: 2216 | D81: 2400 | E81: 2521 | F81: 2684-2719-2750 | G81: 2773 | H81: 2950 | I81: 3142-3211-3228 | J81: 3278-3349-3372-3411 | K81: 3526 | O81: DENTRO | P81: 5870 | Q81: ALLIANCE SPECIALIZED SYSTEMS | R81: MAYELA ORNELAS LOPEZ | S81: YOKOHAMA | T81: 1106 | U81: JORGE | V81: 1 | W81: 45936 | X81: 29 | Y81: 77 | Z81: =W81+X81 -> 45965 | AA81: =TODAY() -> 45957 | AB81: =AA81-W81 -> 21 | AC81: LO | AD81: N/A | AE81: DINGLI | AF81: COMBUSTIÓN | AG81: 77 | AH81: PLATAFORMA ARTICULADA DE COMBUSTION | AI81: DINGLI | AJ81: BA16CRT2 | AK81: BARC023J00305 | AL81: 10 | AM81: 02 | AN81: 2024 | AO81: 36000 | AP81: 36000 | AT81: DIRECTA | AU81: 45936 | AX81: DERRAMADERO | AY81: https://maps.app.goo.gl/HBQV4ZTVdqQ29wFRA?g_st=aw | AZ81: GONZALO GALINDO | BA81: 8994603976 | BZ81: ='CONTROL DE RENTAS'!$Z81-'CONTROL DE RENTAS'!$AA81 -> 8 | CA81: =IF(BZ81>=7,"VIGENTE","POR VENCER") -> VIGENTE
A82: 78 | B82: 2002-2124 | C82: 2263 | E82: 2498 | F82: 2751 | G82: 2916 | H82: 2928-2966 | J82: 3393 | K82: 3551 | O82: TALLER | V82: 1 | Y82: 78 | Z82: =W82+X82 -> 0 | AA82: =TODAY() -> 45957 | AB82: =AA82-W82 -> 45957 | AC82: LO | AD82: N/A | AE82: DINGLI | AF82: COMBUSTIÓN | AG82: 78 | AH82: PLATAFORMA ARTICULADA DE COMBUSTION | AI82: DINGLI | AJ82: BA16CRT2 | AK82: BARC023J00306 | AL82: 10 | AM82: 02 | AN82: 2024 | AO82: 36000 | AP82: 52500 | BZ82: ='CONTROL DE RENTAS'!$Z82-'CONTROL DE RENTAS'!$AA82 -> -45957 | CA82: =IF(BZ82>=7,"VIGENTE","POR VENCER") -> POR VENCER
A83: 79 | B83: 2055 | C83: 2291-2299 | D83: 2373-2461 | F83: 2671-2700 | G83: 2855 | J83: 3309 | O83: DENTRO | P83: 5711 | Q83: SALTERRA | R83: YAZMIN VARGAS | S83: NEMAK, GARCIA | T83: 853 | U83: CARLOS | V83: 1 | W83: 45904 | X83: 27 | Y83: 79 | Z83: =W83+X83 -> 45931 | AA83: =TODAY() -> 45957 | AB83: =AA83-W83 -> 53 | AC83: LO | AD83: N/A | AE83: DINGLI | AF83: COMBUSTIÓN | AG83: 79 | AH83: PLATAFORMA ARTICULADA DE COMBUSTION | AI83: DINGLI | AJ83: BA16CRT2 | AK83: BARC023J00307 | AL83: 10 | AM83: 02 | AN83: 2024 | AO83: 36000 | AP83: 18000 | AT83: DIRECTA | AU83: 45876 | BZ83: ='CONTROL DE RENTAS'!$Z83-'CONTROL DE RENTAS'!$AA83 -> -26 | CA83: =IF(BZ83>=7,"VIGENTE","POR VENCER") -> POR VENCER
A84: 80 | O84: DISPONIBLE | V84: 1 | Y84: 80 | Z84: =W84+X84 -> 0 | AA84: =TODAY() -> 45957 | AB84: =AA84-W84 -> 45957 | AC84: COMYMAQ | AD84: N/A | AE84: COMYMAQ | AF84: COMBUSTIÓN | AG84: 80 | AH84: TORRE DE ILUMINACION | AI84: SDMO | AJ84: RL6_1B | AK84: RL6_1B12007487 | AL84: 50 | AM84: 01 | AN84: 2012 | AO84: 12000 | AP84: 0 | BZ84: ='CONTROL DE RENTAS'!$Z84-'CONTROL DE RENTAS'!$AA84 -> -45957 | CA84: =IF(BZ84>=7,"VIGENTE","POR VENCER") -> POR VENCER
A85: 81 | O85: DISPONIBLE | V85: 1 | Y85: 81 | Z85: =W85+X85 -> 0 | AA85: =TODAY() -> 45957 | AB85: =AA85-W85 -> 45957 | AC85: COMYMAQ | AD85: N/A | AE85: COMYMAQ | AF85: COMBUSTIÓN | AG85: 81 | AH85: TORRE DE ILUMINACION | AI85: SDMO | AJ85: RL6_1B | AK85: RL6_1B12004116 | AL85: 50 | AM85: 01 | AN85: 2012 | AO85: 12000 | AP85: 0 | BZ85: ='CONTROL DE RENTAS'!$Z85-'CONTROL DE RENTAS'!$AA85 -> -45957 | CA85: =IF(BZ85>=7,"VIGENTE","POR VENCER") -> POR VENCER
A86: 82 | K86: 3587 | O86: DENTRO | P86: 5907 | Q86: PROYECTOS Y CONSTRUCCIONES SIERRA MADRE | R86: ALFFONSO SANCHEZ | S86: PROSPERITY 1 | T86: 3 | U86: JORGE | V86: 1 | W86: 45951 | X86: 27 | Y86: 82 | Z86: =W86+X86 -> 45978 | AA86: =TODAY() -> 45957 | AB86: =AA86-W86 -> 6 | AC86: COMYMAQ | AD86: N/A | AE86: COMYMAQ | AF86: COMBUSTIÓN | AG86: 82 | AH86: TORRE DE ILUMINACION | AI86: SDMO | AJ86: RL6_1B | AK86: RL6_1B12008593 | AL86: 50 | AM86: 01 | AN86: 2012 | AO86: 12000 | AP86: 0 | AT86: DIRECTA | AU86: 45951 | BZ86: ='CONTROL DE RENTAS'!$Z86-'CONTROL DE RENTAS'!$AA86 -> 21 | CA86: =IF(BZ86>=7,"VIGENTE","POR VENCER") -> VIGENTE
A87: 83 | O87: DISPONIBLE | V87: 1 | Y87: 83 | Z87: =W87+X87 -> 0 | AA87: =TODAY() -> 45957 | AB87: =AA87-W87 -> 45957 | AC87: COMYMAQ | AD87: N/A | AE87: COMYMAQ | AF87: COMBUSTIÓN | AG87: 83 | AH87: TORRE DE ILUMINACION | AI87: SDMO | AJ87: RL6_1B | AK87: RL6_1B11003373 | AL87: 50 | AM87: 01 | AN87: 2011 | AO87: 12000 | AP87: 0 | BZ87: ='CONTROL DE RENTAS'!$Z87-'CONTROL DE RENTAS'!$AA87 -> -45957 | CA87: =IF(BZ87>=7,"VIGENTE","POR VENCER") -> POR VENCER
A88: 84 | O88: DISPONIBLE | V88: 1 | Y88: 84 | Z88: =W88+X88 -> 0 | AA88: =TODAY() -> 45957 | AB88: =AA88-W88 -> 45957 | AC88: COMYMAQ | AD88: N/A | AE88: COMYMAQ | AF88: COMBUSTIÓN | AG88: 84 | AH88: TORRE DE ILUMINACION | AI88: SDMO | AJ88: RL6_1B | AK88: RL6_1B12004118 | AL88: 50 | AM88: 01 | AN88: 2012 | AO88: 12000 | AP88: 0 | BZ88: ='CONTROL DE RENTAS'!$Z88-'CONTROL DE RENTAS'!$AA88 -> -45957 | CA88: =IF(BZ88>=7,"VIGENTE","POR VENCER") -> POR VENCER
A89: 85 | B89: 2039 | O89: DISPONIBLE | V89: 1 | Y89: 85 | Z89: =W89+X89 -> 0 | AA89: =TODAY() -> 45957 | AB89: =AA89-W89 -> 45957 | AC89: COMYMAQ | AD89: N/A | AE89: COMYMAQ | AF89: COMBUSTIÓN | AG89: 85 | AH89: TORRE DE ILUMINACION | AI89: SDMO | AJ89: RL6_1B | AK89: RL6_1B12008340 | AL89: 50 | AM89: 01 | AN89: 2012 | AO89: 12000 | AP89: 3467 | BZ89: ='CONTROL DE RENTAS'!$Z89-'CONTROL DE RENTAS'!$AA89 -> -45957 | CA89: =IF(BZ89>=7,"VIGENTE","POR VENCER") -> POR VENCER
A90: 86 | O90: DISPONIBLE | V90: 1 | Y90: 86 | Z90: =W90+X90 -> 0 | AA90: =TODAY() -> 45957 | AB90: =AA90-W90 -> 45957 | AC90: COMYMAQ | AD90: N/A | AE90: COMYMAQ | AF90: COMBUSTIÓN | AG90: 86 | AH90: TORRE DE ILUMINACION | AI90: SDMO | AJ90: RL6_1B | AK90: RL6_1B13005075 | AL90: 50 | AM90: 01 | AN90: 2013 | AO90: 12000 | AP90: 0 | BZ90: ='CONTROL DE RENTAS'!$Z90-'CONTROL DE RENTAS'!$AA90 -> -45957 | CA90: =IF(BZ90>=7,"VIGENTE","POR VENCER") -> POR VENCER
A91: 87 | O91: TALLER | V91: 1 | Y91: 87 | Z91: =W91+X91 -> 0 | AA91: =TODAY() -> 45957 | AB91: =AA91-W91 -> 45957 | AC91: COMYMAQ | AD91: N/A | AE91: COMYMAQ | AF91: COMBUSTIÓN | AG91: 87 | AH91: TORRE DE ILUMINACION | AI91: SDMO | AJ91: RL6_1B | AK91: RL6_1B12007220 | AL91: 50 | AM91: 01 | AN91: 2012 | AO91: 12000 | AP91: 0 | BZ91: ='CONTROL DE RENTAS'!$Z91-'CONTROL DE RENTAS'!$AA91 -> -45957 | CA91: =IF(BZ91>=7,"VIGENTE","POR VENCER") -> POR VENCER
A92: 88 | O92: TALLER | V92: 1 | Y92: 88 | Z92: =W92+X92 -> 0 | AA92: =TODAY() -> 45957 | AB92: =AA92-W92 -> 45957 | AC92: COMYMAQ | AD92: N/A | AE92: COMYMAQ | AF92: COMBUSTIÓN | AG92: 88 | AH92: TORRE DE ILUMINACION | AI92: TEREX | AJ92: RL4 | AK92: RL416J-2853 | AL92: 50 | AM92: 01 | AN92: 2016 | AO92: 15000 | AP92: 0 | BZ92: ='CONTROL DE RENTAS'!$Z92-'CONTROL DE RENTAS'!$AA92 -> -45957 | CA92: =IF(BZ92>=7,"VIGENTE","POR VENCER") -> POR VENCER
A93: 89 | O93: TALLER | V93: 1 | Y93: 89 | Z93: =W93+X93 -> 0 | AA93: =TODAY() -> 45957 | AB93: =AA93-W93 -> 45957 | AC93: COMYMAQ | AD93: N/A | AE93: COMYMAQ | AF93: COMBUSTIÓN | AG93: 89 | AH93: TORRE DE ILUMINACION | AI93: TEREX | AJ93: RL4 | AK93: RL416J-2844 | AL93: 50 | AM93: 01 | AN93: 2016 | AO93: 15000 | AP93: 0
A94: 90 | O94: TALLER | V94: 1 | Y94: 90 | Z94: =W94+X94 -> 0 | AA94: =TODAY() -> 45957 | AB94: =AA94-W94 -> 45957 | AC94: COMYMAQ | AD94: N/A | AE94: COMYMAQ | AF94: COMBUSTIÓN | AG94: 90 | AH94: TORRE DE ILUMINACION | AI94: TEREX | AJ94: RL4 | AK94: RL4J-7399 | AL94: 50 | AM94: 01 | AN94: 2012 | AO94: 15000 | AP94: 0 | BZ94: ='CONTROL DE RENTAS'!$Z94-'CONTROL DE RENTAS'!$AA94 -> -45957 | CA94: =IF(BZ94>=7,"VIGENTE","POR VENCER") -> POR VENCER
A95: 91 | O95: TALLER | V95: 1 | Y95: 91 | Z95: =W95+X95 -> 0 | AA95: =TODAY() -> 45957 | AB95: =AA95-W95 -> 45957 | AC95: COMYMAQ | AD95: N/A | AE95: COMYMAQ | AF95: COMBUSTIÓN | AG95: 91 | AH95: TORRE DE ILUMINACION | AI95: TEREX | AJ95: RL4 | AK95: RL415-251 | AL95: 50 | AM95: 01 | AN95: 2015 | AO95: 15000 | AP95: 0 | BZ95: ='CONTROL DE RENTAS'!$Z95-'CONTROL DE RENTAS'!$AA95 -> -45957 | CA95: =IF(BZ95>=7,"VIGENTE","POR VENCER") -> POR VENCER
A96: 92 | O96: TALLER | V96: 1 | Y96: 92 | Z96: =W96+X96 -> 0 | AA96: =TODAY() -> 45957 | AB96: =AA96-W96 -> 45957 | AC96: COMYMAQ | AD96: N/A | AE96: COMYMAQ | AF96: COMBUSTIÓN | AG96: 92 | AH96: TORRE DE ILUMINACION | AI96: SDMO | AJ96: RL6_1B | AK96: RL6_1B12008589 | AL96: 50 | AM96: 01 | AN96: 2015 | AO96: 12000 | AP96: 0 | BB96: 01967T | BD96: NO | BE96: N/A | BF96: SIN GPS | BG96: APLICA | BH96: 40373.67 | BJ96: =IF(BK96="mxn",BH96/#REF!,BH96) -> 40373.67 | BK96: USD | BZ96: ='CONTROL DE RENTAS'!$Z96-'CONTROL DE RENTAS'!$AA96 -> -45957 | CA96: =IF(BZ96>=7,"VIGENTE","POR VENCER") -> POR VENCER
A97: 93 | O97: TALLER | V97: 1 | Y97: 93 | Z97: =W97+X97 -> 0 | AA97: =TODAY() -> 45957 | AB97: =AA97-W97 -> 45957 | AC97: COMYMAQ | AD97: N/A | AE97: COMYMAQ | AF97: COMBUSTIÓN | AG97: 93 | AH97: TORRE DE ILUMINACION | AI97: SDMO | AJ97: RL6_1B | AK97: RL6_1B12008591 | AL97: 50 | AM97: 01 | AN97: 2015 | AO97: 12000 | AP97: 0 | BB97: 02236T | BD97: NO | BE97: N/A | BF97: SIN GPS | BG97: APLICA | BH97: 41052.42 | BJ97: =IF(BK97="mxn",BH97/#REF!,BH97) -> 41052.42 | BK97: USD | BZ97: ='CONTROL DE RENTAS'!$Z97-'CONTROL DE RENTAS'!$AA97 -> -45957 | CA97: =IF(BZ97>=7,"VIGENTE","POR VENCER") -> POR VENCER
A98: 94 | B98: 2046 | C98: 2204-2236-2281 | D98: 2471 | E98: 2578 | F98: 2615 | G98: 2769 | H98: 2931-2973-3010 | I98: 3110-3114 | J98: 3288-3436 | O98: DENTRO | P98: 5791 | Q98: PROYECTOS Y CONSTRUCCIONES SIERRA MADRE | R98: MONICA GALLEGOS | S98: PESQUERIA | T98: 5010 | U98: JORGE | V98: 1 | W98: 45931 | X98: 27 | Y98: 94 | Z98: =W98+X98 -> 45958 | AA98: =TODAY() -> 45957 | AB98: =AA98-W98 -> 26 | AC98: COMYMAQ | AD98: SEGAMAC | AE98: COMYMAQ | AF98: COMBUSTIÓN | AG98: 94 | AH98: PLATAFORMA ARTICULADA DE COMBUSTION | AI98: GENIE | AJ98: Z45/25J RT | AK98: Z452516A-55147 | AL98: 10 | AM98: 02 | AN98: 2016 | AO98: 33000 | AP98: 33000 | AQ98: =1028.72 -> 1028.72 | AR98: =AQ98*$AQ$1 -> 20324.112 | AS98: =AP98-AR98 -> 12675.888 | AT98: DIRECTA | AU98: 45903 | AX98: PESQUERIA | AY98: https://maps.app.goo.gl/nWx5js9BQptKZyZu6 | AZ98: EDUARDO DAVILA | BA98: 8182535597 | BB98: 02065T | BD98: NO | BE98: N/A | BF98: GPS | BG98: 8132399095 | BH98: 54305.48 | BJ98: =IF(BK98="mxn",BH98/#REF!,BH98) -> 54305.48 | BK98: USD | BL98: MOTOR | BZ98: ='CONTROL DE RENTAS'!$Z98-'CONTROL DE RENTAS'!$AA98 -> 1 | CA98: =IF(BZ98>=7,"VIGENTE","POR VENCER") -> POR VENCER
A99: 95 | B99: S/FACTURA | C99: S/FACTURA | D99: S/FACTURA | G99: 2886 | H99: 3061 | I99: 3251 | J99: 3310-3410 | K99: 3511 | O99: DENTRO | P99: 5893 | Q99: GRUAS Y ELEVADORES DE MAZATLAN | R99: PEDRO TORRES PEREZ | S99: WALMART REFORMA NUEVO LAREDO | T99: 493 | U99: OSCAR | V99: 1 | W99: 45946 | X99: 27 | Y99: 95 | Z99: =W99+X99 -> 45973 | AA99: =TODAY() -> 45957 | AB99: =AA99-W99 -> 11 | AC99: COMYMAQ | AD99: VIDAL | AE99: COMYMAQ | AG99: 95 | AH99: PLATAFORMA TIPO TIJERA | AI99: GENIE | AJ99: GS1930 | AK99: GS30P-178987 | AL99: 30 | AM99: 01 | AN99: 2018 | AO99: 18000 | AP99: 19500 | AQ99: =219.38 -> 219.38 | AR99: =AQ99*$AQ$1 -> 4334.2248 | AS99: =AP99-AR99 -> 15165.775 | AT99: DIRECTA | AU99: 45946 | BB99: 02881T | BC99: RELLENAS | BD99: NO | BE99: N/A | BF99: GPS | BG99: 8132399103 | BH99: 30883 | BJ99: =IF(BK99="mxn",BH99/#REF!,BH99) -> 30883 | BK99: USD | BZ99: ='CONTROL DE RENTAS'!$Z99-'CONTROL DE RENTAS'!$AA99 -> 16 | CA99: =IF(BZ99>=7,"VIGENTE","POR VENCER") -> VIGENTE
A100: 96 | B100: 2133 | D100: 2355-2423 | E100: 2477 | H100: 3002 | I100: 3163 | J100: 3333 | O100: TALLER | V100: 1 | Y100: 96 | Z100: =W100+X100 -> 0 | AA100: =TODAY() -> 45957 | AB100: =AA100-W100 -> 45957 | AC100: COMYMAQ | AD100: COMYMAQ | AE100: COMYMAQ | AF100: COMBUSTIÓN | AG100: 96 | AH100: TORRE DE ILUMINACION | AI100: WACKER | AJ100: GEN0066 | AK100: WNCLTVOIKPUM0937 | AL100: 50 | AM100: 01 | AN100: 2018 | AP100: 0 | BZ100: ='CONTROL DE RENTAS'!$Z100-'CONTROL DE RENTAS'!$AA100 -> -45957 | CA100: =IF(BZ100>=7,"VIGENTE","POR VENCER") -> POR VENCER
A101: 97 | B101: 1999-2072-2128-2155 | C101: 2193-2241 | D101: 2349-2427 | E101: 2496-2518-2540-2574 | F101: 2731 | G101: 2767 | I101: 3208-3227-3234 | J101: 3367 | K101: 3541 | O101: DENTRO | P101: 5826 | Q101: FERROMINIO DISEÑO Y CONSTRUCCION | R101: FERROMINIO DISEÑO Y CONSTRUCCION | S101: CIENEGA DE FLORES LITIO | T101: 6931 | U101: JORGE | V101: 1 | W101: 45944 | X101: 27 | Y101: 97 | Z101: =W101+X101 -> 45971 | AA101: =TODAY() -> 45957 | AB101: =AA101-W101 -> 13 | AC101: COMYMAQ | AD101: VIDAL | AE101: COMYMAQ | AF101: COMBUSTIÓN | AG101: 97 | AH101: PLATAFORMA ARTICULADA DE COMBUSTION | AI101: GENIE | AJ101: Z60/34J | AK101: Z6014-14360 | AL101: 10 | AM101: 08 | AN101: 2014 | AO101: 51000 | AP101: 52500 | AT101: DIRECTA | AU101: 45918 | BB101: 03698T | BZ101: ='CONTROL DE RENTAS'!$Z101-'CONTROL DE RENTAS'!$AA101 -> 14 | CA101: =IF(BZ101>=7,"VIGENTE","POR VENCER") -> VIGENTE
...

Sheet REVISAR
C4: DENTRO O FUERA | D4: NUMERO DE CONTRATO | E4: NOMBRE DEL CLIENTE | F4: COMPRADOR | G4: OBRA | H4: HORAS | I4: VENDEDOR | K4: FECHA INICIO DE PERIODO | L4: DIAS CONTRATADO | M4: NUMERO DE EQUIPO | N4: VENCIMIENTO DE PERIODO | O4: BALANCE POR FECHA | P4: DIAS TRANSCURRIDOS | Q4: TIPO DE NEGOCIO | R4: ASEGURADO | S4: PROVEEDOR | T4: TOTAL | U4: =M4 -> NUMERO DE EQUIPO | V4: DESCRIPCION DEL EQUIPO | W4: MARCA | X4: MODELO | Y4: NUMERO DE SERIE | AB4: AÑO | AC4: PRECIO REAL | AD4: 0 | AE4: TIPO RENTA | AF4: INICIO RENTA | AG4: REGRESO DE EQUIPO | AH4: COMENTARIOS
C5: REGRESO | D5: 5363 | E5: HEMOECO | F5: DARA SANCHEZ | G5: EN SUS INSTALACIONES | I5: CARLOS | J5: 1 | K5: 45685 | L5: 27 | M5: 1 | N5: =K5+L5 -> 45712 | O5: =TODAY() -> 45957 | P5: =O5-K5 -> 272 | Q5: COMYMAQ | S5: COMYMAQ | U5: 1 | V5: ROMPEDORA | W5: CHICAGO PNEUMATICS | X5: CP1240 | AE5: DIRECTA | AF5: 45685 | AG5: 45708 | AI5: ORDEN N°54804, JORGE MONTOYA FUSION (CAMBIO POR FALLA EL DIA 15-02-20 EQUIPO #153) (CAMBIO POR FALLA EL DIA 31-03-23 EQUIPO #140) | AJ5: USD
A6: 11041 | C6: REGRESO | D6: 5263 | E6: HEMOECO | F6: ISAIAS VALDEZ | G6: EN SUS INSTALACIONES | I6: CARLOS | J6: 1 | K6: 45674 | L6: 27 | M6: 1 | N6: =K6+L6 -> 45701 | O6: =TODAY() -> 45957 | P6: =O6-K6 -> 283 | Q6: COMYMAQ | S6: COMYMAQ | U6: 1 | V6: ROMPEDORA | W6: CHICAGO PNEUMATICS | X6: CP1240 | AE6: DIRECTA | AF6: 45646 | AG6: 45680 | AI6: INTERCAMBIO POR EQUIPO #148 EL DIA 01-02-23
B7: 11217 | C7: REGRESO | D7: 5364 | E7: HEMOECO | F7: DARA SANCHEZ | G7: EN SUS INSTALACIONES | I7: CARLOS | J7: 1 | K7: 45685 | L7: 27 | M7: 2 | N7: =K7+L7 -> 45712 | O7: =TODAY() -> 45957 | P7: =O7-K7 -> 272 | Q7: COMYMAQ | S7: COMYMAQ | U7: 2 | V7: ROMPEDORA | W7: CHICAGO PNEUMATICS | X7: CP1240 | AE7: DIRECTA | AF7: 45685 | AG7: 45708 | AI7: INTERCAMBIO POR EQUIPO #238 EL DIA 20-02-23
C8: REGRESO | D8: 5264 | E8: HEMOECO | F8: ISAIAS VALDEZ | G8: EN SUS INSTALACIONES | I8: CARLOS | J8: 1 | K8: 45674 | L8: 27 | M8: 2 | N8: =K8+L8 -> 45701 | O8: =TODAY() -> 45957 | P8: =O8-K8 -> 283 | Q8: COMYMAQ | S8: COMYMAQ | U8: 2 | V8: ROMPEDORA | W8: CHICAGO PNEUMATICS | X8: CP1240 | AE8: DIRECTA | AF8: 45646 | AG8: 45680
A9: 9494-9540 | B9: 9686 | C9: REGRESO | D9: 5344 | E9: ANGEL RAMOS DE LEON | F9: ANGEL RAMOS DE LEON | G9: TERNIUM PESQUERIA | H9: 425 | I9: CARLOS | J9: 1 | K9: 45703 | L9: 3 | M9: 27 | N9: =K9+L9 -> 45706 | O9: =TODAY() -> 45957 | P9: =O9-K9 -> 254 | Q9: COMYMAQ | R9: COMYMAQ | S9: COMYMAQ | T9: COMBUSTIÓN | U9: 27 | V9: COMPRESOR | W9: ATLAS COPCO | X9: XATS375T3 | Y9: 4500B1310CR072827 | Z9: 40 | AA9: 02 | AE9: DIRECTA | AF9: 45675 | AG9: 45707 | AI9: USD
C10: REGRESO | D10: 4857 | E10: ZINK POWER | F10: RENE LARA | G10: ZINK POWER | H10: 4279 | I10: CARLOS | J10: 1 | K10: 45713 | L10: 27 | M10: 27 | N10: 45740 | O10: 45726 | P10: 13 | Q10: COMYMAQ | R10: COMYMAQ | S10: COMYMAQ | T10: COMBUSTIÓN | U10: 27 | V10: COMPRESOR | W10: ATLAS COPCO | X10: XATS375T3 | Y10: 4500B1310CR072827 | Z10: 40 | AA10: 02 | AE10: DIRECTA | AF10: 45405 | AG10: 45724 | AH10: INTERCAMBIO DE EQUIPO # 27 POR EL # 52
C11: REGRESO | D11: 5411 | E11: ALIMENTOS SR NATURAL | F11: DOMINGO AGUILAR HERNANDEZ | G11: ESCOBEDO | H11: 8128 | I11: JORGE | J11: 1 | K11: 45720 | L11: 6 | M11: 28 | N11: 45726 | O11: 45724 | P11: 4 | Q11: COMYMAQ | R11: COMYMAQ | S11: COMYMAQ | T11: COMBUSTIÓN | U11: 28 | V11: GENERADOR DE 100KVA | W11: HIMOINSA | X11: HFW-100 T6 CEM7 VTA | Y11: 171005365 | Z11: 60 | AA11: 3 | AB11: 2017 | AE11: DIRECTA | AF11: 45720 | AG11: 45723 | AI11: INTERCAMBIO POR EQUIPO #209 EL DIA 24-04-23
C12: REGRESO | D12: 5368 | E12: ALLIANCE SPECIALIZED SYSTEMS | F12: MAYELA ORNELAS LOPEZ | G12: MERCADO LIBRE | H12: 16 | I12: JORGE | J12: 1 | K12: 45687 | L12: 6 | M12: 34 | N12: =K12+L12 -> 45693 | O12: =TODAY() -> 45957 | P12: =O12-K12 -> 270 | Q12: COMYMAQ | R12: COMYMAQ | S12: COMYMAQ | T12: ELECTRICA | U12: 34 | V12: PLATAFORMA TELESCOPICA ELECTRICA | W12: ZOOMLION | X12: ZT22JE | Y12: 07771200100P000052 | Z12: 10 | AA12: 09 | AB12: 2024 | AE12: DIRECTA | AF12: 45687 | AG12: 45692
B13: 10303 | C13: REGRESO | D13: 5293 | E13: ARENKO | F13: ALEJANDRO | I13: CARLOS | J13: 1 | K13: 45667 | L13: 6 | M13: 34 | N13: =K13+L13 -> 45673 | O13: =TODAY() -> 45957 | P13: =O13-K13 -> 290 | Q13: COMYMAQ | R13: COMYMAQ | S13: COMYMAQ | T13: ELECTRICA | U13: 34 | V13: PLATAFORMA TELESCOPICA ELECTRICA | W13: ZOOMLION | X13: ZT22JE | Y13: 07771200100P000052 | Z13: 10 | AA13: 09 | AB13: 2024 | AE13: DIRECTA | AF13: 45660 | AG13: 45673 | AI13: USD
A14: 10240 | B14: 10436 | C14: REGRESO | D14: 5348 | E14: T3RC3TO CONSTRUCCIONES | F14: OSVALDO SANCHEZ | G14: PARQUE INDUSTRIAL MARTEL SAN JAVIER | H14: 22 | I14: JORGE | J14: 1 | K14: 45708 | L14: 13 | M14: 36 | N14: =K14+L14 -> 45721 | O14: =TODAY() -> 45957 | P14: =O14-K14 -> 249 | Q14: COMYMAQ | R14: COMYMAQ | S14: COMYMAQ | T14: COMBUSTIÓN | U14: 36 | V14: PLATAFORMA TELESCOPICA DE COMBUSTION | W14: ZOOMLION | X14: ZT20J | Y14: 0771100001P000073 | Z14: 10 | AA14: 08 | AB14: 2024 | AE14: DIRECTA | AF14: 45678 | AG14: 45722
A15: 10181 | B15: 10435 | C15: REGRESO | D15: 5325 | E15: DIANA MODESTA | F15: DIANA MODESTA | G15: EN SUS INSTALACIONES | H15: 9 | I15: CARLOS | J15: 1 | K15: 45668 | L15: 6 | M15: 36 | N15: =K15+L15 -> 45674 | O15: =TODAY() -> 45957 | P15: =O15-K15 -> 289 | Q15: COMYMAQ | R15: COMYMAQ | S15: COMYMAQ | T15: COMBUSTIÓN | U15: 36 | V15: PLATAFORMA TELESCOPICA DE COMBUSTION | W15: ZOOMLION | X15: ZT20J | Y15: 0771100001P000073 | Z15: 10 | AA15: 08 | AB15: 2024 | AE15: DIRECTA | AF15: 45668 | AG15: 45675
A16: 9034 | B16: 9175 | C16: REGRESO | D16: 5158 | E16: REDISA | F16: ROCIO | G16: KRONOS | H16: 7076 | I16: CARLOS | J16: 1 | K16: 45622 | L16: 27 | M16: 40 | N16: =K16+L16 -> 45649 | O16: =TODAY() -> 45957 | P16: =O16-K16 -> 335 | Q16: COMYMAQ | R16: COMYMAQ | S16: COMYMAQ | T16: COMBUSTIÓN | U16: 40 | V16: GENERADOR DE 45KVA | W16: HIMOINSA | X16: HYW-45 T6 | Y16: 181002534 | Z16: 60 | AA16: 02 | AC16: 35000 | AD16: 0 | AE16: DIRECTA | AF16: 45594 | AG16: 45639
A17: 9180 | C17: REGRESO | D17: 5433 | E17: ALIMENTOS SR NATURAL | F17: DOMINGO JOSÉ AGUILAR | G17: SR NATURAL (GALLETAS) | H17: 9787 | I17: JORGE | J17: 1 | K17: 45730 | L17: 0 | M17: 41 | N17: =K17+L17 -> 45730 | O17: =TODAY() -> 45957 | P17: =O17-K17 -> 227 | Q17: COMYMAQ | R17: COMYMAQ | S17: COMYMAQ | T17: COMBUSTIÓN | U17: 41 | V17: GENERADOR DE 45KVA | W17: HIMOINSA | X17: HYW-45 T6 | Y17: 181002535 | Z17: 60 | AA17: 02 | AC17: 35000 | AD17: 0 | AE17: DIRECTA | AF17: 45730 | AG17: 45731
A18: 9480 | B18: 9594 | C18: REGRESO | D18: 5242 | E18: REDISA | F18: ANGELES | G18: VYNMSA SPACE B | H18: 9765 | I18: CARLOS | J18: 1 | K18: 45632 | L18: 27 | M18: 41 | N18: =K18+L18 -> 45659 | O18: =TODAY() -> 45957 | P18: =O18-K18 -> 325 | Q18: COMYMAQ | R18: COMYMAQ | S18: COMYMAQ | T18: COMBUSTIÓN | U18: 41 | V18: GENERADOR DE 45KVA | W18: HIMOINSA | X18: HYW-45 T6 | Y18: 181002535 | Z18: 60 | AA18: 02 | AC18: 35000 | AD18: 0 | AE18: DIRECTA | AF18: 45632 | AG18: 45660
A19: 9005-9013-9088 | B19: 9157 | C19: REGRESO | D19: 5334 | E19: ARENKO | F19: ALEJANDRO | G19: DLG EL CARMEN | H19: 2681 | I19: CARLOS | J19: 1 | K19: 45699 | L19: 27 | M19: 42 | N19: =K19+L19 -> 45726 | O19: =TODAY() -> 45957 | P19: =O19-K19 -> 258 | Q19: COMYMAQ | R19: COMYMAQ | S19: COMYMAQ | T19: COMBUSTIÓN | U19: 42 | V19: SOLDADORA | W19: SHINDAIWA | X19: DGW400DMS | Y19: W00255006843 | Z19: 70 | AA19: 01 | AC19: 24000 | AD19: 0 | AE19: DIRECTA | AF19: 45671 | AG19: 45724
A20: 10433 | B20: 10544 | C20: REGRESO | D20: 5294 | E20: ARENKO | F20: ALEJANDRO | G20: CONEKTA 3 | H20: 2472 | I20: CARLOS | J20: 1 | K20: 45294 | L20: 2 | M20: 42 | N20: =K20+L20 -> 45296 | O20: =TODAY() -> 45957 | P20: =O20-K20 -> 663 | Q20: COMYMAQ | R20: COMYMAQ | S20: COMYMAQ | T20: COMBUSTIÓN | U20: 42 | V20: SOLDADORA | W20: SHINDAIWA | X20: DGW400DMS | Y20: W00255006843 | Z20: 70 | AA20: 01 | AC20: 24000 | AD20: 0 | AE20: DIRECTA | AF20: 45660 | AG20: 45664
B21: 9645-9711 | C21: REGRESO | D21: 5182 | E21: ARENKO | F21: ARENKO | G21: TREDEC 12 | H21: 3031 | I21: CARLOS | J21: 1 | K21: 45663 | L21: 27 | M21: 43 | N21: =K21+L21 -> 45690 | O21: =TODAY() -> 45957 | P21: =O21-K21 -> 294 | Q21: COMYMAQ | R21: COMYMAQ | S21: COMYMAQ | T21: COMBUSTIÓN | U21: 43 | V21: SOLDADORA | W21: SHINDAIWA | X21: DGW400DMS | Y21: W00255006848 | Z21: 70 | AA21: 01 | AC21: 24000 | AD21: 0 | AE21: DIRECTA | AF21: 45607 | AG21: 45689
A22: 9153 | B22: 9291 | C22: REGRESO | D22: 5195 | E22: ARENKO | F22: ARENKO | G22: FINSA GPE NAVE EATON | H22: 384 | I22: CARLOS | J22: 1 | K22: 45699 | L22: 27 | M22: 44 | N22: =K22+L22 -> 45726 | O22: =TODAY() -> 45957 | P22: =O22-K22 -> 258 | Q22: COMYMAQ | R22: COMYMAQ | S22: COMYMAQ | T22: COMBUSTIÓN | U22: 44 | V22: SOLDADORA | W22: SHINDAIWA | X22: DGW400DMS | Y22: W00255006861 | Z22: 70 | AA22: 01 | AC22: 24000 | AD22: 0 | AE22: DIRECTA | AF22: 45615 | AG22: 45715
A23: 9645-9711 | C23: DENTRO | D23: 5183 | E23: ARENKO | F23: ARENKO | G23: CONEKTA | H23: 3274 | I23: CARLOS | J23: 1 | K23: 45607 | L23: 6 | M23: 44 | N23: =K23+L23 -> 45613 | O23: =TODAY() -> 45957 | P23: =O23-K23 -> 350 | Q23: COMYMAQ | R23: COMYMAQ | S23: COMYMAQ | T23: COMBUSTIÓN | U23: 44 | V23: SOLDADORA | W23: SHINDAIWA | X23: DGW400DMS | Y23: W00255006861 | Z23: 70 | AA23: 01 | AC23: 24000 | AD23: 0 | AE23: DIRECTA | AF23: 45607 | AG23: 45611
A24: 9002 | C24: REGRESO | D24: 5328 | E24: REDISA | F24: CRISTAL | G24: RMSG MARTEL | H24: 5378 | I24: CARLOS | J24: 1 | K24: 45698 | L24: 6 | M24: 45 | N24: 45704 | O24: 45705 | P24: 7 | Q24: COMYMAQ | R24: COMYMAQ | S24: COMYMAQ | T24: COMBUSTIÓN | U24: 45 | V24: TORRE DE ILUMINACION | W24: WAKER | X24: LTV-6L | Y24: WNCLTV01APUM02629 | Z24: 50 | AA24: 01 | AB24: 2012 | AD24: 0 | AE24: DIRECTA | AF24: 45670 | AG24: 45705
A25: 9241 | C25: TALLER | D25: 5268 | E25: SALTERRA | F25: YAZMIN VARGAS | G25: NEMAK, GARCIA | H25: 5301 | I25: CARLOS | J25: 1 | K25: 45647 | L25: 1 | M25: 45 | N25: 45648 | O25: 45653 | P25: 6 | Q25: COMYMAQ | R25: COMYMAQ | S25: COMYMAQ | T25: COMBUSTIÓN | U25: 45 | V25: TORRE DE ILUMINACION | W25: WAKER | X25: LTV-6L | Y25: WNCLTV01APUM02629 | Z25: 50 | AA25: 01 | AB25: 2012 | AD25: 0 | AE25: SUB RENTA | AF25: 45647 | AG25: 45652
A26: 9096 | C26: DENTRO | D26: 5186 | E26: REDISA | F26: ROCIO | G26: INBURSA SUCURSAL MONTERREY | H26: 5064 | I26: CARLOS | J26: 1 | K26: 45638 | L26: 13 | M26: 45 | N26: =K26+L26 -> 45651 | O26: =TODAY() -> 45957 | P26: =O26-K26 -> 319 | Q26: COMYMAQ | R26: COMYMAQ | S26: COMYMAQ | T26: COMBUSTIÓN | U26: 45 | V26: TORRE DE ILUMINACION | W26: WAKER | X26: LTV-6L | Y26: WNCLTV01APUM02629 | Z26: 50 | AA26: 01 | AB26: 2012 | AD26: 0 | AE26: DIRECTA | AF26: 45610 | AG26: 45645
A27: 9556 | B27: 9642 | C27: DENTRO | D27: 5163 | E27: REDISA | F27: ROCIO | G27: EN SUS INSTALACIONES | H27: 5010 | I27: CARLOS | J27: 1 | K27: 45596 | L27: 6 | M27: 45 | N27: =K27+L27 -> 45602 | O27: =TODAY() -> 45957 | P27: =O27-K27 -> 361 | Q27: COMYMAQ | R27: COMYMAQ | S27: COMYMAQ | T27: COMBUSTIÓN | U27: 45 | V27: TORRE DE ILUMINACION | W27: WAKER | X27: LTV-6L | Y27: WNCLTV01APUM02629 | Z27: 50 | AA27: 01 | AB27: 2012 | AD27: 0 | AE27: DIRECTA | AF27: 45596 | AG27: 45603
A28: 10154-10293 | C28: REGRESO | D28: 5132 | E28: DISTRIBUIDORA KARCEMEX | F28: ROLANDO CONTRERAS | G28: UNILEVER | H28: 5007 | I28: CARLOS | J28: 1 | K28: 45584 | L28: 6 | M28: 45 | N28: =K28+L28 -> 45590 | O28: =TODAY() -> 45957 | P28: =O28-K28 -> 373 | Q28: COMYMAQ | R28: COMYMAQ | S28: COMYMAQ | T28: COMBUSTIÓN | U28: 45 | V28: TORRE DE ILUMINACION | W28: WAKER | X28: LTV-6L | Y28: WNCLTV01APUM02629 | Z28: 50 | AA28: 01 | AB28: 2012 | AD28: 0 | AE28: DIRECTA | AF28: 45584 | AG28: 45596
B29: 9592 | C29: REGRESO | D29: 5208 | E29: GOIMSA GRUAS Y SERVICIOS | F29: GOIMSA GRUAS Y SERVICIOS | G29: REYNOSA TAMAULIPAS | H29: 3483 | I29: CARLOS | J29: 1 | K29: 45680 | L29: 27 | M29: 46 | N29: 45707 | O29: 45715 | P29: 35 | Q29: COMYMAQ | R29: COMYMAQ | S29: COMYMAQ | T29: COMBUSTIÓN | U29: 46 | V29: TORRE DE ILUMINACION | W29: WAKER | X29: LTV-6L | Y29: WNCLTV01EPUM02683 | Z29: 50 | AA29: 01 | AB29: 2012 | AC29: 12000 | AE29: DIRECTA | AF29: 45624 | AG29: 45714
A30: 9179-9215-9281 | C30: REGRESO | D30: 5137 | E30: REDISA | F30: CRISTAL | G30: DULCES NOMBRES | H30: 3408 | I30: CARLOS | J30: 1 | K30: 45600 | L30: 13 | M30: 46 | N30: =K30+L30 -> 45613 | O30: =TODAY() -> 45957 | P30: =O30-K30 -> 357 | Q30: COMYMAQ | R30: COMYMAQ | S30: COMYMAQ | T30: COMBUSTIÓN | U30: 46 | V30: TORRE DE ILUMINACION | W30: WAKER | X30: LTV-6L | Y30: WNCLTV01EPUM02683 | Z30: 50 | AA30: 01 | AB30: 2012 | AC30: 12000 | AE30: DIRECTA | AF30: 45586 | AG30: 45607
A31: 10242-10243 | C31: CANCELADO | D31: 5133 | E31: DISTRIBUIDORA KARCEMEX | F31: ROLANDO CONTRERAS | G31: UNILEVER | H31: 3407 | I31: CARLOS | J31: 1 | K31: 45584 | L31: 6 | M31: 46 | N31: =K31+L31 -> 45590 | O31: =TODAY() -> 45957 | P31: =O31-K31 -> 373 | Q31: COMYMAQ | R31: COMYMAQ | S31: COMYMAQ | T31: COMBUSTIÓN | U31: 46 | V31: TORRE DE ILUMINACION | W31: WAKER | X31: LTV-6L | Y31: WNCLTV01EPUM02683 | Z31: 50 | AA31: 01 | AB31: 2012 | AC31: 12000 | AE31: DIRECTA | AF31: 45584 | AH31: CLIENTE CANCELO CONTARTO | AJ31: USD
A32: 9002 | C32: REGRESO | D32: 5119 | E32: JULIO OVIEDO | F32: JULIO OVIEDO | G32: OBRA TRANSYS | H32: 2474 | I32: CARLOS | J32: 1 | K32: 45602 | L32: 27 | M32: 47 | N32: =K32+L32 -> 45629 | O32: =TODAY() -> 45957 | P32: =O32-K32 -> 355 | Q32: COMYMAQ | R32: COMYMAQ | S32: COMYMAQ | T32: COMBUSTIÓN | U32: 47 | V32: PLATAFORMA TIPO TIJERA | W32: GENIE | X32: GS-5390 RT | Y32: GS9015-50990 | Z32: 30 | AA32: 05 | AC32: 50000 | AD32: 0 | AE32: DIRECTA | AF32: 45574 | AG32: 45643
B33: 9645-9711 | C33: REGRESO | D33: 5359 | E33: JULIO OVIEDO | F33: JULIO OVIEDO | G33: BOTCAT | H33: 1652 | I33: CARLOS | J33: 1 | K33: 45712 | L33: 27 | M33: 48 | N33: =K33+L33 -> 45739 | O33: =TODAY() -> 45957 | P33: =O33-K33 -> 245 | Q33: COMYMAQ | R33: COMYMAQ | S33: COMYMAQ | T33: COMBUSTIÓN | U33: 48 | V33: PLATAFORMA TIPO TIJERA | W33: GENIE | X33: GS-4069 RT | Y33: GS6915-7668 | Z33: 30 | AA33: 04 | AB33: 2016 | AC33: 35000 | AD33: 0 | AE33: DIRECTA | AF33: 45712 | AG33: 45726 | AH33: INTERCAMBIO DE EQUIPO # 48 POR EL # 49
A34: 9485 | C34: TALLER | D34: 5098 | E34: OSCAR CABRERA | F34: OSCAR CABRERA | G34: NIFCO | H34: 1635 | I34: CARLOS | J34: 1 | K34: 45562 | L34: 6 | M34: 48 | N34: 45568 | O34: 45569 | P34: 7 | Q34: COMYMAQ | R34: COMYMAQ | S34: COMYMAQ | T34: COMBUSTIÓN | U34: 48 | V34: PLATAFORMA TIPO TIJERA | W34: GENIE | X34: GS-4069 RT | Y34: GS6915-7668 | Z34: 30 | AB34: 2016 | AD34: 0 | AE34: SUB RENTA | AF34: 45562
A35: 9158-9198 | C35: CANCELADO | D35: 5098 | E35: OSCAR CABRERA | F35: OSCAR CABRERA | G35: NIFCO | H35: 1645 | I35: CARLOS | J35: 1 | K35: 45569 | L35: 6 | M35: 48 | N35: =K35+L35 -> 45575 | O35: =TODAY() -> 45957 | P35: =O35-K35 -> 388 | Q35: COMYMAQ | R35: COMYMAQ | S35: COMYMAQ | T35: COMBUSTIÓN | U35: 48 | V35: PLATAFORMA TIPO TIJERA | W35: GENIE | X35: GS-4069 RT | Y35: GS6915-7668 | Z35: 30 | AA35: 04 | AB35: 2016 | AC35: 35000 | AD35: 0 | AE35: SUB RENTA | AF35: 45562 | AG35: 45573 | AI35: MXN
C36: REGRESO | D36: 5327 | E36: ASESORES Y CONSULTORES EN TECNOLOGIA | F36: ROMARIO CASTILLO GUAJARDO | G36: VYNMSA SANTA CATARINA INDUSTRIAL PARK II | H36: 2772 | I36: CARLOS | J36: 1 | K36: 45670 | L36: 27 | M36: 49 | N36: =K36+L36 -> 45697 | O36: =TODAY() -> 45957 | P36: =O36-K36 -> 287 | Q36: COMYMAQ | R36: COMYMAQ | S36: COMYMAQ | T36: COMBUSTIÓN | U36: 49 | V36: PLATAFORMA TIPO TIJERA | W36: GENIE | X36: GS-4069 RT | Y36: GS6916F-8982 | Z36: 30 | AA36: 04 | AB36: 2016 | AC36: 35000 | AD36: 0 | AE36: DIRECTA | AF36: 45670 | AG36: 45698
A37: 9153 | B37: 9291 | C37: TALLER | D37: 5039 | E37: HECTOR HUGO GARCIA ROMERO | F37: HECTOR HUGO GARCIA ROMERO | G37: PARQUE MILLENIUM | I37: JORGE | J37: 1 | K37: 45642 | L37: 6 | M37: 49 | N37: =K37+L37 -> 45648 | O37: =TODAY() -> 45957 | P37: =O37-K37 -> 315 | Q37: COMYMAQ | R37: COMYMAQ | S37: COMYMAQ | T37: COMBUSTIÓN | U37: 49 | V37: PLATAFORMA TIPO TIJERA | W37: GENIE | X37: GS-4069 RT | Y37: GS6916F-8982 | Z37: 30 | AA37: 04 | AB37: 2016 | AC37: 35000 | AD37: 0
A38: 9155 | B38: 9320 | C38: REGRESO | D38: 5397 | E38: ANDREA YAZMIN | F38: ANDREA YAZMIN | G38: TORREON | H38: 1199 | I38: JORGE | J38: 1 | K38: 45708 | L38: 27 | M38: 50 | N38: =K38+L38 -> 45735 | O38: =TODAY() -> 45957 | P38: =O38-K38 -> 249 | Q38: COMYMAQ | R38: COMYMAQ | S38: COMYMAQ | T38: COMBUSTIÓN | U38: 50 | V38: PLATAFORMA TIPO TIJERA | W38: GENIE | X38: GS-4390 RT | Y38: GS9016F-52358 | Z38: 30 | AA38: 04 | AB38: 2015 | AC38: 40000 | AD38: 0 | AE38: DIRECTA | AF38: 45708 | AG38: 45726 | AH38: INTERCAMBIO DE EQUIPO # 50 POR EL # 79
A39: 9009 | B39: 9154 | C39: REGRESO | D39: 5359 | E39: JULIO OVIEDO | F39: JULIO OVIEDO | G39: BOTCAT | H39: 1185 | I39: CARLOS | J39: 1 | K39: 45684 | L39: 27 | M39: 50 | N39: =K39+L39 -> 45711 | O39: =TODAY() -> 45957 | P39: =O39-K39 -> 273 | Q39: COMYMAQ | R39: COMYMAQ | S39: COMYMAQ | T39: COMBUSTIÓN | U39: 50 | V39: PLATAFORMA TIPO TIJERA | W39: GENIE | X39: GS-4390 RT | Y39: GS9016F-52358 | Z39: 30 | AA39: 04 | AB39: 2015 | AC39: 40000 | AD39: 0 | AE39: DIRECTA | AF39: 45684 | AG39: 45700
A40: 9931 | C40: REGRESO | D40: 5120 | E40: JULIO OVIEDO | F40: JULIO OVIEDO | G40: OBRA TRANSYS | H40: 1064 | I40: CARLOS | J40: 1 | K40: 45658 | L40: 27 | M40: 50 | N40: =K40+L40 -> 45685 | O40: =TODAY() -> 45957 | P40: =O40-K40 -> 299 | Q40: COMYMAQ | R40: COMYMAQ | S40: COMYMAQ | T40: COMBUSTIÓN | U40: 50 | V40: PLATAFORMA TIPO TIJERA | W40: GENIE | X40: GS-4390 RT | Y40: GS9016F-52358 | Z40: 30 | AA40: 04 | AB40: 2015 | AC40: 40000 | AD40: 0 | AE40: DIRECTA | AF40: 45574 | AG40: 45671 | AI40: USD
C41: DENTRO | D41: 5098 | E41: OSCAR CABRERA | F41: OSCAR CABRERA | G41: NIFCO | H41: 1064 | I41: CARLOS | J41: 1 | K41: 45562 | L41: 6 | M41: 50 | N41: =K41+L41 -> 45568 | O41: =TODAY() -> 45957 | P41: =O41-K41 -> 395 | Q41: COMYMAQ | R41: COMYMAQ | S41: COMYMAQ | T41: COMBUSTIÓN | U41: 50 | V41: PLATAFORMA TIPO TIJERA | W41: GENIE | X41: GS-4390 RT | Y41: GS9016F-52358 | Z41: 30
A42: 10239 | C42: REGRESO | D42: 5367 | E42: REDISA | F42: TADEO | G42: ANIDA | H42: 4887 | I42: CARLOS | J42: 1 | K42: 45694 | L42: 1 | M42: 51 | N42: =K42+L42 -> 45695 | O42: =TODAY() -> 45957 | P42: =O42-K42 -> 263 | Q42: COMYMAQ | R42: COMYMAQ | S42: COMYMAQ | T42: COMBUSTIÓN | U42: 51 | V42: COMPRESOR | W42: ATLAS COPCO | X42: XAS 375 | Y42: 8972 4224 87 | Z42: 40 | AA42: 02 | AC42: 51000 | AD42: 53040 | AE42: DIRECTA | AF42: 45687 | AG42: 45696 | AI42: USD
A43: 10009 | C43: REGRESO | D43: 4900 | E43: ZINK POWER | F43: RENE LARA | G43: ZINK POWER | H43: 4067 | I43: CARLOS | J43: 1 | K43: 45575 | L43: 27 | M43: 51 | N43: 45602 | O43: 45589 | P43: 14 | Q43: COMYMAQ | R43: COMYMAQ | S43: COMYMAQ | T43: COMBUSTIÓN | U43: 51 | V43: COMPRESOR | W43: ATLAS COPCO | X43: XAS 375 | Y43: 8972 4224 87 | Z43: 40 | AA43: 02 | AC43: 51000 | AD43: 53040 | AF43: 45435 | AG43: 45589
A44: 10303 | C44: REGRESO | D44: 4900 | E44: ZINK POWER | F44: RENE LARA | G44: ZINK POWER | H44: 5403 | I44: CARLOS | J44: 1 | K44: 45575 | L44: 27 | M44: 51 | N44: =K44+L44 -> 45602 | O44: =TODAY() -> 45957 | P44: =O44-K44 -> 382 | Q44: COMYMAQ | R44: COMYMAQ | S44: COMYMAQ | T44: COMBUSTIÓN | U44: 51 | V44: COMPRESOR | W44: ATLAS COPCO | X44: XAS 375 | Y44: 8972 4224 87 | Z44: 40 | AA44: 02 | AC44: 51000 | AD44: 53040 | AE44: DIRECTA | AF44: 45435 | AG44: 45618 | AH44: INTERCAMBIO DE EQUIPO # 51 POR EL # 216
A45: 9898 | B45: 10103 | C45: REGRESO | D45: 4857 | E45: ZINK POWER | F45: RENE LARA | G45: ZINK POWER | H45: 1640 | I45: CARLOS | J45: 1 | K45: 45713 | L45: 27 | M45: 52 | N45: 45740 | O45: 45722 | P45: 9 | Q45: COMYMAQ | R45: COMYMAQ | S45: COMYMAQ | T45: COMBUSTIÓN | U45: 52 | V45: COMPRESOR | W45: ATLAS COPCO | X45: XAS 375 | Y45: 8972422490 | Z45: 40 | AA45: 02 | AB45: 2012 | AC45: 51000 | AD45: 0 | AE45: DIRECTA | AF45: 45405 | AG45: 45721 | AH45: INTERCAMBIO POR EQUIPO # 52 POR EL # 27
C46: REGRESO | D46: 5078 | E46: SIME SERVICIOS | F46: JORGE AYALA | G46: SIME SERVI FDL | H46: 3883 | I46: JORGE | J46: 1 | K46: 45696 | L46: 27 | M46: 53 | N46: =K46+L46 -> 45723 | O46: =TODAY() -> 45957 | P46: =O46-K46 -> 261 | Q46: COMYMAQ | R46: N/A | S46: COMYMAQ | T46: COMBUSTIÓN | U46: 53 | V46: PLATAFORMA TELESCOPICA DE COMBUSTION | W46: GENIE | X46: S-60X | Y46: S60X14A-28910 | Z46: 20 | AA46: 01 | AB46: 2014 | AC46: 51000 | AD46: 53500 | AE46: DIRECTA | AF46: 45556 | AG46: 45709
A47: 9161-9201 | C47: REGRESO | D47: 3539 | E47: PLC Y MONTAJE INDUSTRIAL | F47: PEDRO MACIAS | G47: PCC Aerostructures Monterrey | H47: 4309 | I47: JORGE | J47: 1 | K47: 44642 | L47: 1 | M47: 53 | N47: 44643 | O47: 44644 | P47: 2 | Q47: COMYMAQ | S47: COMYMAQ | T47: COMBUSTIÓN | U47: 53 | V47: MONTACARGAS DE 5 MIL LIBRAS | W47: LIUGONG | X47: CLG2025H | Y47: ET025625 | AB47: 2012 | AC47: 21000 | AE47: DIRECTA | AF47: 44642 | AG47: 44643
A48: 10179 | C48: REGRESO | D48: 3513 | E48: SOPORTE INDUSTRIAL E INGENIERIA | F48: GUSTAVO EDUARDO | G48: DHL, CIENEGA DE FLORES | I48: JORGE | J48: 1 | K48: 44618 | L48: 1 | M48: 53 | N48: 44619 | O48: 44620 | P48: 2 | Q48: COMYMAQ | S48: COMYMAQ | T48: COMBUSTIÓN | U48: 53 | V48: MONTACARGAS DE 5 MIL LIBRAS | W48: LIUGONG | X48: CLG2025H | Y48: ET025625 | AB48: 2012 | AC48: 21000 | AE48: DIRECTA | AF48: 44618 | AG48: 44620
A49: 9171 | B49: 9314 | C49: TALLER | D49: 5202 | E49: T3RCETO CONSTRUCCIONES | F49: OSVALDO RUIZ | G49: VESTA PARK APODACA | H49: 4586 | I49: JORGE | J49: 1 | K49: 45618 | L49: 29 | M49: 54 | N49: =K49+L49 -> 45647 | O49: =TODAY() -> 45957 | P49: =O49-K49 -> 339 | Q49: COMYMAQ | R49: N/A | S49: COMYMAQ | T49: COMBUSTIÓN | U49: 54 | V49: PLATAFORMA TELESCOPICA DE COMBUSTION | W49: GENIE | X49: S-60X | Y49: S60X14A-28914 | Z49: 20 | AA49: 01 | AB49: 2014 | AC49: 51000 | AD49: 55620 | AE49: DIRECTA | AF49: 45618 | AG49: 45650
A50: 9460 | C50: CANCELADO | D50: 5196 | E50: BILDEN | F50: ALBERTO CUEVAS | G50: JOYAS DE ANAHUAC | H50: 485 | I50: JORGE | J50: 1 | K50: 45615 | L50: 27 | M50: 54 | N50: =K50+L50 -> 45642 | O50: =TODAY() -> 45957 | P50: =O50-K50 -> 342 | Q50: COMYMAQ | R50: N/A | S50: COMYMAQ | T50: COMBUSTIÓN | U50: 54 | V50: PLATAFORMA TELESCOPICA DE COMBUSTION | W50: GENIE | X50: S-60X | Y50: S60X14A-28914 | Z50: 20 | AA50: 01 | AB50: 2014 | AC50: 51000 | AD50: 55620 | AE50: DIRECTA | AF50: 45615
C51: REGRESO | D51: 5062 | E51: SALTERRA | F51: YAZMIN VARGAS | G51: NEMAK, GARCIA | H51: 4536 | I51: CARLOS | J51: 1 | K51: 45604 | L51: 6 | M51: 54 | N51: =K51+L51 -> 45610 | O51: =TODAY() -> 45957 | P51: =O51-K51 -> 353 | Q51: COMYMAQ | R51: N/A | S51: COMYMAQ | T51: COMBUSTIÓN | U51: 54 | V51: PLATAFORMA TELESCOPICA DE COMBUSTION | W51: GENIE | X51: S-60X | Y51: S60X14A-28914 | Z51: 20 | AA51: 01 | AB51: 2014 | AC51: 51000 | AD51: 55620 | AE51: DIRECTA | AF51: 45548 | AG51: 45615
A52: 9460 | C52: REGRESO | D52: 4962 | E52: IMB MONTAJES Y LAMINACION | F52: GERARDO GOMEZ | G52: ZIEMANN, PARQUE CHUY MARIA | H52: 4520 | I52: JORGE | J52: 1 | K52: 45542 | L52: 2 | M52: 54 | N52: =K52+L52 -> 45544 | O52: =TODAY() -> 45957 | P52: =O52-K52 -> 415 | Q52: COMYMAQ | R52: N/A | S52: COMYMAQ | T52: COMBUSTIÓN | U52: 54 | V52: PLATAFORMA TELESCOPICA DE COMBUSTION | W52: GENIE | X52: S-60X | Y52: S60X14A-28914 | Z52: 20 | AA52: 01 | AB52: 2014 | AG52: 45544 | AH52: DIRECTA
A53: 9107 | C53: REGRESO | D53: 5167 | E53: CELL NORTH COMPANY DE MEXICO | F53: CELL NORTH COMPANY DE MEXICO | G53: JOHNSON CONTROLS PLANTA COMPONENTES | H53: 2778 | I53: CARLOS | J53: 1 | K53: 45628 | L53: 13 | M53: 55 | N53: =K53+L53 -> 45641 | O53: =TODAY() -> 45957 | P53: =O53-K53 -> 329 | Q53: COMYMAQ | R53: N/A | S53: COMYMAQ | T53: COMBUSTIÓN | U53: 55 | V53: PLATAFORMA TELESCOPICA DE COMBUSTION | W53: GENIE | X53: S-85 | Y53: S8515-12224 | Z53: 20 | AA53: 02 | AB53: 2015 | AC53: 110000 | AD53: 0 | AE53: DIRECTA | AF53: 45597 | AG53: 45636 | AH53: INTERCAMBIO POR EQUIPO # 55 POR EL # 56
A54: 9077 | C54: REGRESO | D54: 5160 | E54: SERGIO CARRIZALES | F54: SERGIO CARRIZALES | G54: FORZASTEEL | H54: 2904 | I54: CARLOS | J54: 1 | K54: 45659 | L54: 27 | M54: 55 | N54: =K54+L54 -> 45686 | O54: =TODAY() -> 45957 | P54: =O54-K54 -> 298 | Q54: COMYMAQ | R54: N/A | S54: COMYMAQ | T54: COMBUSTIÓN | U54: 55 | V54: PLATAFORMA TELESCOPICA DE COMBUSTION | W54: GENIE | X54: S-85 | Y54: S8515-12224 | Z54: 20 | AA54: 02 | AB54: 2015 | AC54: 110000 | AD54: 0 | AE54: DIRECTA | AF54: 45595 | AG54: 45688
A55: 9104 | C55: REGRESO | D55: 5076 | E55: ALLIANCE SPECIALIZED SYSTEMS | F55: FERNANDO PAEZ | G55: PROLEC APODACA | I55: JORGE | J55: 1 | K55: 45584 | L55: 29 | M55: 55 | N55: =K55+L55 -> 45613 | O55: =TODAY() -> 45957 | P55: =O55-K55 -> 373 | Q55: COMYMAQ | R55: N/A | S55: COMYMAQ | T55: COMBUSTIÓN | U55: 55 | V55: PLATAFORMA TELESCOPICA DE COMBUSTION | W55: GENIE | X55: S-85 | Y55: S8515-12224 | Z55: 20 | AA55: 02 | AB55: 2015 | AC55: 110000 | AD55: 0 | AF55: 45554 | AG55: 45596
C56: TALLER | D56: 5167 | E56: CELL NORTH COMPANY DE MEXICO | F56: CELL NORTH COMPANY DE MEXICO | G56: JOHNSON CONTROLS PLANTA COMPONENTES | H56: 3944 | I56: CARLOS | J56: 1 | K56: 45643 | L56: 6 | M56: 56 | N56: =K56+L56 -> 45649 | O56: =TODAY() -> 45957 | P56: =O56-K56 -> 314 | Q56: COMYMAQ | R56: N/A | S56: COMYMAQ | T56: COMBUSTIÓN | U56: 56 | V56: PLATAFORMA TELESCOPICA DE COMBUSTION | W56: GENIE | X56: S-80X | Y56: S80X15-13102 | Z56: 20 | AA56: 02 | AB56: 2015 | AC56: 100000 | AD56: 109000 | AH56: DIRECTA
A57: 9189 | C57: REGRESO | D57: 5160 | E57: SERGIO CARRIZALES | F57: SERGIO CARRIZALES | G57: FORZASTEEL | H57: 3893 | I57: CARLOS | J57: 1 | K57: 45623 | L57: 10 | M57: 56 | N57: =K57+L57 -> 45633 | O57: =TODAY() -> 45957 | P57: =O57-K57 -> 334 | Q57: COMYMAQ | R57: N/A | S57: COMYMAQ | T57: COMBUSTIÓN | U57: 56 | V57: PLATAFORMA TELESCOPICA DE COMBUSTION | W57: GENIE | X57: S-80X | Y57: S80X15-13102 | Z57: 20 | AA57: 02 | AB57: 2015 | AC57: 100000 | AD57: 109000 | AE57: DIRECTA | AF57: 45595 | AG57: 45610 | AH57: INTERCAMBIO DE EQUIPO # 56 POR EL # 55
A58: 9081 | C58: DISPONIBLE | D58: 5076 | E58: ALLIANCE SPECIALIZED SYSTEMS | F58: FERNANDO PAEZ | G58: PROLEC APODACA | H58: 3883 | I58: JORGE | J58: 1 | K58: 45554 | L58: 29 | M58: 56 | N58: =K58+L58 -> 45583 | O58: =TODAY() -> 45957 | P58: =O58-K58 -> 403 | Q58: COMYMAQ | R58: N/A | S58: COMYMAQ | T58: COMBUSTIÓN | U58: 56 | V58: PLATAFORMA TELESCOPICA DE COMBUSTION | W58: GENIE | X58: S-80X | Y58: S80X15-13102 | Z58: 20 | AA58: 02 | AB58: 2015 | AC58: 90000 | AD58: 109000
A59: 9560-9561 | C59: REGRESO | D59: 5279 | E59: TEGMESA | F59: GLADIS HERNANDEZ | G59: NAVE EXPORTACIONES | H59: 283 | I59: CARLOS | J59: 1 | K59: 45703 | L59: 27 | M59: 58 | N59: =K59+L59 -> 45730 | O59: =TODAY() -> 45957 | P59: =O59-K59 -> 254 | Q59: LO | R59: SEGAMAC | S59: SEGAMAC | T59: COMBUSTIÓN | U59: 58 | V59: PLATAFORMA ARTICULADA DE COMBUSTION | W59: ZOOMLION | X59: ZA14J | Y59: 0773400000P000439 | Z59: 10 | AA59: 02 | AB59: 2024 | AC59: 33000 | AD59: 39200 | AE59: DIRECTA | AF59: 46012 | AG59: 45731
A60: 9057-9058-9059-9129--9130 | B60: 9190-9191-9207 | C60: REGRESO | D60: 5255 | E60: PLASTICOS Y FIBRAS DE MEXICO | F60: PLASTICOS Y FIBRAS DE MEXICO | G60: EN SUS INSTALACIONES | H60: 278 | I60: CARLOS | J60: 1 | K60: 45639 | L60: 6 | M60: 58 | N60: =K60+L60 -> 45645 | O60: =TODAY() -> 45957 | P60: =O60-K60 -> 318 | Q60: LO | R60: SEGAMAC | S60: SEGAMAC | T60: COMBUSTIÓN | U60: 58 | V60: PLATAFORMA ARTICULADA DE COMBUSTION | W60: ZOOMLION | X60: ZA14J | Y60: 0773400000P000439 | Z60: 10 | AA60: 02 | AB60: 2024 | AC60: 33000 | AD60: 39200 | AE60: DIRECTA | AF60: 45639 | AG60: 45642 | AH60: INTERCAMBIO POR EQUIPO # 58 POR EL # 204
A61: 9042 | C61: REGRESO | D61: 4991 | E61: ALLIANCE SPECIALIZED SYSTEMS | F61: FRANCISCO PRECIADO | G61: LG, MAGNA - RAMOS ARIZPE | H61: 178 | I61: JORGE | J61: 1 | K61: 45623 | L61: 29 | M61: 58 | N61: =K61+L61 -> 45652 | O61: =TODAY() -> 45957 | P61: =O61-K61 -> 334 | Q61: LO | R61: SEGAMAC | S61: SEGAMAC | T61: COMBUSTIÓN | U61: 58 | V61: PLATAFORMA ARTICULADA DE COMBUSTION | W61: ZOOMLION | X61: ZA14J | Y61: 0773400000P000439 | Z61: 10 | AA61: 02 | AB61: 2024 | AC61: 33000 | AD61: 39200 | AE61: DIRECTA | AF61: 45503 | AG61: 45637
A62: 9373 | B62: 9468 | C62: REGRESO | D62: 4898 | E62: NONACSA | F62: Montserrat Camelo | G62: Avante, Santa Rosa | H62: 0 | I62: EDDY | J62: 1 | K62: 45493 | L62: 6 | M62: 58 | N62: 45499 | O62: 45500 | P62: 7 | Q62: LO | R62: SEGAMAC | S62: SEGAMAC | T62: COMBUSTIÓN | U62: 58 | V62: PLATAFORMA ARTICULADA DE COMBUSTION | W62: ZOOMLION | X62: ZA14J | Y62: 0773400000P000439 | Z62: 10 | AA62: 02 | AB62: 2024 | AD62: 0 | AE62: DIRECTA | AF62: 45430 | AG62: 45439
C63: REGRESO | D63: 5130 | E63: MONARCH QRO | F63: MERCEDES GARCIA | G63: PARQUE INDUSTRIAL FINSA | H63: 282 | I63: CARLOS | J63: 1 | K63: 45583 | L63: 3 | M63: 59 | N63: =K63+L63 -> 45586 | O63: =TODAY() -> 45957 | P63: =O63-K63 -> 374 | Q63: LO | R63: SEGAMAC | S63: SEGAMAC | T63: COMBUSTIÓN | U63: 59 | V63: PLATAFORMA ARTICULADA DE COMBUSTION | W63: ZOOMLION | X63: ZA14J | Y63: 0773400000P000440 | Z63: 10 | AA63: 02 | AB63: 2024 | AC63: 33000 | AD63: 39020 | AE63: DIRECTA | AF63: 45583 | AG63: 45587
A64: 9011-9099 | C64: REGRESO | D64: 5029 | E64: VTA SOLUTIONS | F64: RAUL RODRIGUEZ | G64: TORO, DULCES NOMBRES | H64: 208 | I64: CARLOS | J64: 1 | K64: 45554 | L64: 27 | M64: 59 | N64: 45581 | O64: 45583 | P64: 29 | Q64: LO | R64: SEGAMAC | S64: SEGAMAC | T64: COMBUSTIÓN | U64: 59 | V64: PLATAFORMA ARTICULADA DE COMBUSTION | W64: ZOOMLION | X64: ZA14J | Y64: 0773400000P000440 | Z64: 10 | AA64: 02 | AB64: 2024 | AC64: 33000 | AD64: 39020 | AE64: DIRECTA | AF64: 45554 | AG64: 45582
A65: 9051-9052-9053-9108-9123 | C65: REGRESO | D65: 5009 | E65: INTERNATIONAL METAL B. | F65: KARLA LOZANO | G65: Avante, Santa Rosa | H65: 200 | I65: JORGE | J65: 1 | K65: 45518 | L65: 6 | M65: 59 | N65: 45524 | O65: 45526 | P65: 8 | Q65: LO | R65: SEGAMAC | S65: SEGAMAC | T65: COMBUSTIÓN | U65: 59 | V65: PLATAFORMA ARTICULADA DE COMBUSTION | W65: ZOOMLION | X65: ZA14J | Y65: 0773400000P000440 | Z65: 10 | AA65: 02 | AB65: 2024 | AC65: 33000 | AD65: 0 | AE65: DIRECTA | AF65: 45518 | AG65: 45526
A66: 9004 | C66: REGRESO | D66: 4977 | E66: MAURICIO URIEL | F66: MAURICIO URIEL | G66: RAMOS ARIZPE | H66: 157 | I66: CARLOS | J66: 1 | K66: 45495 | L66: 13 | M66: 59 | N66: 45508 | O66: 45512 | P66: 17 | Q66: LO | R66: SEGAMAC | S66: SEGAMAC | T66: COMBUSTIÓN | U66: 59 | V66: PLATAFORMA ARTICULADA DE COMBUSTION | W66: ZOOMLION | X66: ZA14J | Y66: 0773400000P000440 | Z66: 10 | AA66: 02 | AB66: 2024 | AC66: 33000 | AD66: 0 | AE66: DIRECTA | AF66: 45495 | AG66: 45511
A67: 10741 | B67: 10935 | C67: REGRESO | D67: 4887 | E67: Roberto Betancourt | F67: Roberto Betancourt | G67: AVANTE AEROPUERTO | H67: 1445 | I67: CARLOS | J67: 1 | K67: 45455 | L67: 27 | M67: 59 | N67: 45482 | O67: 45484 | P67: 29 | Q67: LO | R67: SEGAMAC | S67: SEGAMAC | T67: COMBUSTIÓN | U67: 59 | V67: PLATAFORMA ARTICULADA DE COMBUSTION | W67: ZOOMLION | X67: ZA14J | Y67: 0773400000P000440 | Z67: 10 | AA67: 02 | AB67: 2024 | AC67: 33000 | AD67: 35200 | AE67: DIRECTA | AF67: 45426 | AG67: 45483
C68: REGRESO | D68: 5266 | E68: ALLIANCE SPECIALIZED SYSTEMS | F68: MAYELA ORNELAS LOPEZ | G68: EATON, FINSA | H68: 477 | I68: JORGE | J68: 1 | K68: 45676 | L68: 29 | M68: 60 | N68: =K68+L68 -> 45705 | O68: =TODAY() -> 45957 | P68: =O68-K68 -> 281 | Q68: LO | R68: SEGAMAC | S68: SEGAMAC | T68: COMBUSTIÓN | U68: 60 | V68: PLATAFORMA ARTICULADA DE COMBUSTION | W68: ZOOMLION | X68: ZA14J | Y68: 0773400000P000437 | Z68: 10 | AA68: 02 | AB68: 2024 | AC68: 33000 | AD68: 33000 | AE68: DIRECTA | AF68: 45676 | AG68: 45709 | AH68: INTERCAMBIO POR EQUIPO # 60 POR EL # 156
C69: REGRESO | D69: 5041 | E69: ALLIANCE SPECIALIZED SYSTEMS | F69: FRANCISCO PRECIADO | G69: LG, MAGNA - RAMOS ARIZPE | H69: 335 | I69: JORGE | J69: 1 | K69: 45622 | L69: 29 | M69: 60 | N69: =K69+L69 -> 45651 | O69: =TODAY() -> 45957 | P69: =O69-K69 -> 335 | Q69: LO | R69: SEGAMAC | S69: SEGAMAC | T69: COMBUSTIÓN | U69: 60 | V69: PLATAFORMA ARTICULADA DE COMBUSTION | W69: ZOOMLION | X69: ZA14J | Y69: 0773400000P000437 | Z69: 10 | AA69: 02 | AB69: 2024 | AC69: 33000 | AD69: 33000 | AE69: DIRECTA | AF69: 45531 | AG69: 45637
A70: 10469 | C70: REGRESO | D70: 4880 | E70: NONACSA | F70: Montserrat Camelo | G70: Avante, Santa Rosa | H70: 0 | I70: EDDY | J70: 1 | K70: 45525 | L70: 1 | M70: 60 | N70: 45526 | O70: 45528 | P70: 3 | Q70: LO | R70: SEGAMAC | S70: SEGAMAC | T70: COMBUSTIÓN | U70: 60 | V70: PLATAFORMA ARTICULADA DE COMBUSTION | W70: ZOOMLION | X70: ZA14J | Y70: 0773400000P000437 | Z70: 10 | AA70: 02 | AB70: 2024 | AC70: 33000 | AD70: 33000 | AE70: DIRECTA | AF70: 45418 | AG70: 45527
A71: 9082 | C71: REGRESO | D71: 5267 | E71: TEGMESA | F71: GLADIS HERNANDEZ | G71: NAVE EXPORTACIONES | H71: 490 | I71: CARLOS | J71: 1 | K71: 45702 | L71: 27 | M71: 61 | N71: =K71+L71 -> 45729 | O71: =TODAY() -> 45957 | P71: =O71-K71 -> 255 | Q71: LO | R71: SEGAMAC | S71: SEGAMAC | T71: COMBUSTIÓN | U71: 61 | V71: PLATAFORMA ARTICULADA DE COMBUSTION | W71: ZOOMLION | X71: ZA14J | Y71: 0773400000P000438 | Z71: 10 | AA71: 02 | AB71: 2024 | AC71: 33000 | AD71: 33000 | AE71: DIRECTA | AF71: 46012 | AG71: 45734
A72: 9354 | C72: REGRESO | D72: 4881 | E72: ADAN REYES MORENO | F72: ADAN REYES MORENO | G72: GUADALUPE | H72: 0 | I72: EDDY | J72: 1 | K72: 45616 | L72: 27 | M72: 61 | N72: =K72+L72 -> 45643 | O72: =TODAY() -> 45957 | P72: =O72-K72 -> 341 | Q72: LO | R72: SEGAMAC | S72: SEGAMAC | T72: COMBUSTIÓN | U72: 61 | V72: PLATAFORMA ARTICULADA DE COMBUSTION | W72: ZOOMLION | X72: ZA14J | Y72: 0773400000P000438 | Z72: 10 | AA72: 02 | AB72: 2024 | AC72: 33000 | AD72: 33000 | AE72: DIRECTA | AF72: 45420 | AG72: 45644
A73: 9119 | B73: 9205 | C73: REGRESO | D73: 5360 | E73: REDISA | F73: CRISTAL | G73: RMSG MARTEL | H73: 6547 | I73: CARLOS | J73: 1 | K73: 45726 | L73: 1 | M73: 62 | N73: 45727 | O73: 45728 | P73: 2 | Q73: COMYMAQ | R73: N/A | S73: COMYMAQ | T73: COMBUSTIÓN | U73: 62 | V73: TORRE DE ILUMINACION | W73: TEREX | X73: AL4060 | Y73: GKF-22377 | Z73: 50 | AA73: 01 | AB73: 2022 | AD73: 0 | AE73: DIRECTA | AF73: 45684 | AG73: 45728
A74: 10770 | B74: 10962 | C74: REGRESO | D74: 5250 | E74: RENTAL DEPOT | F74: ALEJANDRA BAÑUELOS | G74: PARQUE FINSA GUADALUPE | H74: 6532 | I74: CARLOS | J74: 1 | K74: 45636 | L74: 29 | M74: 62 | N74: =K74+L74 -> 45665 | O74: =TODAY() -> 45957 | P74: =O74-K74 -> 321 | Q74: COMYMAQ | R74: N/A | S74: COMYMAQ | T74: COMBUSTIÓN | U74: 62 | V74: TORRE DE ILUMINACION | W74: TEREX | X74: AL4060 | Y74: GKF-22377 | Z74: 50 | AA74: 01 | AB74: 2022 | AD74: 0 | AE74: DIRECTA | AF74: 45636 | AG74: 45643 | AH74: INTERCAMBIO POR EQUIPO # 62 POR EL # 85
A75: 9023-9086 | C75: REGRESO | D75: 5124 | E75: REDISA | F75: CRISTAL | G75: DULCES NOMBRES | H75: 6411 | I75: CARLOS | J75: 1 | K75: 45607 | L75: 6 | M75: 62 | N75: =K75+L75 -> 45613 | O75: =TODAY() -> 45957 | P75: =O75-K75 -> 350 | Q75: COMYMAQ | R75: N/A | S75: COMYMAQ | T75: COMBUSTIÓN | U75: 62 | V75: TORRE DE ILUMINACION | W75: TEREX | X75: AL4060 | Y75: GKF-22377 | Z75: 50 | AA75: 01 | AB75: 2022 | AD75: 0 | AE75: DIRECTA | AF75: 14 | AG75: 45607
A76: 9023-9086 | C76: TALLER | D76: 5269 | E76: SALTERRA | F76: YAZMIN VARGAS | G76: NEMAK, GARCIA | I76: CARLOS | J76: 1 | K76: 45647 | L76: 1 | M76: 63 | N76: =K76+L76 -> 45648 | O76: =TODAY() -> 45957 | P76: =O76-K76 -> 310 | Q76: COMYMAQ | R76: N/A | S76: COMYMAQ | T76: COMBUSTIÓN | U76: 63 | V76: TORRE DE ILUMINACION | W76: TEREX | X76: AL4060 | Y76: GKF-22372 | Z76: 50 | AA76: 01 | AB76: 2022 | AD76: 0 | AE76: SUB RENTA | AF76: 45647 | AG76: 45653
A77: 9203 | C77: REGRESO | D77: 5249 | E77: GRUPO TREGO | F77: GRUPO TREGO | G77: PARQUE INDUSTRIAL HOUSAN | H77: 7694 | I77: JORGE | J77: 1 | K77: 45636 | L77: 6 | M77: 63 | N77: =K77+L77 -> 45642 | O77: =TODAY() -> 45957 | P77: =O77-K77 -> 321 | Q77: COMYMAQ | R77: N/A | S77: COMYMAQ | T77: COMBUSTIÓN | U77: 63 | V77: TORRE DE ILUMINACION | W77: TEREX | X77: AL4060 | Y77: GKF-22372 | Z77: 50 | AA77: 01 | AB77: 2022 | AD77: 0 | AE77: DIRECTA | AF77: 45636 | AG77: 45644
A78: 11035-11121 | B78: 11228 | C78: REGRESO | D78: 5215 | E78: MANTELEK | F78: CARLOS SIERRA | G78: SIELEK SANTA CATARINA | H78: 7686 | I78: CARLOS | J78: 1 | K78: 45625 | L78: 6 | M78: 63 | N78: 45631 | O78: 45629 | P78: 4 | Q78: COMYMAQ | R78: N/A | S78: COMYMAQ | T78: COMBUSTIÓN | U78: 63 | V78: TORRE DE ILUMINACION | W78: TEREX | X78: AL4060 | Y78: GKF-22372 | Z78: 50 | AA78: 01 | AB78: 2022 | AD78: 0 | AE78: DIRECTA | AF78: 45625 | AG78: 45629
A79: 9894 | C79: CANCELADO | D79: 5220 | E79: MANTELEK | F79: CATARINO | G79: EN SUS INSTALACIONES | H79: 10425 | I79: CARLOS | J79: 1 | K79: 45626 | L79: 6 | M79: 64 | N79: 45632 | O79: 45629 | P79: 3 | Q79: COMYMAQ | R79: N/A | S79: COMYMAQ | T79: COMBUSTIÓN | U79: 64 | V79: TORRE DE ILUMINACION | W79: MAGNUM | X79: MLT3060M | Y79: 1001673 | Z79: 50 | AA79: 01 | AB79: 2010 | AD79: 0 | AE79: DIRECTA | AF79: 45626 | AG79: 45628 | AH79: CLIENTE CANCELO CONTRATO
B80: 10326-10401 | C80: REGRESO | D80: 5214 | E80: RENTAL DEPOT | F80: ALEJANDRA BAÑUELOS | G80: HENGLI 恒立 | H80: 1541 | I80: CARLOS | J80: 1 | K80: 45655 | L80: 29 | M80: 65 | N80: =K80+L80 -> 45684 | O80: =TODAY() -> 45957 | P80: =O80-K80 -> 302 | Q80: COMYMAQ | R80: N/A | S80: COMYMAQ | T80: COMBUSTIÓN | U80: 65 | V80: TORRE DE ILUMINACION | W80: MAGNUM | X80: MLT3060M | Y80: 0830125 | Z80: 50 | AA80: 01 | AB80: 2008 | AD80: 0 | AE80: DIRECTA | AF80: 45625 | AG80: 45685
A81: 10401 | B81: 10457 | C81: REGRESO | D81: 5162 | E81: GRUPO TREGO SERVICIOS E INGENIERIA | F81: GRUPO TREGO SERVICIOS E INGENIERIA | G81: EN SUS INSTALACIONES | H81: 1508 | I81: JORGE | J81: 1 | K81: 45604 | L81: 6 | M81: 65 | N81: =K81+L81 -> 45610 | O81: =TODAY() -> 45957 | P81: =O81-K81 -> 353 | Q81: COMYMAQ | R81: N/A | S81: COMYMAQ | T81: COMBUSTIÓN | U81: 65 | V81: TORRE DE ILUMINACION | W81: MAGNUM | X81: MLT3060M | Y81: 0830125 | Z81: 50 | AA81: 01 | AB81: 2008 | AD81: 0 | AE81: DIRECTA | AF81: 45604 | AG81: 45615
A82: 9024 | C82: DENTRO | D82: 5099 | E82: AUDITORIO MOISES | F82: IGLESIA | G82: AUDITORIO MOISES | H82: 1486 | I82: CARLOS | J82: 1 | K82: 45562 | L82: 2 | M82: 65 | N82: 45564 | O82: 45567 | P82: 5 | Q82: COMYMAQ | R82: N/A | S82: COMYMAQ | T82: COMBUSTIÓN | U82: 65 | V82: TORRE DE ILUMINACION | W82: MAGNUM | X82: MLT3060M | Y82: 0830125 | Z82: 50 | AA82: 01 | AB82: 2008 | AD82: 0 | AE82: DIRECTA | AF82: 45562 | AG82: 45565
A83: 9543 | C83: REGRESO | D83: 5017 | E83: BRANDO ZAPATA | F83: BRANDO ZAPATA | G83: AVANTE AEROPUERTO | H83: 1406 | I83: CARLOS | J83: 1 | K83: 45521 | L83: 13 | M83: 65 | N83: 45534 | O83: 45541 | P83: 20 | Q83: COMYMAQ | R83: N/A | S83: COMYMAQ | T83: COMBUSTIÓN | U83: 65 | V83: TORRE DE ILUMINACION | W83: MAGNUM | X83: MLT3060M | Y83: 0830125 | Z83: 50 | AA83: 01 | AB83: 2008 | AD83: 0 | AE83: SUB RENTA | AF83: 45521 | AG83: 45541
A84: 8994-9069 | C84: REGRESO | D84: 4825 | E84: SIRSA | F84: ARNULFO GARZA | G84: RAMOS ARIZPE | I84: EDDY | J84: 1 | K84: 45418 | L84: 27 | M84: 68 | N84: 45445 | O84: 45447 | P84: 29 | Q84: COMYMAQ | R84: N/A | S84: COMYMAQ | T84: COMBUSTIÓN | U84: 68 | V84: TORRE DE ILUMINACION | W84: WARREN POWER SYSTEMS | X84: WCW64MH | Y84: 2176 | Z84: 50 | AA84: 01 | AB84: 2006 | AC84: 15000 | AD84: 12480 | AE84: DIRECTA | AF84: 45418 | AG84: 45446
C85: REGRESO | D85: 5347 | E85: BEIN BUSINESS | F85: DALILA PIMENTEL | G85: ENVASES UNIVERSALES PLANTA INSURGENTES | H85: 40996 | I85: CARLOS | J85: 1 | K85: 45705 | L85: 6 | M85: 69 | N85: 45711 | O85: 45713 | P85: 8 | Q85: COMYMAQ | R85: VIDAL | S85: COMYMAQ | T85: ELECTRICA | U85: 69 | V85: PLATAFORMA TIPO TIJERA | W85: GENIE | X85: GS1930 | Y85: GS30P-179311 | Z85: 30 | AA85: 01 | AB85: 2018 | AC85: 18000 | AD85: 18000 | AE85: DIRECTA | AF85: 45706 | AG85: 45713
A86: 9114 | C86: TALLER | D86: 5277 | E86: EFFEM | F86: ANGEL VELAZQUEZ | G86: MARS, SANTA CATARINA | H86: 4098 | I86: CARLOS | J86: 1 | K86: 45647 | L86: 13 | M86: 69 | N86: =K86+L86 -> 45660 | O86: =TODAY() -> 45957 | P86: =O86-K86 -> 310 | Q86: COMYMAQ | R86: VIDAL | S86: COMYMAQ | T86: ELECTRICA | U86: 69 | V86: PLATAFORMA TIPO TIJERA | W86: GENIE | X86: GS1930 | Y86: GS30P-179311 | Z86: 30 | AA86: 01 | AB86: 2018 | AC86: 18000 | AD86: 18000 | AE86: DIRECTA | AF86: 45647 | AG86: 45660
A87: 9125 | C87: REGRESO | D87: 5261 | E87: JESUS ALEJANDRO REQUENA ORDAZ | F87: JESUS ALEJANDRO REQUENA ORDAZ | G87: APODACA | H87: 40987 | I87: CARLOS | J87: 1 | K87: 45644 | L87: 1 | M87: 69 | N87: =K87+L87 -> 45645 | O87: =TODAY() -> 45957 | P87: =O87-K87 -> 313 | Q87: COMYMAQ | R87: VIDAL | S87: COMYMAQ | T87: ELECTRICA | U87: 69 | V87: PLATAFORMA TIPO TIJERA | W87: GENIE | X87: GS1930 | Y87: GS30P-179311 | Z87: 30 | AA87: 01 | AB87: 2018 | AC87: 18000 | AD87: 18000 | AE87: =219.38 -> 219.38 | AF87: 45644 | AG87: 45647
A88: 9416 | C88: REGRESO | D88: 5198 | E88: ALFA MAQUINARIA | F88: MELISA ESTRADA | G88: EN SUS INSTALACIONES | H88: 40985 | I88: JORGE | J88: 1 | K88: 45617 | L88: 14 | M88: 69 | N88: 45631 | O88: 45629 | P88: 12 | Q88: COMYMAQ | R88: VIDAL | S88: COMYMAQ | T88: ELECTRICA | U88: 69 | V88: PLATAFORMA TIPO TIJERA | W88: GENIE | X88: GS1930 | Y88: GS30P-179311 | Z88: 30 | AA88: 01 | AB88: 2018 | AC88: 18000 | AD88: 18000 | AE88: DIRECTA | AF88: 45617 | AG88: 45628
C89: REGRESO | D89: 4930 | E89: CONAIR | F89: JUAN ANTONIO GARCIA | G89: VALLE MORELOS | H89: 814 | I89: JORGE | J89: 1 | K89: 45469 | L89: 6 | M89: 69 | N89: 45475 | O89: 45477 | P89: 8 | Q89: COMYMAQ | R89: VIDAL | S89: COMYMAQ | T89: ELECTRICA | U89: 69 | V89: PLATAFORMA TIPO TIJERA | W89: GENIE | X89: GS1930 | Y89: GS30P-179311 | Z89: 30 | AA89: 01 | AB89: 2018 | AC89: 18000 | AD89: 18000 | AE89: DIRECTA | AF89: 45455 | AG89: 45476
A90: 9036 | C90: REGRESO | D90: 4730 | E90: MTP MANTENIMIENTOS | F90: ROBERTO | G90: ALLEN DEL NORTE | H90: 783 | I90: CARLOS | J90: 1 | K90: 45358 | L90: 13 | M90: 69 | N90: =K90+L90 -> 45371 | O90: =TODAY() -> 45957 | P90: =O90-K90 -> 599 | Q90: COMYMAQ | R90: VIDAL | S90: COMYMAQ | T90: ELECTRICA | U90: 69 | V90: PLATAFORMA TIPO TIJERA | W90: GENIE | X90: GS1930 | Y90: GS30P-179311 | Z90: 30 | AA90: 01 | AB90: 2018 | AC90: 18000 | AD90: 18000 | AE90: DIRECTA | AF90: 45316 | AG90: 45374
A91: 9035 | C91: REGRESO | D91: 4622 | E91: JUAN ANTONIO GARCIA | F91: JUAN ANTONIO GARCIA | G91: JUAREZ | H91: 780 | I91: JORGE | J91: 1 | K91: 45240 | L91: 6 | M91: 69 | N91: 45246 | O91: 45252 | P91: 12 | Q91: COMYMAQ | R91: VIDAL | S91: SEGAMAC | T91: ELECTRICA | U91: 69 | V91: PLATAFORMA TIPO TIJERA | W91: GENIE | X91: GS1930 | Y91: GS30P-179311 | Z91: 30 | AA91: 01 | AB91: 2018 | AC91: 18000 | AE91: DIRECTA | AF91: 45240 | AG91: 45252
C92: REGRESO | D92: 4607 | E92: JESUS REQUENA | F92: JESUS REQUENA | G92: GONDI, GUADALUPE | H92: 777 | I92: CARLOS | J92: 1 | K92: 45226 | L92: 6 | M92: 69 | N92: 45232 | O92: 45236 | P92: 10 | Q92: COMYMAQ | R92: VIDAL | S92: SEGAMAC | T92: ELECTRICA | U92: 69 | V92: PLATAFORMA TIPO TIJERA | W92: GENIE | X92: GS1930 | Y92: GS30P-179311 | Z92: 30 | AA92: 01 | AB92: 2018 | AC92: 18000 | AE92: DIRECTA | AF92: 45226 | AG92: 45236
C93: REGRESO | D93: 4595 | E93: EFFEM MEXICO INC Y COMPAÑÍA | F93: GLORIA | G93: MARS, SANTA CATARINA | H93: 775 | I93: CARLOS | J93: 1 | K93: 45220 | L93: 1 | M93: 69 | N93: 45221 | O93: 45224 | P93: 4 | Q93: COMYMAQ | R93: VIDAL | S93: SEGAMAC | T93: ELECTRICA | U93: 69 | V93: PLATAFORMA TIPO TIJERA | W93: GENIE | X93: GS1930 | Y93: GS30P-179311 | Z93: 30 | AA93: 01 | AB93: 2018 | AC93: 18000 | AE93: DIRECTA | AF93: 45220 | AG93: 45223
A94: 9022-9085 | C94: REGRESO | D94: 4568 | E94: JESUS REQUENA | F94: JESUS REQUENA | G94: JHON DEERE, SAN PEDRO | H94: 775 | I94: CARLOS | J94: 1 | K94: 45206 | L94: 1 | M94: 69 | N94: 45207 | O94: 45211 | P94: 5 | Q94: COMYMAQ | R94: VIDAL | S94: SEGAMAC | T94: ELECTRICA | U94: 69 | V94: PLATAFORMA TIPO TIJERA | W94: GENIE | X94: GS1930 | Y94: GS30P-179311 | Z94: 30 | AA94: 01 | AB94: 2018 | AC94: 18000 | AE94: DIRECTA | AF94: 45206
A95: 9022-9085 | B95: 9232 | C95: REGRESO | D95: 4514 | E95: ISS FACILITY SERVICES | F95: ANGEL VELAZQUEZ | G95: MARS, SANTA CATARINA | H95: 767 | I95: CARLOS | J95: 1 | K95: 45171 | L95: 27 | M95: 69 | N95: 45198 | O95: 45206 | P95: 35 | Q95: COMYMAQ | R95: VIDAL | S95: SEGAMAC | T95: ELECTRICA | U95: 69 | V95: PLATAFORMA TIPO TIJERA | W95: GENIE | X95: GS1930 | Y95: GS30P-179311 | Z95: 30 | AA95: 01 | AB95: 2018 | AC95: 18000 | AE95: DIRECTA | AF95: 45171 | AG95: 45205
B96: r | C96: REGRESO | D96: 4456 | E96: METALES RCR | F96: JAIR | G96: JHON DEERE, SAN PEDRO | H96: 3344 | I96: APOLONIO | J96: 1 | K96: 45142 | L96: 2 | M96: 69 | N96: 45144 | O96: 45149 | P96: 7 | Q96: LO | R96: VIDAL | S96: SEGAMAC | T96: ELECTRICA | U96: 69 | V96: PLATAFORMA TIPO TIJERA | W96: GENIE | X96: GS1930 | Y96: GS30P-179311 | Z96: 30 | AA96: 01 | AB96: 2018 | AC96: 18000 | AE96: DIRECTA | AF96: 45142 | AG96: 45145
C97: REGRESO | D97: 4448 | E97: METALES RCR | F97: JAIR | G97: JHON DEERE, SAN PEDRO | H97: 765 | I97: JORGE | J97: 1 | K97: 45135 | L97: 2 | M97: 69 | N97: 45137 | O97: 45139 | P97: 4 | Q97: LO | R97: VIDAL | S97: SEGAMAC | T97: ELECTRICA | U97: 69 | V97: PLATAFORMA TIPO TIJERA | W97: GENIE | X97: GS1930 | Y97: GS30P-179311 | Z97: 30 | AA97: 01 | AB97: 2018 | AC97: 18000 | AE97: DIRECTA | AF97: 45135 | AG97: 45138
C98: REGRESO | D98: 4425 | E98: METALES RCR | F98: JAIR | G98: JHON DEERE, SAN PEDRO | H98: 762 | I98: JORGE | J98: 1 | K98: 45126 | L98: 6 | M98: 69 | N98: 45132 | O98: 45134 | P98: 8 | Q98: LO | R98: VIDAL | S98: SEGAMAC | T98: ELECTRICA | U98: 69 | V98: PLATAFORMA TIPO TIJERA | W98: GENIE | X98: GS1930 | Y98: GS30P-179311 | Z98: 30 | AA98: 01 | AB98: 2018 | AC98: 18000 | AE98: DIRECTA | AF98: 45121 | AG98: 45132
C99: REGRESO | D99: 4408 | E99: INNOVAREG | F99: ALAN LIBRADO | G99: EN SUS INSTALACIONES | H99: 752 | I99: CARLOS | J99: 1 | K99: 45113 | L99: 1 | M99: 69 | N99: 45114 | O99: 45117 | P99: 4 | Q99: LO | R99: VIDAL | S99: SEGAMAC | T99: ELECTRICA | U99: 69 | V99: PLATAFORMA TIPO TIJERA | W99: GENIE | X99: GS1930 | Y99: GS30P-179311 | Z99: 30 | AA99: 01 | AB99: 2018 | AC99: 18000 | AE99: DIRECTA | AF99: 45113 | AG99: 45115
C100: REGRESO | D100: 4383 | E100: JESUS REQUENA | F100: JESUS REQUENA | G100: BODEGA AURRERA, SANTA ROSA | H100: 756 | I100: CARLOS | J100: 1 | K100: 45093 | L100: 6 | M100: 69 | N100: 45099 | O100: 45100 | P100: 7 | Q100: LO | R100: VIDAL | S100: SEGAMAC | T100: ELECTRICA | U100: 69 | V100: PLATAFORMA TIPO TIJERA | W100: GENIE | X100: GS1930 | Y100: GS30P-179311 | Z100: 30 | AA100: 01 | AB100: 2018 | AC100: 18000 | AE100: DIRECTA | AF100: 45093 | AG100: 45099
C101: REGRESO | D101: 4369 | E101: JESUS REQUENA | F101: JESUS REQUENA | G101: FELIX U GOMEZ | H101: 755 | I101: CARLOS | J101: 1 | K101: 45087 | L101: 1 | M101: 69 | N101: 45088 | O101: 45090 | P101: 3 | Q101: LO | R101: VIDAL | S101: SEGAMAC | T101: ELECTRICA | U101: 69 | V101: PLATAFORMA TIPO TIJERA | W101: GENIE | X101: GS1930 | Y101: GS30P-179311 | Z101: 30 | AA101: 01 | AB101: 2018 | AC101: 18000 | AE101: DIRECTA | AF101: 45087 | AG101: 45089
A102: 9780-9843-9934 | B102: 9974-10012 | C102: REGRESO | D102: 4291 | E102: EDIFICACIONES METALICAS Y CUBIERTAS | F102: ROSAURA NIETO | G102: PARQUE DIAMANTE | H102: 742 | I102: JORGE | J102: 1 | K102: 45079 | L102: 11 | M102: 69 | N102: 45090 | O102: 45086 | P102: 7 | Q102: LO | R102: VIDAL | S102: SEGAMAC | T102: ELECTRICA | U102: 69 | V102: PLATAFORMA TIPO TIJERA | W102: GENIE | X102: GS1930 | Y102: GS30P-179311 | Z102: 30 | AA102: 01 | AB102: 2018 | AC102: 18000 | AE102: DIRECTA | AF102: 45037 | AG102: 45084
A103: 9012 | B103: 9160 | C103: REGRESO | D103: 4214 | E103: COPACHISA | F103: RUTH LOPEZ | G103: AMAZON, PARQUE KRONOS | H103: 733 | I103: JORGE | J103: 1 | K103: 44981 | L103: 27 | M103: 69 | N103: 45008 | O103: 45009 | P103: 28 | Q103: LO | R103: VIDAL | S103: SEGAMAC | T103: ELECTRICA | U103: 69 | V103: PLATAFORMA TIPO TIJERA | W103: GENIE | X103: GS1930 | Y103: GS30P-179311 | AB103: 2018 | AC103: 18000 | AE103: DIRECTA | AF103: 44981 | AG103: 45009
...

Sheet RENTABILIDAD GLOBAL
B2: =TODAY() -> 45957
B4: VENDEDOR | C4: EQUIPOS RENTADOS | D4: PORCENTAJE | E4: EQUIPOS COMPROMISO | F4: DIFERENCIA PARA META
B5: CARLOS | C5: =SUMIFS('CONTROL DE RENTAS'!V5:V307,'CONTROL DE RENTAS'!U5:U307,'RENTABILIDAD GLOBAL'!B5,'CONTROL DE RENTAS'!O5:O307,"DENTRO") -> 38 | D5: =C5/$C$15 -> 0.14615385 | E5: =+$C$15/5 -> 52 | F5: =C5-E5 -> -14
B6: JORGE | C6: =SUMIFS('CONTROL DE RENTAS'!V5:V307,'CONTROL DE RENTAS'!U5:U307,'RENTABILIDAD GLOBAL'!B6,'CONTROL DE RENTAS'!O5:O307,"DENTRO") -> 65 | D6: =C6/$C$15 -> 0.25 | E6: =+$C$15/5 -> 52 | F6: =C6-E6 -> 13
B7: JUAN | C7: =SUMIFS('CONTROL DE RENTAS'!V5:V307,'CONTROL DE RENTAS'!U5:U307,'RENTABILIDAD GLOBAL'!B7,'CONTROL DE RENTAS'!O5:O307,"DENTRO") -> 0 | D7: =C7/$C$15 -> 0 | E7: =+$C$15/5 -> 52 | F7: =C7-E7 -> -52
B8: OSCAR | C8: =SUMIFS('CONTROL DE RENTAS'!V4:V306,'CONTROL DE RENTAS'!U4:U306,'RENTABILIDAD GLOBAL'!B8,'CONTROL DE RENTAS'!O4:O306,"DENTRO") -> 32 | D8: =C8/$C$15 -> 0.12307692 | E8: =+$C$15/5 -> 52 | F8: =C8-E8 -> -20
B9: ARON | C9: =SUMIFS('CONTROL DE RENTAS'!V5:V307,'CONTROL DE RENTAS'!U5:U307,'RENTABILIDAD GLOBAL'!B9,'CONTROL DE RENTAS'!O5:O307,"DENTRO") -> 0 | D9: =C9/$C$15 -> 0 | E9: =+$C$15/5 -> 52 | F9: =C9-E9 -> -52
B11: TOTAL DE EQUIPOS RENTADOS | C11: =SUM(C5:C9) -> 135 | D11: =C11/$C$15 -> 0.51923077 | E11: =SUM(E5:E7) -> 156 | F11: =C11-E11 -> -21
B12: EQUIPOS DISPONIBLES | C12: {=SUM(SUMIFS('CONTROL DE RENTAS'!V2:V306,'CONTROL DE RENTAS'!O2:O306,$B$36:$B$37))} -> 75 | D12: =C12/$C$15 -> 0.28846154
B13: EQUIPOS EN TALLER EXTERNO | C13: =SUMIFS('CONTROL DE RENTAS'!V5:V307,'CONTROL DE RENTAS'!O5:O307,"TALLER EXTERNO") -> 1 | D13: =C13/$C$15 -> 0.0038461538
B14: EQUIPOS NO DISPONIBLES | C14: =SUM(SUMIFS('CONTROL DE RENTAS'!V5:V307,'CONTROL DE RENTAS'!O5:O307,"TALLER")) -> 49 | D14: =C14/$C$15 -> 0.18846154
B15: TOTAL DE EQUIPOS | C15: =SUM(C11:C14) -> 260 | D15: =C15/C15 -> 1
B17: EQUIPOS COMYMAQ | C17: =SUMIFS('CONTROL DE RENTAS'!V5:V307,'CONTROL DE RENTAS'!AC5:AC307,"COMYMAQ") -> 211 | D17: =C17/$C$15 -> 0.81153846
B18: EQUIPOS EN LEASING | C18: =SUMIFS('CONTROL DE RENTAS'!V5:V307,'CONTROL DE RENTAS'!AC5:AC307,"LO") -> 18 | D18: =C18/$C$15 -> 0.069230769
B19: EQUIPOS PROPIOS | C19: =C17+C18 -> 229 | D19: =D17+D18 -> 0.88076923
B20: EQUIPOS SUBARRENDADOS | C20: =SUMIFS('CONTROL DE RENTAS'!V5:V307,'CONTROL DE RENTAS'!AC5:AC307,"SUBARRENDADAS") -> 17 | D20: =C20/$C$15 -> 0.065384615
B21: EQUIPOS CONTRATO ESPECIAL | C21: =SUMIFS('CONTROL DE RENTAS'!V5:V307,'CONTROL DE RENTAS'!AC5:AC307,"CONTRATO ESPECIAL") -> 14 | D21: =C21/$C$15 -> 0.053846154
B22: TOTAL DE EQUIPOS | C22: =SUM(C19:C21) -> 260 | D22: =C22/C22 -> 1
B32: ESTATUS
B33: TALLER
B34: INTERCAMBIO
B35: TALLER EXTERNO
B36: DISPONIBLE
B37: INTERCAMBIO
N65: DENTRO | O65: 4502 | P65: GACSA | Q65: JOAO LEYVA | R65: EN SUS INSTALACIONES | S65: 376 | T65: APOLONIO | V65: 45169 | W65: 27
O97: 4501 | P97: ALLIANCE SPECIALIZED SYSTEMS | Q97: ROSEMBERG ALVARADO | R97: REYNOSA | S97: 2394 | T97: JORGE | V97: 45169 | W97: 29

Sheet RENTABILIDAD POR CATEGORIA
B2: =TODAY() -> 45957
B3: CATEGORIA | C3: CLASE | D3: DESCRIPCION | E3: CANTIDAD | F3: DENTRO | G3: DISPONIBLE | H3: TALLER | I3: GENERAL | J3: SEGMENTO RENTA | K3: SEGMENTO DISPONIBLE | L3: SEGMENTO TALLER | N3: SEGMENTO CLASE
B4: 10 | C4: PLATAFORMAS ARTICULADAS | J4: =SUM(F5:F14)/$E$41 -> 0.25668449
B5: 10 | C5: 01 | D5: 45 FT ELECTRICA CON JIB | E5: =SUMIFS('CONTROL DE RENTAS'!$V$42:$V$336,'CONTROL DE RENTAS'!$AL$42:$AL$336,$B5,'CONTROL DE RENTAS'!$AM$42:$AM$336,$C5) -> 18 | F5: =SUMIFS('CONTROL DE RENTAS'!$V$42:$V$336,'CONTROL DE RENTAS'!$AL$42:$AL$336,$B5,'CONTROL DE RENTAS'!$AM$42:$AM$336,$C5,'CONTROL DE RENTAS'!$O$42:$O$336,"DENTRO") -> 16 | G5: =SUMIFS('CONTROL DE RENTAS'!$V$42:$V$336,'CONTROL DE RENTAS'!$AL$42:$AL$336,$B5,'CONTROL DE RENTAS'!$AM$42:$AM$336,$C5,'CONTROL DE RENTAS'!$O$42:$O$336,"DISPONIBLE") -> 0 | H5: {=SUM(SUMIFS('CONTROL DE RENTAS'!$V$42:$V$336,'CONTROL DE RENTAS'!$AL$42:$AL$336,$B5,'CONTROL DE RENTAS'!$AM$42:$AM$336,$C5,'CONTROL DE RENTAS'!$O$42:$O$336,'RENTABILIDAD GLOBAL'!$B$33:$B$35))} -> 2 | I5: =$E5/$E$41 -> 0.096256684 | J5: =$F5/$E$41 -> 0.085561497 | K5: =$G5/$E$41 -> 0 | L5: =$H5/$E$41 -> 0.010695187 | N5: =+F5/E5 -> 0.88888889
B6: 10 | C6: 02 | D6: 45 FT COMBUSTION CON JIB | E6: =SUMIFS('CONTROL DE RENTAS'!$V$42:$V$336,'CONTROL DE RENTAS'!$AL$42:$AL$336,$B6,'CONTROL DE RENTAS'!$AM$42:$AM$336,$C6) -> 30 | F6: =SUMIFS('CONTROL DE RENTAS'!$V$42:$V$336,'CONTROL DE RENTAS'!$AL$42:$AL$336,$B6,'CONTROL DE RENTAS'!$AM$42:$AM$336,$C6,'CONTROL DE RENTAS'!$O$42:$O$336,"DENTRO") -> 18 | G6: =SUMIFS('CONTROL DE RENTAS'!$V$42:$V$336,'CONTROL DE RENTAS'!$AL$42:$AL$336,$B6,'CONTROL DE RENTAS'!$AM$42:$AM$336,$C6,'CONTROL DE RENTAS'!$O$42:$O$336,"DISPONIBLE") -> 3 | H6: {=SUM(SUMIFS('CONTROL DE RENTAS'!$V$42:$V$336,'CONTROL DE RENTAS'!$AL$42:$AL$336,$B6,'CONTROL DE RENTAS'!$AM$42:$AM$336,$C6,'CONTROL DE RENTAS'!$O$42:$O$336,'RENTABILIDAD GLOBAL'!$B$33:$B$35))} -> 9 | I6: =$E6/$E$41 -> 0.16042781 | J6: =$F6/$E$41 -> 0.096256684 | K6: =$G6/$E$41 -> 0.016042781 | L6: =$H6/$E$41 -> 0.048128342 | N6: =+F6/E6 -> 0.6
B7: 10 | C7: 03 | D7: 45 FT ELECTRICA SIN JIB | E7: =SUMIFS('CONTROL DE RENTAS'!$V$42:$V$336,'CONTROL DE RENTAS'!$AL$42:$AL$336,$B7,'CONTROL DE RENTAS'!$AM$42:$AM$336,$C7) -> 7 | F7: =SUMIFS('CONTROL DE RENTAS'!$V$42:$V$336,'CONTROL DE RENTAS'!$AL$42:$AL$336,$B7,'CONTROL DE RENTAS'!$AM$42:$AM$336,$C7,'CONTROL DE RENTAS'!$O$42:$O$336,"DENTRO") -> 5 | G7: =SUMIFS('CONTROL DE RENTAS'!$V$42:$V$336,'CONTROL DE RENTAS'!$AL$42:$AL$336,$B7,'CONTROL DE RENTAS'!$AM$42:$AM$336,$C7,'CONTROL DE RENTAS'!$O$42:$O$336,"DISPONIBLE") -> 1 | H7: {=SUM(SUMIFS('CONTROL DE RENTAS'!$V$42:$V$336,'CONTROL DE RENTAS'!$AL$42:$AL$336,$B7,'CONTROL DE RENTAS'!$AM$42:$AM$336,$C7,'CONTROL DE RENTAS'!$O$42:$O$336,'RENTABILIDAD GLOBAL'!$B$33:$B$35))} -> 1 | I7: =$E7/$E$41 -> 0.037433155 | J7: =$F7/$E$41 -> 0.026737968 | K7: =$G7/$E$41 -> 0.0053475936 | L7: =$H7/$E$41 -> 0.0053475936 | N7: =+F7/E7 -> 0.71428571
B8: 10 | C8: 04 | D8: 45 FT COMBUSTION SIN JIB | E8: =SUMIFS('CONTROL DE RENTAS'!$V$42:$V$336,'CONTROL DE RENTAS'!$AL$42:$AL$336,$B8,'CONTROL DE RENTAS'!$AM$42:$AM$336,$C8) -> 1 | F8: =SUMIFS('CONTROL DE RENTAS'!$V$42:$V$336,'CONTROL DE RENTAS'!$AL$42:$AL$336,$B8,'CONTROL DE RENTAS'!$AM$42:$AM$336,$C8,'CONTROL DE RENTAS'!$O$42:$O$336,"DENTRO") -> 1 | G8: =SUMIFS('CONTROL DE RENTAS'!$V$42:$V$336,'CONTROL DE RENTAS'!$AL$42:$AL$336,$B8,'CONTROL DE RENTAS'!$AM$42:$AM$336,$C8,'CONTROL DE RENTAS'!$O$42:$O$336,"DISPONIBLE") -> 0 | H8: {=SUM(SUMIFS('CONTROL DE RENTAS'!$V$42:$V$336,'CONTROL DE RENTAS'!$AL$42:$AL$336,$B8,'CONTROL DE RENTAS'!$AM$42:$AM$336,$C8,'CONTROL DE RENTAS'!$O$42:$O$336,'RENTABILIDAD GLOBAL'!$B$33:$B$35))} -> 0 | I8: =$E8/$E$41 -> 0.0053475936 | J8: =$F8/$E$41 -> 0.0053475936 | K8: =$G8/$E$41 -> 0 | L8: =$H8/$E$41 -> 0 | N8: =+F8/E8 -> 1
B9: 10 | C9: 05 | D9: 40 FT ELECTRICA NARROW | E9: =SUMIFS('CONTROL DE RENTAS'!$V$42:$V$336,'CONTROL DE RENTAS'!$AL$42:$AL$336,$B9,'CONTROL DE RENTAS'!$AM$42:$AM$336,$C9) -> 0 | F9: =SUMIFS('CONTROL DE RENTAS'!$V$42:$V$336,'CONTROL DE RENTAS'!$AL$42:$AL$336,$B9,'CONTROL DE RENTAS'!$AM$42:$AM$336,$C9,'CONTROL DE RENTAS'!$O$42:$O$336,"DENTRO") -> 0 | G9: =SUMIFS('CONTROL DE RENTAS'!$V$42:$V$336,'CONTROL DE RENTAS'!$AL$42:$AL$336,$B9,'CONTROL DE RENTAS'!$AM$42:$AM$336,$C9,'CONTROL DE RENTAS'!$O$42:$O$336,"DISPONIBLE") -> 0 | H9: {=SUM(SUMIFS('CONTROL DE RENTAS'!$V$42:$V$336,'CONTROL DE RENTAS'!$AL$42:$AL$336,$B9,'CONTROL DE RENTAS'!$AM$42:$AM$336,$C9,'CONTROL DE RENTAS'!$O$42:$O$336,'RENTABILIDAD GLOBAL'!$B$33:$B$35))} -> 0 | I9: =$E9/$E$41 -> 0 | J9: =$F9/$E$41 -> 0 | K9: =$G9/$E$41 -> 0 | L9: =$H9/$E$41 -> 0 | N9: 0
B10: 10 | C10: 06 | D10: 33 FT ELECTRICA | E10: =SUMIFS('CONTROL DE RENTAS'!$V$42:$V$336,'CONTROL DE RENTAS'!$AL$42:$AL$336,$B10,'CONTROL DE RENTAS'!$AM$42:$AM$336,$C10) -> 5 | F10: =SUMIFS('CONTROL DE RENTAS'!$V$42:$V$336,'CONTROL DE RENTAS'!$AL$42:$AL$336,$B10,'CONTROL DE RENTAS'!$AM$42:$AM$336,$C10,'CONTROL DE RENTAS'!$O$42:$O$336,"DENTRO") -> 0 | G10: =SUMIFS('CONTROL DE RENTAS'!$V$42:$V$336,'CONTROL DE RENTAS'!$AL$42:$AL$336,$B10,'CONTROL DE RENTAS'!$AM$42:$AM$336,$C10,'CONTROL DE RENTAS'!$O$42:$O$336,"DISPONIBLE") -> 4 | H10: {=SUM(SUMIFS('CONTROL DE RENTAS'!$V$42:$V$336,'CONTROL DE RENTAS'!$AL$42:$AL$336,$B10,'CONTROL DE RENTAS'!$AM$42:$AM$336,$C10,'CONTROL DE RENTAS'!$O$42:$O$336,'RENTABILIDAD GLOBAL'!$B$33:$B$35))} -> 1 | I10: =$E10/$E$41 -> 0.026737968 | J10: =$F10/$E$41 -> 0 | K10: =$G10/$E$41 -> 0.021390374 | L10: =$H10/$E$41 -> 0.0053475936 | N10: =+F10/E10 -> 0
B11: 10 | C11: 07 | D11: 30 FT ELECTRICA NARROW | E11: =SUMIFS('CONTROL DE RENTAS'!$V$42:$V$336,'CONTROL DE RENTAS'!$AL$42:$AL$336,$B11,'CONTROL DE RENTAS'!$AM$42:$AM$336,$C11) -> 1 | F11: =SUMIFS('CONTROL DE RENTAS'!$V$42:$V$336,'CONTROL DE RENTAS'!$AL$42:$AL$336,$B11,'CONTROL DE RENTAS'!$AM$42:$AM$336,$C11,'CONTROL DE RENTAS'!$O$42:$O$336,"DENTRO") -> 1 | G11: =SUMIFS('CONTROL DE RENTAS'!$V$42:$V$336,'CONTROL DE RENTAS'!$AL$42:$AL$336,$B11,'CONTROL DE RENTAS'!$AM$42:$AM$336,$C11,'CONTROL DE RENTAS'!$O$42:$O$336,"DISPONIBLE") -> 0 | H11: {=SUM(SUMIFS('CONTROL DE RENTAS'!$V$42:$V$336,'CONTROL DE RENTAS'!$AL$42:$AL$336,$B11,'CONTROL DE RENTAS'!$AM$42:$AM$336,$C11,'CONTROL DE RENTAS'!$O$42:$O$336,'RENTABILIDAD GLOBAL'!$B$33:$B$35))} -> 0 | I11: =$E11/$E$41 -> 0.0053475936 | J11: =$F11/$E$41 -> 0.0053475936 | K11: =$G11/$E$41 -> 0 | L11: =$H11/$E$41 -> 0 | N11: =+F11/E11 -> 1
B12: 10 | C12: 08 | D12: 60 FT COMBUSTION | E12: =SUMIFS('CONTROL DE RENTAS'!$V$42:$V$336,'CONTROL DE RENTAS'!$AL$42:$AL$336,$B12,'CONTROL DE RENTAS'!$AM$42:$AM$336,$C12) -> 8 | F12: =SUMIFS('CONTROL DE RENTAS'!$V$42:$V$336,'CONTROL DE RENTAS'!$AL$42:$AL$336,$B12,'CONTROL DE RENTAS'!$AM$42:$AM$336,$C12,'CONTROL DE RENTAS'!$O$42:$O$336,"DENTRO") -> 7 | G12: =SUMIFS('CONTROL DE RENTAS'!$V$42:$V$336,'CONTROL DE RENTAS'!$AL$42:$AL$336,$B12,'CONTROL DE RENTAS'!$AM$42:$AM$336,$C12,'CONTROL DE RENTAS'!$O$42:$O$336,"DISPONIBLE") -> 0 | H12: {=SUM(SUMIFS('CONTROL DE RENTAS'!$V$42:$V$336,'CONTROL DE RENTAS'!$AL$42:$AL$336,$B12,'CONTROL DE RENTAS'!$AM$42:$AM$336,$C12,'CONTROL DE RENTAS'!$O$42:$O$336,'RENTABILIDAD GLOBAL'!$B$33:$B$35))} -> 1 | I12: =$E12/$E$41 -> 0.042780749 | J12: =$F12/$E$41 -> 0.037433155 | K12: =$G12/$E$41 -> 0 | L12: =$H12/$E$41 -> 0.0053475936 | N12: =+F12/E12 -> 0.875
B13: 10 | C13: 09 | D13: 60 FT ELECTRICA | E13: =SUMIFS('CONTROL DE RENTAS'!$V$42:$V$336,'CONTROL DE RENTAS'!$AL$42:$AL$336,$B13,'CONTROL DE RENTAS'!$AM$42:$AM$336,$C13) -> 0 | F13: =SUMIFS('CONTROL DE RENTAS'!$V$42:$V$336,'CONTROL DE RENTAS'!$AL$42:$AL$336,$B13,'CONTROL DE RENTAS'!$AM$42:$AM$336,$C13,'CONTROL DE RENTAS'!$O$42:$O$336,"DENTRO") -> 0 | G13: =SUMIFS('CONTROL DE RENTAS'!$V$42:$V$336,'CONTROL DE RENTAS'!$AL$42:$AL$336,$B13,'CONTROL DE RENTAS'!$AM$42:$AM$336,$C13,'CONTROL DE RENTAS'!$O$42:$O$336,"DISPONIBLE") -> 0 | H13: {=SUM(SUMIFS('CONTROL DE RENTAS'!$V$42:$V$336,'CONTROL DE RENTAS'!$AL$42:$AL$336,$B13,'CONTROL DE RENTAS'!$AM$42:$AM$336,$C13,'CONTROL DE RENTAS'!$O$42:$O$336,'RENTABILIDAD GLOBAL'!$B$33:$B$35))} -> 0 | I13: =$E13/$E$41 -> 0 | J13: =$F13/$E$41 -> 0 | K13: =$G13/$E$41 -> 0 | L13: =$H13/$E$41 -> 0 | N13: 0
B14: 10 | C14: 10 | D14: 135 FT COMBUSTION CON JIB | E14: =SUMIFS('CONTROL DE RENTAS'!$V$42:$V$336,'CONTROL DE RENTAS'!$AL$42:$AL$336,$B14,'CONTROL DE RENTAS'!$AM$42:$AM$336,$C14) -> 1 | F14: =SUMIFS('CONTROL DE RENTAS'!$V$42:$V$336,'CONTROL DE RENTAS'!$AL$42:$AL$336,$B14,'CONTROL DE RENTAS'!$AM$42:$AM$336,$C14,'CONTROL DE RENTAS'!$O$42:$O$336,"DENTRO") -> 0 | G14: =SUMIFS('CONTROL DE RENTAS'!$V$42:$V$336,'CONTROL DE RENTAS'!$AL$42:$AL$336,$B14,'CONTROL DE RENTAS'!$AM$42:$AM$336,$C14,'CONTROL DE RENTAS'!$O$42:$O$336,"DISPONIBLE") -> 0 | H14: {=SUM(SUMIFS('CONTROL DE RENTAS'!$V$42:$V$336,'CONTROL DE RENTAS'!$AL$42:$AL$336,$B14,'CONTROL DE RENTAS'!$AM$42:$AM$336,$C14,'CONTROL DE RENTAS'!$O$42:$O$336,'RENTABILIDAD GLOBAL'!$B$33:$B$35))} -> 1 | I14: =$E14/$E$41 -> 0.0053475936 | J14: =$F14/$E$41 -> 0 | K14: =$G14/$E$41 -> 0 | L14: =$H14/$E$41 -> 0.0053475936 | N14: 0
B15: 20 | C15: PLATAFORMAS TELESCOPICAS | G15: =SUMIFS('CONTROL DE RENTAS'!$V$43:$V$336,'CONTROL DE RENTAS'!$AL$43:$AL$336,$B15,'CONTROL DE RENTAS'!$AM$43:$AM$336,$C15,'CONTROL DE RENTAS'!$O$43:$O$336,"DISPONIBLE") -> 0 | J15: =SUM(F16:F17)/$E$41 -> 0.026737968
B16: 20 | C16: 01 | D16: 60 FT COMBUSTION | E16: =SUMIFS('CONTROL DE RENTAS'!$V$42:$V$336,'CONTROL DE RENTAS'!$AL$42:$AL$336,$B16,'CONTROL DE RENTAS'!$AM$42:$AM$336,$C16) -> 5 | F16: =SUMIFS('CONTROL DE RENTAS'!$V$42:$V$336,'CONTROL DE RENTAS'!$AL$42:$AL$336,$B16,'CONTROL DE RENTAS'!$AM$42:$AM$336,$C16,'CONTROL DE RENTAS'!$O$42:$O$336,"DENTRO") -> 3 | G16: =SUMIFS('CONTROL DE RENTAS'!$V$42:$V$336,'CONTROL DE RENTAS'!$AL$42:$AL$336,$B16,'CONTROL DE RENTAS'!$AM$42:$AM$336,$C16,'CONTROL DE RENTAS'!$O$42:$O$336,"DISPONIBLE") -> 0 | H16: {=SUM(SUMIFS('CONTROL DE RENTAS'!$V$42:$V$336,'CONTROL DE RENTAS'!$AL$42:$AL$336,$B16,'CONTROL DE RENTAS'!$AM$42:$AM$336,$C16,'CONTROL DE RENTAS'!$O$42:$O$336,'RENTABILIDAD GLOBAL'!$B$33:$B$35))} -> 2 | I16: =$E16/$E$41 -> 0.026737968 | J16: =$F16/$E$41 -> 0.016042781 | K16: =$G16/$E$41 -> 0 | L16: =$H16/$E$41 -> 0.010695187 | N16: =+F16/E16 -> 0.6
B17: 20 | C17: 02 | D17: 80 FT COMBUSTION | E17: =SUMIFS('CONTROL DE RENTAS'!$V$42:$V$336,'CONTROL DE RENTAS'!$AL$42:$AL$336,$B17,'CONTROL DE RENTAS'!$AM$42:$AM$336,$C17) -> 5 | F17: =SUMIFS('CONTROL DE RENTAS'!$V$42:$V$336,'CONTROL DE RENTAS'!$AL$42:$AL$336,$B17,'CONTROL DE RENTAS'!$AM$42:$AM$336,$C17,'CONTROL DE RENTAS'!$O$42:$O$336,"DENTRO") -> 2 | G17: =SUMIFS('CONTROL DE RENTAS'!$V$42:$V$336,'CONTROL DE RENTAS'!$AL$42:$AL$336,$B17,'CONTROL DE RENTAS'!$AM$42:$AM$336,$C17,'CONTROL DE RENTAS'!$O$42:$O$336,"DISPONIBLE") -> 0 | H17: {=SUM(SUMIFS('CONTROL DE RENTAS'!$V$42:$V$336,'CONTROL DE RENTAS'!$AL$42:$AL$336,$B17,'CONTROL DE RENTAS'!$AM$42:$AM$336,$C17,'CONTROL DE RENTAS'!$O$42:$O$336,'RENTABILIDAD GLOBAL'!$B$33:$B$35))} -> 3 | I17: =$E17/$E$41 -> 0.026737968 | J17: =$F17/$E$41 -> 0.010695187 | K17: =$G17/$E$41 -> 0 | L17: =$H17/$E$41 -> 0.016042781 | N17: =+F17/E17 -> 0.4
B18: 30 | C18: PLATAFORMAS TIPO TIJERA | G18: =SUMIFS('CONTROL DE RENTAS'!$V$43:$V$336,'CONTROL DE RENTAS'!$AL$43:$AL$336,$B18,'CONTROL DE RENTAS'!$AM$43:$AM$336,$C18,'CONTROL DE RENTAS'!$O$43:$O$336,"DISPONIBLE") -> 0 | J18: =SUM(F19:F23)/$E$41 -> 0.07486631
B19: 30 | C19: 01 | D19: 19 FT ELECTRICA | E19: =SUMIFS('CONTROL DE RENTAS'!$V$42:$V$336,'CONTROL DE RENTAS'!$AL$42:$AL$336,$B19,'CONTROL DE RENTAS'!$AM$42:$AM$336,$C19) -> 7 | F19: =SUMIFS('CONTROL DE RENTAS'!$V$42:$V$336,'CONTROL DE RENTAS'!$AL$42:$AL$336,$B19,'CONTROL DE RENTAS'!$AM$42:$AM$336,$C19,'CONTROL DE RENTAS'!$O$42:$O$336,"DENTRO") -> 7 | G19: =SUMIFS('CONTROL DE RENTAS'!$V$42:$V$336,'CONTROL DE RENTAS'!$AL$42:$AL$336,$B19,'CONTROL DE RENTAS'!$AM$42:$AM$336,$C19,'CONTROL DE RENTAS'!$O$42:$O$336,"DISPONIBLE") -> 0 | H19: {=SUM(SUMIFS('CONTROL DE RENTAS'!$V$42:$V$336,'CONTROL DE RENTAS'!$AL$42:$AL$336,$B19,'CONTROL DE RENTAS'!$AM$42:$AM$336,$C19,'CONTROL DE RENTAS'!$O$42:$O$336,'RENTABILIDAD GLOBAL'!$B$33:$B$35))} -> 0 | I19: =$E19/$E$41 -> 0.037433155 | J19: =$F19/$E$41 -> 0.037433155 | K19: =$G19/$E$41 -> 0 | L19: =$H19/$E$41 -> 0 | N19: =+F19/E19 -> 1
B20: 30 | C20: 02 | D20: 26 FT ELECTRICA | E20: =SUMIFS('CONTROL DE RENTAS'!$V$42:$V$336,'CONTROL DE RENTAS'!$AL$42:$AL$336,$B20,'CONTROL DE RENTAS'!$AM$42:$AM$336,$C20) -> 1 | F20: =SUMIFS('CONTROL DE RENTAS'!$V$42:$V$336,'CONTROL DE RENTAS'!$AL$42:$AL$336,$B20,'CONTROL DE RENTAS'!$AM$42:$AM$336,$C20,'CONTROL DE RENTAS'!$O$42:$O$336,"DENTRO") -> 1 | G20: =SUMIFS('CONTROL DE RENTAS'!$V$42:$V$336,'CONTROL DE RENTAS'!$AL$42:$AL$336,$B20,'CONTROL DE RENTAS'!$AM$42:$AM$336,$C20,'CONTROL DE RENTAS'!$O$42:$O$336,"DISPONIBLE") -> 0 | H20: {=SUM(SUMIFS('CONTROL DE RENTAS'!$V$42:$V$336,'CONTROL DE RENTAS'!$AL$42:$AL$336,$B20,'CONTROL DE RENTAS'!$AM$42:$AM$336,$C20,'CONTROL DE RENTAS'!$O$42:$O$336,'RENTABILIDAD GLOBAL'!$B$33:$B$35))} -> 0 | I20: =$E20/$E$41 -> 0.0053475936 | J20: =$F20/$E$41 -> 0.0053475936 | K20: =$G20/$E$41 -> 0 | L20: =$H20/$E$41 -> 0 | N20: =+F20/E20 -> 1
B21: 30 | C21: 03 | D21: 32 FT ELECTRICA | E21: =SUMIFS('CONTROL DE RENTAS'!$V$42:$V$336,'CONTROL DE RENTAS'!$AL$42:$AL$336,$B21,'CONTROL DE RENTAS'!$AM$42:$AM$336,$C21) -> 4 | F21: =SUMIFS('CONTROL DE RENTAS'!$V$42:$V$336,'CONTROL DE RENTAS'!$AL$42:$AL$336,$B21,'CONTROL DE RENTAS'!$AM$42:$AM$336,$C21,'CONTROL DE RENTAS'!$O$42:$O$336,"DENTRO") -> 0 | G21: =SUMIFS('CONTROL DE RENTAS'!$V$42:$V$336,'CONTROL DE RENTAS'!$AL$42:$AL$336,$B21,'CONTROL DE RENTAS'!$AM$42:$AM$336,$C21,'CONTROL DE RENTAS'!$O$42:$O$336,"DISPONIBLE") -> 2 | H21: {=SUM(SUMIFS('CONTROL DE RENTAS'!$V$42:$V$336,'CONTROL DE RENTAS'!$AL$42:$AL$336,$B21,'CONTROL DE RENTAS'!$AM$42:$AM$336,$C21,'CONTROL DE RENTAS'!$O$42:$O$336,'RENTABILIDAD GLOBAL'!$B$33:$B$35))} -> 2 | I21: =$E21/$E$41 -> 0.021390374 | J21: =$F21/$E$41 -> 0 | K21: =$G21/$E$41 -> 0.010695187 | L21: =$H21/$E$41 -> 0.010695187 | N21: =+F21/E21 -> 0
B22: 30 | C22: 04 | D22: 40 FT ELECTRICA | E22: =SUMIFS('CONTROL DE RENTAS'!$V$42:$V$336,'CONTROL DE RENTAS'!$AL$42:$AL$336,$B22,'CONTROL DE RENTAS'!$AM$42:$AM$336,$C22) -> 7 | F22: =SUMIFS('CONTROL DE RENTAS'!$V$42:$V$336,'CONTROL DE RENTAS'!$AL$42:$AL$336,$B22,'CONTROL DE RENTAS'!$AM$42:$AM$336,$C22,'CONTROL DE RENTAS'!$O$42:$O$336,"DENTRO") -> 4 | G22: =SUMIFS('CONTROL DE RENTAS'!$V$42:$V$336,'CONTROL DE RENTAS'!$AL$42:$AL$336,$B22,'CONTROL DE RENTAS'!$AM$42:$AM$336,$C22,'CONTROL DE RENTAS'!$O$42:$O$336,"DISPONIBLE") -> 3 | H22: {=SUM(SUMIFS('CONTROL DE RENTAS'!$V$42:$V$336,'CONTROL DE RENTAS'!$AL$42:$AL$336,$B22,'CONTROL DE RENTAS'!$AM$42:$AM$336,$C22,'CONTROL DE RENTAS'!$O$42:$O$336,'RENTABILIDAD GLOBAL'!$B$33:$B$35))} -> 0 | I22: =$E22/$E$41 -> 0.037433155 | J22: =$F22/$E$41 -> 0.021390374 | K22: =$G22/$E$41 -> 0.016042781 | L22: =$H22/$E$41 -> 0 | N22: =+F22/E22 -> 0.57142857
B23: 30 | C23: 05 | D23: 53 FT COMBUSTION | E23: =SUMIFS('CONTROL DE RENTAS'!$V$42:$V$336,'CONTROL DE RENTAS'!$AL$42:$AL$336,$B23,'CONTROL DE RENTAS'!$AM$42:$AM$336,$C23) -> 3 | F23: =SUMIFS('CONTROL DE RENTAS'!$V$42:$V$336,'CONTROL DE RENTAS'!$AL$42:$AL$336,$B23,'CONTROL DE RENTAS'!$AM$42:$AM$336,$C23,'CONTROL DE RENTAS'!$O$42:$O$336,"DENTRO") -> 2 | G23: =SUMIFS('CONTROL DE RENTAS'!$V$42:$V$336,'CONTROL DE RENTAS'!$AL$42:$AL$336,$B23,'CONTROL DE RENTAS'!$AM$42:$AM$336,$C23,'CONTROL DE RENTAS'!$O$42:$O$336,"DISPONIBLE") -> 1 | H23: {=SUM(SUMIFS('CONTROL DE RENTAS'!$V$42:$V$336,'CONTROL DE RENTAS'!$AL$42:$AL$336,$B23,'CONTROL DE RENTAS'!$AM$42:$AM$336,$C23,'CONTROL DE RENTAS'!$O$42:$O$336,'RENTABILIDAD GLOBAL'!$B$33:$B$35))} -> 0 | I23: =$E23/$E$41 -> 0.016042781 | J23: =$F23/$E$41 -> 0.010695187 | K23: =$G23/$E$41 -> 0.0053475936 | L23: =$H23/$E$41 -> 0 | N23: =+F23/E23 -> 0.66666667
B24: 40 | C24: COMPRESORES | G24: =SUMIFS('CONTROL DE RENTAS'!$V$43:$V$336,'CONTROL DE RENTAS'!$AL$43:$AL$336,$B24,'CONTROL DE RENTAS'!$AM$43:$AM$336,$C24,'CONTROL DE RENTAS'!$O$43:$O$336,"DISPONIBLE") -> 0 | J24: =SUM(F25:F26)/$E$41 -> 0.010695187
B25: 40 | C25: 01 | D25: COMPRESOR 185CFM | E25: =SUMIFS('CONTROL DE RENTAS'!$V$42:$V$336,'CONTROL DE RENTAS'!$AL$42:$AL$336,$B25,'CONTROL DE RENTAS'!$AM$42:$AM$336,$C25) -> 7 | F25: =SUMIFS('CONTROL DE RENTAS'!$V$42:$V$336,'CONTROL DE RENTAS'!$AL$42:$AL$336,$B25,'CONTROL DE RENTAS'!$AM$42:$AM$336,$C25,'CONTROL DE RENTAS'!$O$42:$O$336,"DENTRO") -> 1 | G25: =SUMIFS('CONTROL DE RENTAS'!$V$42:$V$336,'CONTROL DE RENTAS'!$AL$42:$AL$336,$B25,'CONTROL DE RENTAS'!$AM$42:$AM$336,$C25,'CONTROL DE RENTAS'!$O$42:$O$336,"DISPONIBLE") -> 6 | H25: {=SUM(SUMIFS('CONTROL DE RENTAS'!$V$42:$V$336,'CONTROL DE RENTAS'!$AL$42:$AL$336,$B25,'CONTROL DE RENTAS'!$AM$42:$AM$336,$C25,'CONTROL DE RENTAS'!$O$42:$O$336,'RENTABILIDAD GLOBAL'!$B$33:$B$35))} -> 0 | I25: =$E25/$E$41 -> 0.037433155 | J25: =$F25/$E$41 -> 0.0053475936 | K25: =$G25/$E$41 -> 0.032085561 | L25: =$H25/$E$41 -> 0 | N25: =+F25/E25 -> 0.14285714
B26: 40 | C26: 02 | D26: COMPRESOR 375CFM | E26: =SUMIFS('CONTROL DE RENTAS'!$V$42:$V$336,'CONTROL DE RENTAS'!$AL$42:$AL$336,$B26,'CONTROL DE RENTAS'!$AM$42:$AM$336,$C26) -> 4 | F26: =SUMIFS('CONTROL DE RENTAS'!$V$42:$V$336,'CONTROL DE RENTAS'!$AL$42:$AL$336,$B26,'CONTROL DE RENTAS'!$AM$42:$AM$336,$C26,'CONTROL DE RENTAS'!$O$42:$O$336,"DENTRO") -> 1 | G26: =SUMIFS('CONTROL DE RENTAS'!$V$42:$V$336,'CONTROL DE RENTAS'!$AL$42:$AL$336,$B26,'CONTROL DE RENTAS'!$AM$42:$AM$336,$C26,'CONTROL DE RENTAS'!$O$42:$O$336,"DISPONIBLE") -> 1 | H26: {=SUM(SUMIFS('CONTROL DE RENTAS'!$V$42:$V$336,'CONTROL DE RENTAS'!$AL$42:$AL$336,$B26,'CONTROL DE RENTAS'!$AM$42:$AM$336,$C26,'CONTROL DE RENTAS'!$O$42:$O$336,'RENTABILIDAD GLOBAL'!$B$33:$B$35))} -> 2 | I26: =$E26/$E$41 -> 0.021390374 | J26: =$F26/$E$41 -> 0.0053475936 | K26: =$G26/$E$41 -> 0.0053475936 | L26: =$H26/$E$41 -> 0.010695187 | N26: =+F26/E26 -> 0.25
B27: 50 | C27: TORRE DE ILUMINACION | G27: =SUMIFS('CONTROL DE RENTAS'!$V$43:$V$336,'CONTROL DE RENTAS'!$AL$43:$AL$336,$B27,'CONTROL DE RENTAS'!$AM$43:$AM$336,$C27,'CONTROL DE RENTAS'!$O$43:$O$336,"DISPONIBLE") -> 0 | J27: =SUM(F28:F28)/$E$41 -> 0.058823529
B28: 50 | C28: 01 | D28: TORRE DE ILUMINACION | E28: =SUMIFS('CONTROL DE RENTAS'!$V$42:$V$336,'CONTROL DE RENTAS'!$AL$42:$AL$336,$B28,'CONTROL DE RENTAS'!$AM$42:$AM$336,$C28) -> 42 | F28: =SUMIFS('CONTROL DE RENTAS'!$V$42:$V$336,'CONTROL DE RENTAS'!$AL$42:$AL$336,$B28,'CONTROL DE RENTAS'!$AM$42:$AM$336,$C28,'CONTROL DE RENTAS'!$O$42:$O$336,"DENTRO") -> 11 | G28: =SUMIFS('CONTROL DE RENTAS'!$V$42:$V$336,'CONTROL DE RENTAS'!$AL$42:$AL$336,$B28,'CONTROL DE RENTAS'!$AM$42:$AM$336,$C28,'CONTROL DE RENTAS'!$O$42:$O$336,"DISPONIBLE") -> 11 | H28: {=SUM(SUMIFS('CONTROL DE RENTAS'!$V$42:$V$336,'CONTROL DE RENTAS'!$AL$42:$AL$336,$B28,'CONTROL DE RENTAS'!$AM$42:$AM$336,$C28,'CONTROL DE RENTAS'!$O$42:$O$336,'RENTABILIDAD GLOBAL'!$B$33:$B$35))} -> 20 | I28: =$E28/$E$41 -> 0.22459893 | J28: =$F28/$E$41 -> 0.058823529 | K28: =$G28/$E$41 -> 0.058823529 | L28: =$H28/$E$41 -> 0.10695187 | N28: =+F28/E28 -> 0.26190476
B29: 60 | C29: GENERADORES | G29: =SUMIFS('CONTROL DE RENTAS'!$V$43:$V$336,'CONTROL DE RENTAS'!$AL$43:$AL$336,$B29,'CONTROL DE RENTAS'!$AM$43:$AM$336,$C29,'CONTROL DE RENTAS'!$O$43:$O$336,"DISPONIBLE") -> 0 | J29: =SUM(F30:F32)/$E$41 -> 0.037433155
B30: 60 | C30: 01 | D30: GENERADOR 25KVA | E30: =SUMIFS('CONTROL DE RENTAS'!$V$42:$V$336,'CONTROL DE RENTAS'!$AL$42:$AL$336,$B30,'CONTROL DE RENTAS'!$AM$42:$AM$336,$C30) -> 1 | F30: =SUMIFS('CONTROL DE RENTAS'!$V$42:$V$336,'CONTROL DE RENTAS'!$AL$42:$AL$336,$B30,'CONTROL DE RENTAS'!$AM$42:$AM$336,$C30,'CONTROL DE RENTAS'!$O$42:$O$336,"DENTRO") -> 1 | G30: =SUMIFS('CONTROL DE RENTAS'!$V$42:$V$336,'CONTROL DE RENTAS'!$AL$42:$AL$336,$B30,'CONTROL DE RENTAS'!$AM$42:$AM$336,$C30,'CONTROL DE RENTAS'!$O$42:$O$336,"DISPONIBLE") -> 0 | H30: {=SUM(SUMIFS('CONTROL DE RENTAS'!$V$42:$V$336,'CONTROL DE RENTAS'!$AL$42:$AL$336,$B30,'CONTROL DE RENTAS'!$AM$42:$AM$336,$C30,'CONTROL DE RENTAS'!$O$42:$O$336,'RENTABILIDAD GLOBAL'!$B$33:$B$35))} -> 0 | I30: =$E30/$E$41 -> 0.0053475936 | J30: =$F30/$E$41 -> 0.0053475936 | K30: =$G30/$E$41 -> 0 | L30: =$H30/$E$41 -> 0 | N30: =+F30/E30 -> 1
B31: 60 | C31: 02 | D31: GENERADOR 45KVA | E31: =SUMIFS('CONTROL DE RENTAS'!$V$42:$V$336,'CONTROL DE RENTAS'!$AL$42:$AL$336,$B31,'CONTROL DE RENTAS'!$AM$42:$AM$336,$C31) -> 11 | F31: =SUMIFS('CONTROL DE RENTAS'!$V$42:$V$336,'CONTROL DE RENTAS'!$AL$42:$AL$336,$B31,'CONTROL DE RENTAS'!$AM$42:$AM$336,$C31,'CONTROL DE RENTAS'!$O$42:$O$336,"DENTRO") -> 4 | G31: =SUMIFS('CONTROL DE RENTAS'!$V$42:$V$336,'CONTROL DE RENTAS'!$AL$42:$AL$336,$B31,'CONTROL DE RENTAS'!$AM$42:$AM$336,$C31,'CONTROL DE RENTAS'!$O$42:$O$336,"DISPONIBLE") -> 7 | H31: {=SUM(SUMIFS('CONTROL DE RENTAS'!$V$42:$V$336,'CONTROL DE RENTAS'!$AL$42:$AL$336,$B31,'CONTROL DE RENTAS'!$AM$42:$AM$336,$C31,'CONTROL DE RENTAS'!$O$42:$O$336,'RENTABILIDAD GLOBAL'!$B$33:$B$35))} -> 0 | I31: =$E31/$E$41 -> 0.058823529 | J31: =$F31/$E$41 -> 0.021390374 | K31: =$G31/$E$41 -> 0.037433155 | L31: =$H31/$E$41 -> 0 | N31: =+F31/E31 -> 0.36363636
B32: 60 | C32: 03 | D32: GENERADOR 100KVA | E32: =SUMIFS('CONTROL DE RENTAS'!$V$42:$V$336,'CONTROL DE RENTAS'!$AL$42:$AL$336,$B32,'CONTROL DE RENTAS'!$AM$42:$AM$336,$C32) -> 5 | F32: =SUMIFS('CONTROL DE RENTAS'!$V$42:$V$336,'CONTROL DE RENTAS'!$AL$42:$AL$336,$B32,'CONTROL DE RENTAS'!$AM$42:$AM$336,$C32,'CONTROL DE RENTAS'!$O$42:$O$336,"DENTRO") -> 2 | G32: =SUMIFS('CONTROL DE RENTAS'!$V$42:$V$336,'CONTROL DE RENTAS'!$AL$42:$AL$336,$B32,'CONTROL DE RENTAS'!$AM$42:$AM$336,$C32,'CONTROL DE RENTAS'!$O$42:$O$336,"DISPONIBLE") -> 3 | H32: {=SUM(SUMIFS('CONTROL DE RENTAS'!$V$42:$V$336,'CONTROL DE RENTAS'!$AL$42:$AL$336,$B32,'CONTROL DE RENTAS'!$AM$42:$AM$336,$C32,'CONTROL DE RENTAS'!$O$42:$O$336,'RENTABILIDAD GLOBAL'!$B$33:$B$35))} -> 0 | I32: =$E32/$E$41 -> 0.026737968 | J32: =$F32/$E$41 -> 0.010695187 | K32: =$G32/$E$41 -> 0.016042781 | L32: =$H32/$E$41 -> 0 | N32: =+F32/E32 -> 0.4
B33: 70 | C33: SOLDADORA | G33: =SUMIFS('CONTROL DE RENTAS'!$V$43:$V$336,'CONTROL DE RENTAS'!$AL$43:$AL$336,$B33,'CONTROL DE RENTAS'!$AM$43:$AM$336,$C33,'CONTROL DE RENTAS'!$O$43:$O$336,"DISPONIBLE") -> 0 | J33: =SUM(F34:F34)/$E$41 -> 0
B34: 70 | C34: 01 | D34: SOLDADORA | E34: =SUMIFS('CONTROL DE RENTAS'!$V$42:$V$336,'CONTROL DE RENTAS'!$AL$42:$AL$336,$B34,'CONTROL DE RENTAS'!$AM$42:$AM$336,$C34) -> 10 | F34: =SUMIFS('CONTROL DE RENTAS'!$V$42:$V$336,'CONTROL DE RENTAS'!$AL$42:$AL$336,$B34,'CONTROL DE RENTAS'!$AM$42:$AM$336,$C34,'CONTROL DE RENTAS'!$O$42:$O$336,"DENTRO") -> 0 | G34: =SUMIFS('CONTROL DE RENTAS'!$V$42:$V$336,'CONTROL DE RENTAS'!$AL$42:$AL$336,$B34,'CONTROL DE RENTAS'!$AM$42:$AM$336,$C34,'CONTROL DE RENTAS'!$O$42:$O$336,"DISPONIBLE") -> 9 | H34: {=SUM(SUMIFS('CONTROL DE RENTAS'!$V$42:$V$336,'CONTROL DE RENTAS'!$AL$42:$AL$336,$B34,'CONTROL DE RENTAS'!$AM$42:$AM$336,$C34,'CONTROL DE RENTAS'!$O$42:$O$336,'RENTABILIDAD GLOBAL'!$B$33:$B$35))} -> 1 | I34: =$E34/$E$41 -> 0.053475936 | J34: =$F34/$E$41 -> 0 | K34: =$G34/$E$41 -> 0.048128342 | L34: =$H34/$E$41 -> 0.0053475936 | N34: =+F34/E34 -> 0
B35: 80 | C35: MANIPULADOR | G35: =SUMIFS('CONTROL DE RENTAS'!$V$43:$V$336,'CONTROL DE RENTAS'!$AL$43:$AL$336,$B35,'CONTROL DE RENTAS'!$AM$43:$AM$336,$C35,'CONTROL DE RENTAS'!$O$43:$O$336,"DISPONIBLE") -> 0 | J35: =SUM(F36:F36)/$E$41 -> 0
B36: 80 | C36: 01 | D36: MANIPULADOR | E36: =SUMIFS('CONTROL DE RENTAS'!$V$42:$V$336,'CONTROL DE RENTAS'!$AL$42:$AL$336,$B36,'CONTROL DE RENTAS'!$AM$42:$AM$336,$C36) -> 0 | F36: =SUMIFS('CONTROL DE RENTAS'!$V$42:$V$336,'CONTROL DE RENTAS'!$AL$42:$AL$336,$B36,'CONTROL DE RENTAS'!$AM$42:$AM$336,$C36,'CONTROL DE RENTAS'!$O$42:$O$336,"DENTRO") -> 0 | G36: =SUMIFS('CONTROL DE RENTAS'!$V$42:$V$336,'CONTROL DE RENTAS'!$AL$42:$AL$336,$B36,'CONTROL DE RENTAS'!$AM$42:$AM$336,$C36,'CONTROL DE RENTAS'!$O$42:$O$336,"DISPONIBLE") -> 0 | H36: {=SUM(SUMIFS('CONTROL DE RENTAS'!$V$42:$V$336,'CONTROL DE RENTAS'!$AL$42:$AL$336,$B36,'CONTROL DE RENTAS'!$AM$42:$AM$336,$C36,'CONTROL DE RENTAS'!$O$42:$O$336,'RENTABILIDAD GLOBAL'!$B$33:$B$35))} -> 0 | I36: =$E36/$E$41 -> 0 | J36: =$F36/$E$41 -> 0 | K36: =$G36/$E$41 -> 0 | L36: =$H36/$E$41 -> 0 | N36: 0
B37: 90 | C37: MONTACARGAS | G37: =SUMIFS('CONTROL DE RENTAS'!$V$43:$V$336,'CONTROL DE RENTAS'!$AL$43:$AL$336,$B37,'CONTROL DE RENTAS'!$AM$43:$AM$336,$C37,'CONTROL DE RENTAS'!$O$43:$O$336,"DISPONIBLE") -> 0 | J37: =SUM(F38:F40)/$E$41 -> 0.016042781
B38: 90 | C38: 01 | D38: 5 MIL LIBRAS | E38: =SUMIFS('CONTROL DE RENTAS'!$V$42:$V$336,'CONTROL DE RENTAS'!$AL$42:$AL$336,$B38,'CONTROL DE RENTAS'!$AM$42:$AM$336,$C38) -> 0 | F38: =SUMIFS('CONTROL DE RENTAS'!$V$42:$V$336,'CONTROL DE RENTAS'!$AL$42:$AL$336,$B38,'CONTROL DE RENTAS'!$AM$42:$AM$336,$C38,'CONTROL DE RENTAS'!$O$42:$O$336,"DENTRO") -> 0 | G38: =SUMIFS('CONTROL DE RENTAS'!$V$42:$V$336,'CONTROL DE RENTAS'!$AL$42:$AL$336,$B38,'CONTROL DE RENTAS'!$AM$42:$AM$336,$C38,'CONTROL DE RENTAS'!$O$42:$O$336,"DISPONIBLE") -> 0 | H38: {=SUM(SUMIFS('CONTROL DE RENTAS'!$V$42:$V$336,'CONTROL DE RENTAS'!$AL$42:$AL$336,$B38,'CONTROL DE RENTAS'!$AM$42:$AM$336,$C38,'CONTROL DE RENTAS'!$O$42:$O$336,'RENTABILIDAD GLOBAL'!$B$33:$B$35))} -> 0 | I38: =$E38/$E$41 -> 0 | J38: =$F38/$E$41 -> 0 | K38: =$G38/$E$41 -> 0 | L38: =$H38/$E$41 -> 0 | N38: =+F38/E38 -> #DIV/0!
B39: 90 | C39: 02 | D39: 7 MIL LIBRAS | E39: =SUMIFS('CONTROL DE RENTAS'!$V$42:$V$336,'CONTROL DE RENTAS'!$AL$42:$AL$336,$B39,'CONTROL DE RENTAS'!$AM$42:$AM$336,$C39) -> 1 | F39: =SUMIFS('CONTROL DE RENTAS'!$V$42:$V$336,'CONTROL DE RENTAS'!$AL$42:$AL$336,$B39,'CONTROL DE RENTAS'!$AM$42:$AM$336,$C39,'CONTROL DE RENTAS'!$O$42:$O$336,"DENTRO") -> 1 | G39: =SUMIFS('CONTROL DE RENTAS'!$V$42:$V$336,'CONTROL DE RENTAS'!$AL$42:$AL$336,$B39,'CONTROL DE RENTAS'!$AM$42:$AM$336,$C39,'CONTROL DE RENTAS'!$O$42:$O$336,"DISPONIBLE") -> 0 | H39: {=SUM(SUMIFS('CONTROL DE RENTAS'!$V$42:$V$336,'CONTROL DE RENTAS'!$AL$42:$AL$336,$B39,'CONTROL DE RENTAS'!$AM$42:$AM$336,$C39,'CONTROL DE RENTAS'!$O$42:$O$336,'RENTABILIDAD GLOBAL'!$B$33:$B$35))} -> 0 | I39: =$E39/$E$41 -> 0.0053475936 | J39: =$F39/$E$41 -> 0.0053475936 | K39: =$G39/$E$41 -> 0 | L39: =$H39/$E$41 -> 0 | N39: =+F39/E39 -> 1
B40: 90 | C40: 03 | D40: 8 MIL LIBRAS | E40: =SUMIFS('CONTROL DE RENTAS'!$V$42:$V$336,'CONTROL DE RENTAS'!$AL$42:$AL$336,$B40,'CONTROL DE RENTAS'!$AM$42:$AM$336,$C40) -> 3 | F40: =SUMIFS('CONTROL DE RENTAS'!$V$42:$V$336,'CONTROL DE RENTAS'!$AL$42:$AL$336,$B40,'CONTROL DE RENTAS'!$AM$42:$AM$336,$C40,'CONTROL DE RENTAS'!$O$42:$O$336,"DENTRO") -> 2 | G40: =SUMIFS('CONTROL DE RENTAS'!$V$42:$V$336,'CONTROL DE RENTAS'!$AL$42:$AL$336,$B40,'CONTROL DE RENTAS'!$AM$42:$AM$336,$C40,'CONTROL DE RENTAS'!$O$42:$O$336,"DISPONIBLE") -> 1 | H40: {=SUM(SUMIFS('CONTROL DE RENTAS'!$V$42:$V$336,'CONTROL DE RENTAS'!$AL$42:$AL$336,$B40,'CONTROL DE RENTAS'!$AM$42:$AM$336,$C40,'CONTROL DE RENTAS'!$O$42:$O$336,'RENTABILIDAD GLOBAL'!$B$33:$B$35))} -> 0 | I40: =$E40/$E$41 -> 0.016042781 | J40: =$F40/$E$41 -> 0.010695187 | K40: =$G40/$E$41 -> 0.0053475936 | L40: =$H40/$E$41 -> 0 | N40: =+F40/E40 -> 0.66666667
E41: =SUM(E5:E40) -> 187 | F41: =SUM(F5:F40) -> 90 | G41: =SUM(G5:G40) -> 52 | H41: =SUM(H5:H40) -> 45 | I41: =SUM(I5:I40) -> 1 | J41: =J4+J15+J18+J24+J27+J29+J33+J35+J37 -> 0.48128342 | K41: =SUM(K5:K40) -> 0.27807487 | L41: =SUM(L5:L40) -> 0.24064171

Sheet ETIQUETAS
A1: NEGOCIACION
B2: #5491
A3: CLIENTE
B4: PAJ PINTURAS
A8: EQUIPO
B9: PLATAFORMA ARTICULADA DE COMBUSTION
A14: NUMERO | B14: #182
A15: ECONOMICO
A19: PROVEEDOR
B20: COMYMAQ
A23: PERIODO | B23: DEL 16 DE ABRIL AL 13 DE MAYO DEL 2025
C32: .
